Workbook

Sheet Dashboard
A1: DASHBOARD
A4: Constituency Battlefield Class | B4: Seats
A5: Stronghold | B5: =COUNTIF('117 Battles '!$F$4:$F$120, A5) -> 22
A6: Lean | B6: =COUNTIF('117 Battles '!$F$4:$F$120, A6) -> 20
A7: Battleground | B7: =COUNTIF('117 Battles '!$F$4:$F$120, A7) -> 26
A8: Opposition Lean | B8: =COUNTIF('117 Battles '!$F$4:$F$120, A8) -> 20
A9: Highly Volatile | B9: =COUNTIF('117 Battles '!$F$4:$F$120, A9) -> 29
A11: 2027 Party-wise Strategic Posture as of September 2026
A12: Party | B12: Defend | C12: Battleground | D12: Expand | E12: Long Shot
B13: Party currently has a meaningful position/hold that needs protecting | C13: Party has a credible competitive pathway | D13: Opposition held seat where evidence suggests potential growth | E13: Current evidence does not show a strong near term pathway
A14: AAP | B14: {=COUNTIF(INDEX('117 Battles '!$T$4:$W$120, 0, MATCH($A14, {"AAP","INC","SAD","BJP"}, 0)), B$12)} -> 27 | C14: {=COUNTIF(INDEX('117 Battles '!$T$4:$W$120, 0, MATCH($A14, {"AAP","INC","SAD","BJP"}, 0)), C$12)} -> 72 | D14: {=COUNTIF(INDEX('117 Battles '!$T$4:$W$120, 0, MATCH($A14, {"AAP","INC","SAD","BJP"}, 0)), D$12)} -> 7 | E14: {=COUNTIF(INDEX('117 Battles '!$T$4:$W$120, 0, MATCH($A14, {"AAP","INC","SAD","BJP"}, 0)), E$12)} -> 11
A15: INC | B15: {=COUNTIF(INDEX('117 Battles '!$T$4:$W$120, 0, MATCH($A15, {"AAP","INC","SAD","BJP"}, 0)), B$12)} -> 11 | C15: {=COUNTIF(INDEX('117 Battles '!$T$4:$W$120, 0, MATCH($A15, {"AAP","INC","SAD","BJP"}, 0)), C$12)} -> 39 | D15: {=COUNTIF(INDEX('117 Battles '!$T$4:$W$120, 0, MATCH($A15, {"AAP","INC","SAD","BJP"}, 0)), D$12)} -> 28 | E15: {=COUNTIF(INDEX('117 Battles '!$T$4:$W$120, 0, MATCH($A15, {"AAP","INC","SAD","BJP"}, 0)), E$12)} -> 39
A16: SAD | B16: {=COUNTIF(INDEX('117 Battles '!$T$4:$W$120, 0, MATCH($A16, {"AAP","INC","SAD","BJP"}, 0)), B$12)} -> 1 | C16: {=COUNTIF(INDEX('117 Battles '!$T$4:$W$120, 0, MATCH($A16, {"AAP","INC","SAD","BJP"}, 0)), C$12)} -> 28 | D16: {=COUNTIF(INDEX('117 Battles '!$T$4:$W$120, 0, MATCH($A16, {"AAP","INC","SAD","BJP"}, 0)), D$12)} -> 20 | E16: {=COUNTIF(INDEX('117 Battles '!$T$4:$W$120, 0, MATCH($A16, {"AAP","INC","SAD","BJP"}, 0)), E$12)} -> 68
A17: BJP | B17: {=COUNTIF(INDEX('117 Battles '!$T$4:$W$120, 0, MATCH($A17, {"AAP","INC","SAD","BJP"}, 0)), B$12)} -> 2 | C17: {=COUNTIF(INDEX('117 Battles '!$T$4:$W$120, 0, MATCH($A17, {"AAP","INC","SAD","BJP"}, 0)), C$12)} -> 8 | D17: {=COUNTIF(INDEX('117 Battles '!$T$4:$W$120, 0, MATCH($A17, {"AAP","INC","SAD","BJP"}, 0)), D$12)} -> 14 | E17: {=COUNTIF(INDEX('117 Battles '!$T$4:$W$120, 0, MATCH($A17, {"AAP","INC","SAD","BJP"}, 0)), E$12)} -> 93
A19: Party | B19: Core Strategic Problem | C19: Priority Actionables
A20: AAP | B20: Protect a very large but exposed incumbent footprint | C20: Governance delivery Candidate correction Manage internal rebellion Protect Malwa organisational strength Track high-risk seats
A21: INC | B21: Convert opposition opportunity into Assembly seats | C21: Resolve factionalism Build Malwa organisation Candidate-first seat planning Activate booth network Present concrete policy alternatives
A22: BJP | B22: Convert expanded vote presence into constituencies | C22: Build seat-level organisation Expand rural credibility Integrate new recruits Clarify alliance structure Strengthen Punjab-specific leadership
A23: SAD | B23: Rebuild credibility and electoral relevance | C23: Political renewal Stabilise cadre/candidates Manage Panthic fragmentation Clarify alliance strategy Rebuild urban complement
A24: Emerging | B24: Convert local influence into durable organisation | C24: Concentrate on organisational depth Credible candidates Formalise structures Demonstrate multi-seat scalability
A27: Structural indicator | B27: AAP | C27: INC | D27: SAD | E27: BJP
A28: Phase 4 equal-weight analyst score /10 | B28: =ROUND(AVERAGE((B29/117)*10,(B30/117)*10,(B31/13)*10,(B32/40)*10,(B33/SUM($B$33:$E$33))*10,(B34/SUM($B$34:$E$34))*10) + 2.17, 2) -> 8.35 | C28: =ROUND(AVERAGE((C29/117)*10,(C30/117)*10,(C31/13)*10,(C32/40)*10,(C33/SUM($B$33:$E$33))*10,(C34/SUM($B$34:$E$34))*10) + 2.17, 2) -> 5.31 | D28: =ROUND(AVERAGE((D29/117)*10,(D30/117)*10,(D31/13)*10,(D32/40)*10,(D33/SUM($B$33:$E$33))*10,(D34/SUM($B$34:$E$34))*10) + 2.17, 2) -> 3.33 | E28: =ROUND(AVERAGE((E29/117)*10,(E30/117)*10,(E31/13)*10,(E32/40)*10,(E33/SUM($B$33:$E$33))*10,(E34/SUM($B$34:$E$34))*10) + 2.17, 2) -> 3.2
A29: Formal Assembly MLAs | B29: 94 | C29: 16 | D29: 3 | E29: 2
A30: Current aligned seats used | B30: 95 | C30: 16 | D30: 1 | E30: 2
A31: 2024 LS seats (diagnostic) | B31: 3 | C31: 7 | D31: 1 | E31: 0
A32: 2024 LS vote share % (diagnostic) | B32: 26.02 | C32: 26.3 | D32: 13.42 | E32: 18.56
A33: 2025 Zila Parishad zones | B33: 218 | C33: 62 | D33: 46 | E33: 7
A34: May 2026 civic wards | B34: 958 | C34: 397 | D34: 192 | E34: 172
A37: Assembly 2017,2022 - Taken as Main LokSabha 2019, 2024 - Mid-term stress testing
A40: Category | B40: Tab Name | C40: Description & Scope
A41: Constituency Analysis | B41: 117 Battles | C41: Comprehensive seat-by-seat classification, challenger scores, and party dynamics across all 117 ACs Seat strength and projections
A42: Constituency Analysis | B42: Top Battlegrounds | C42: Deep dive into the 20 most competitive seats, margins, and key local drivers
A43: Constituency Analysis | B43: Assembly Competitiveness | C43: Assembly Competitiveness Index (ACI), closeness metrics, and margin turbulence
A44: Constituency Analysis | B44: Assembly Volatality | C44: Electoral Volatility Index (AVI), turnover scores, and seat volatility classification
A45: Constituency Analysis | B45: Assembly Trajectories | C45: Historical trajectory comparison across 2017 & 2022 AE vs 2019 & 2024 LS
A46: Strategic Assessment | B46: Party wise Performance | C46: Historical election performance, vote shares, seat shares, and swings
A47: Strategic Assessment | B47: Party Social Coalitions | C47: Social base, caste matrix, and coalition breakdown across major political parties
A48: Strategic Assessment | B48: Political Geography | C48: Regional breakdown across Malwa, Majha, Doaba, Urban, and Rural Punjab
A49: Strategic Assessment | B49: Voter Groups | C49: Key demographic and socio-economic voter segments, concerns, and party alignment
A50: Strategic Assessment | B50: Issues | C50: Salience, severity, and political risk mapping of key state and local issues
A51: Strategic Assessment | B51: Final Assesment | C51: Strategic SWOT, paths to victory, and structural party classifications for 2027
... A70: Strategic Posture | B70: Classification showing how a party should approach a seat: Defend, Battleground, Expand or Long Shot. | C70: A vulnerable seat already held by a party may be classified as Defend, while a winnable opposition-held seat may be Expand.

Sheet Final Assesment
A1: PUNJAB 2027 FINAL ASSESSMENT
A2: EARLY 2027 STRUCTURAL CLASSIFICATION
A3: Party/Force | B3: Classification | C3: Evidence for classification | D3: Structural advantage | E3: Structural disadvantage | F3: What would upgrade classification | G3: What would downgrade classification | H3: Confidence
A4: AAP | B4: Frontrunner (structural) | C4: 94 formal MLAs,strongest recent local-body performance,Mann,welfare and statewide organisation;2024 LS correction secondary. | D4: Incumbency + ground network + largest current Assembly base | E4: High-salience governance burden and coalition erosion; ticket/elite issues | F4: Sustained Assembly polling lead + welfare satisfaction + Malwa retention evidence | G4: Broad anti-incumbency + Congress consolidation + Malwa erosion | H4: Medium-High
A5: INC | B5: Strong Challenger | C5: 16 MLAs,deep candidate/organisation network and current Congress coordination effort;7 MPs/37 LS segments secondary parliamentary evidence. | D5: Broad social/regional acceptability and experienced candidates | E5: Factionalism; only16 MLAs and huge Malwa gap from2022 | F5: Leadership unity + strong Malwa polling/organisation | G5: Factional split/rebels + BJP/SAD/WPD fragment anti-AAP vote | H5: Medium-High
A6: BJP | B6: Competitive / Expanding | C6: 2 MLAs,expanding civic/urban+booth network,new recruits;18.56% LS/23 segments secondary diagnostics. | D6: Largest expansion headroom and national resources | E6: Rural/Sikh/farmer ceiling and vote concentration | F6: Strong rural candidates/polling + Assembly conversion in mixed seats | G6: Rural rejection persists and Centre-farmer/federal issues dominate | H6: Medium
A7: SAD | B7: Recovering Regional Force | C7: 3 formal MLAs but narrower aligned footprint;rural local-body residue,Bathinda/Panthic networks;2024 LS weakness secondary. | D7: Historic cadre/regional identity | E7: 13.42% LS vote, defections, Badal/sacrilege baggage, WPD competition | F7: Vote stabilisation + leader/cadre returns + credible reform/alliance clarity | G7: More defections + WPD scales + rural vote shifts to INC/AAP | H7: Medium
A8: BSP | B8: Regional / Niche Spoiler | C8: Distinct Doaba/social-justice cadre,1 MLA and local organisation;LS evidence secondary. | D8: Ideological/cadre distinctiveness in selected SC-heavy seats | E8: Low recent statewide conversion and heterogeneous Dalit vote | F8: Strong candidates + measurable Doaba vote growth | G8: Continued low single-digit share and tactical shift to larger parties | H8: Medium
A9: WPD / Panthic Independents | B9: Emerging Regional Force / Spoiler | C9: Two independent MPs+Panthic/candidate networks;15 LS segments disruption diagnostic,not statewide AE baseline. | D9: Authentic alternative Panthic/candidate energy | E9: Registration/organisation/scalability and legal/personal constraints | F9: Formal organisation + credible multi-district candidates + issue breadth | G9: Support stays personal/local and factions split | H9: Low-Medium statewide / High local
A15: FINAL PARTY MATRIX
A16: Party | B16: Base | C16: Must Retain | D16: Growth Opportunity | E16: Biggest Threat | F16: Key Region | G16: Key Political Problem | H16: Path to Victory
A17: AAP | B17: Large Assembly/local-body base; 2022 cross-group coalition; welfare; Mann | C17: Malwa + sufficient Doaba/Majha + organisational incumbency | D17: Recover 2024-adverse seats through Assembly reversion/candidate reset; exploit opposition fragmentation | E17: Cross-group anti-incumbency consolidation and multiple local rebellions | F17: Malwa | G17: Convert incumbency from liability into delivery credibility while managing jobs/drugs/farmer/law-order grievances | H17: Contain losses from current94 formal seats, preserve broad-enough coalition and prevent one opposition pole from dominating.
A18: INC | B18: Majha/Doaba parliamentary strength; broad anti-AAP coalition; candidate bench | C18: 2024 MPs/segments, current MLAs, OBC/Dalit/candidate coalition | D18: Large Malwa conversion from AAP-held Assembly-first competitive seats | E18: Factionalism and BJP/SAD/WPD splitting opposition | F18: Malwa | G18: Turn broad but distributed leadership into one campaign and one ticket machine | H18: Retain Majha/Doaba + make major Malwa gains + become principal anti-AAP option.
A19: SAD | B19: Residual rural/Panthic/Jat Sikh cadre and Bathinda-Malwa networks | C19: Existing cadre/pockets and remaining trust | D19: AAP rural dissatisfaction; lower winning thresholds; possible alliance complement | E19: WPD/Panthic fragmentation, Badal legacy, defections and urban loss to BJP | F19: Malwa | G19: Re-establish why SAD is uniquely relevant before asking voters to return | H19: Restore credibility/core, add a non-core/urban leg, rebuild Malwa seat conversion and reduce splinter competition.
A20: BJP | B20: Urban Hindu/trader/MSME core;2024 standalone voters; national resources | C20: Urban core and new recruits | D20: Test whether2024 urban/parliamentary support can be reproduced in Assembly contests through viable local candidates,booths and mixed-seat coalitions. | E20: Rural/Sikh/farmer ceiling; Centre-state/federal liabilities; vote concentration | F20: Urban nodes across all three regions, then rural bridge | G20: Turn a high but concentrated vote into constituency-scale coalitions | H20: Convert urban base → build local candidates/booths → gain enough rural/Sikh credibility → exploit multi-cornered pluralities.
A21: BSP | B21: Doaba cadre/social-justice pockets | C21: Core organisation and viable SC-heavy seats | D21: Selective reserved-seat growth | E21: Low conversion, tactical voting to larger parties | F21: Doaba | G21: Translate distinct identity into credible local candidates, not demographic arithmetic | H21: Build multiple seat wins and broader coalition first; current evidence is not government-scale.
A22: WPD / Emerging | B22: Khadoor/Faridkot/selected Panthic networks; personal mandates | C22: Candidate strongholds and organisational nodes | D22: SAD weakness/Panthic vacuum and high-volatility seats | E22: Personality dependence, registration/scalability, mutual fragmentation | F22: Majha first; selected Malwa area | G22: Build an organisation and governance proposition larger than individual leaders | H22: Formalise → field credible multi-seat slate → broaden beyond Panthic protest; government-scale path remains unproven.
A29: No. | B29: DATA | C29: TREND | D29: WHY | E29: WHO / WHERE | F29: ELECTORAL IMPACT | G29: 2027 IMPLICATION
A30: 1 | B30: AAP:92 Assembly seats in2022; only33 LS-segment leads in2024; then strong2025/26 local-body performance. | C30: AAP's coalition weakened at parliamentary level but organisation did not collapse. | D30: 2022 was a broad change wave;2024 fragmented that coalition across INC/BJP/IND/SAD, while sub-state incumbency networks remained intact. | E30: Malwa AAP base; Majha warning; Doaba competitive; welfare/local-office-holder networks statewide. | F30: LS swing cannot be directly projected onto Assembly seats. | G30: The key AAP question is coalition retention and Assembly-vs-LS reversion-not whether2024 erased2022.
A31: 2 | B31: INC:77 seats2017 →18 in2022 →7 MPs/37 LS-segment leads2024. | C31: Congress can collapse and recover quickly because its support is broad but leadership/candidate dependent. | D31: Amarinder anchored2017/19; factional churn hurt2022; strong candidates and broad social acceptability aided2024. | E31: Majha/Doaba strongest; Malwa is growth frontier. | F31: Congress has the clearest opposition government path but also the largest organisational conversion challenge. | G31: Watch unity and Malwa seat-level organisation more than national/statewide vote share alone.
A32: 3 | B32: Malwa contains69/117 seats; AAP won66 in2022 but led24 LS segments2024. | C32: Punjab's largest region moved from AAP near-monopoly to multi-party fragmentation. | D32: Mann/change/farm-youth coalition drove2022; Congress/SAD/BJP/IND regained different pockets in2024. | E32: Rural farmer/labour/youth seats plus Ludhiana/Bathinda/Abohar urban-industrial nodes. | F32: A small regional movement can change dozens of Assembly seats. | G32: No party forms a stable majority coalition without a serious Malwa strategy.
A33: 4 | B33: Majha2024 LS segments: INC10, BJP6, IND6, AAP2, SAD1. | C33: Majha is the most politically fragmented region. | D33: Border/security, Panthic politics, farm issues, urban Hindu pockets and candidate networks activate differently by election type. | E33: Amritsar-Gurdaspur-Tarn Taran/Pathankot belt. | F33: Statewide swings can break into four/five different local contests here. | G33: Majha is the best stress-test for any claim of a simple statewide wave.
A34: 5 | B34: Assembly:AAP23.72%2017→42.01%2022. Parliamentary diagnostic:7.38%2019→26.02%2024. | C34: Election-type movement can differ radically. | D34: 2019 weak AAP LS preceded2022 Assembly landslide;2024 therefore cannot be read as2027 seat map. | E34: Statewide;especially AAP-held seats where2024 differed. | F34: LS identifies coalition stress,not Assembly vulnerability by itself. | G34: Build2027 from2022/current Assembly evidence,then use2024 to ask where coalition stressed.
A35: 6 | B35: Assembly:SAD25.24%2017→18.38%2022. Parliamentary diagnostic:27.45%2019→13.42%2024; rural local-body footprint persists. | C35: SAD weakened in both election types but organisation has not disappeared. | D35: Assembly decline,credibility costs,lost BJP complement and Panthic fragmentation. | E35: Bathinda-Malwa rural/Panthic pockets. | F35: Can affect close seats without statewide-power scale. | G35: Track Assembly/current cadre conversion and WPD competition.
A36: 7 | B36: Assembly:BJP5.39%2017→6.60%2022. Parliamentary diagnostic:9.63%2019 alliance-limited→18.56%2024 standalone. | C36: Parliamentary expansion faster than Assembly conversion. | D36: Alliance structure changed and support remains urban/semiurban concentrated. | E36: Urban nodes across three regions. | F36: High LS vote can yield few MLAs if candidates/rural reach weak. | G36: Measure Assembly viability through runner-up position,ACI/AVI,civic/booth strength and rural bridge.
A37: 8 | B37: Two independent MPs +15 independent-led LS segments in2024; WPD later gained Ayali and district/youth structures. | C37: Panthic protest now has an electoral channel outside SAD. | D37: SAD credibility crisis created a vacuum; charismatic candidates converted it locally. | E37: Khadoor/Tarn Taran/Faridkot and selected Malwa. | F37: Emerging candidates can change margins and issue salience even with limited statewide organisation. | G37: The question is scalability: candidate mandates must become booths, candidates and a broader governance agenda.
A38: 9 | B38: Youth unemployment22.3% Apr-Jun2026; migration widespread; drugs/farmer/law-order remain high salience; AAP welfare remains large. | C38: 2027 can simultaneously contain anti-incumbency and beneficiary retention. | D38: Households evaluate multiple issues; Centre/state blame is split; material welfare can coexist with dissatisfaction. | E38: Youth, farm households, women, employees, urban business and migration-linked families statewide. | F38: No single issue guarantees a uniform swing; issue mix determines which coalition component moves. | G38: War room should track issue attribution and beneficiary satisfaction, not just issue importance.
A39: 10 | B39: Revised Phase5 model now weights 2022 Assembly/current Assembly evidence far above 2019/2024 Lok Sabha signals. | C39: Seat intelligence shifts from four-election chronology to election-type relevance. | D39: 2019 showed that a weak LS result can be followed by an Assembly landslide; 2024 is better interpreted as coalition fragmentation/stress rather than an Assembly seat map. | E39: All117 seats, especially AAP-held seats where 2024 LS pointed elsewhere. | F39: Candidate, incumbency, organisation and Assembly-specific voter return become more important than parliamentary segment leads. | G39: Use 2019 for history, 2024 for coalition stress, and build the 2027 battlefield primarily from 2022 Assembly + current organisation/issues + recent Assembly tests.

Sheet 117 Battles 
A1: 2027 BATTLEFIELD MAP
A2: What each category means: Stronghold: Safe, dominant seat. The incumbent party has won consistently with wide margins and low competition. Lean: Incumbent holds an advantage, with low-to-moderate competition and steady support. Battleground: Evenly balanced contest / toss-up where neither party has a clear structural buffer. Opposition Lean: The incumbent is under severe pressure; the primary challenger has won multiple recent elections here. Highly Volatile: Unstable seat with frequent party turnovers across election cycles or sharp voter swings. Example: Sujanpur Result: Opposition Lean (Incumbent INC faces strong challenger BJP, who won the 2017 Assembly and 2024 Lok Sabha segment).
A3: AC | B3: Seat | C3: District | D3: Region | E3: Current incumbent | F3: Classification | G3: Current | H3: 2017 AE | I3: 2022 AE | J3: 2019 LS Historical | K3: 2024 LS Diagnostic | L3: Recent Assembly Update | M3: 2022 Runner-up | N3: 2022 Margin% | O3: ACI | P3: AVI | Q3: Combined | R3: Primary Challenger | S3: 2024 Stress? | T3: AAP | U3: INC | V3: SAD | W3: BJP | X3: Multi-cornered
A4: 1 | B4: Sujanpur | C4: Pathankot | D4: Majha | E4: Naresh Puri | F4: =IFS(OR(P4>=75, ((H4<>J4)+(J4<>I4)+(I4<>K4))>=3), "Highly Volatile", AND(COUNTIF(H4:K4, G4)+1>=4, O4<55, P4<65), "Stronghold", AND(COUNTIF(H4:K4, G4)+1>=3, O4<70, P4<75), "Lean", AND(R4<>G4, ((H4=R4)+(J4=R4)+(K4=R4))>=2, O4<60, P4<70), "Opposition Lean", TRUE, "Battleground") -> Opposition Lean | G4: INC | H4: BJP | I4: INC | J4: BJP | K4: BJP | M4: BJP | N4: 3.61 | O4: {=_xlfn.XLOOKUP(B4, 'Assembly Competitiveness'!$B$4:$B$120,'Assembly Competitiveness'!$O$4:$O$120, "-")} -> 56.4095 | P4: {=_xlfn.XLOOKUP(B4,'Assembly Volatality'!$B$4:$B$120,'Assembly Volatality'!$L$4:$L$120, "-")} -> 53.7 | Q4: =ROUND(0.45*O4+0.4*P4+0.15*IF(H4<>K4,100,0),1) -> 46.9 | R4: BJP | S4: YES | T4: =IFS( AND(G4="AAP", OR(F4="Stronghold", F4="Lean")), "Defend", OR( AND(G4="AAP", OR(F4="Battleground", F4="Highly Volatile", F4="Opposition Lean")), AND(R4="AAP", OR(F4="Battleground", F4="Highly Volatile", F4="Opposition Lean")) ), "Battleground", OR(K4="AAP", M4="AAP", R4="AAP"), "Expand", TRUE, "Long Shot" ) -> Long Shot | U4: =IFS( AND(G4="INC", OR(F4="Stronghold", F4="Lean")), "Defend", OR( AND(G4="INC", OR(F4="Battleground", F4="Highly Volatile", F4="Opposition Lean")), AND(R4="INC", OR(F4="Battleground", F4="Highly Volatile", F4="Opposition Lean")) ), "Battleground", OR(K4="INC", M4="INC", R4="INC"), "Expand", TRUE, "Long Shot" ) -> Battleground | V4: =IFS( AND(G4="SAD", OR(F4="Stronghold", F4="Lean")), "Defend", OR( AND(G4="SAD", OR(F4="Battleground", F4="Highly Volatile", F4="Opposition Lean")), AND(R4="SAD", OR(F4="Battleground", F4="Highly Volatile", F4="Opposition Lean")) ), "Battleground", OR(K4="SAD", M4="SAD", R4="SAD"), "Expand", TRUE, "Long Shot" ) -> Long Shot | W4: =IFS( AND(G4="BJP", OR(F4="Stronghold", F4="Lean")), "Defend", OR( AND(G4="BJP", OR(F4="Battleground", F4="Highly Volatile", F4="Opposition Lean")), AND(R4="BJP", OR(F4="Battleground", F4="Highly Volatile", F4="Opposition Lean")) ), "Battleground", OR(K4="BJP", M4="BJP", R4="BJP"), "Expand", TRUE, "Long Shot" ) -> Battleground | X4: =IFS(K4="EMERGING", "YES", COUNTIFS(T4:W4, "<>Long Shot", T4:W4, "<>") >= 3, "YES", TRUE, "")
A5: 2 | B5: Bhoa | C5: Pathankot | D5: Majha | E5: Lal Chand | F5: =IFS( OR(P5>=75, ((H5<>J5)+(J5<>I5)+(I5<>K5))>=3), "Highly Volatile", AND(COUNTIF(H5:K5, G5)+1>=4, O5<55, P5<65), "Stronghold", AND(COUNTIF(H5:K5, G5)+1>=3, O5<70, P5<75), "Lean", AND(R5<>G5, ((H5=R5)+(J5=R5)+(K5=R5))>=2, O5<60, P5<70), "Opposition Lean", TRUE, "Battleground" ) -> Highly Volatile | G5: AAP | H5: INC | I5: AAP | J5: BJP | K5: BJP | M5: INC | N5: 0.88 | O5: {=_xlfn.XLOOKUP(B5, 'Assembly Competitiveness'!$B$4:$B$120,'Assembly Competitiveness'!$O$4:$O$120, "-")} -> 61.088 | P5: {=_xlfn.XLOOKUP(B5,'Assembly Volatality'!$B$4:$B$120,'Assembly Volatality'!$L$4:$L$120, "-")} -> 61.5 | Q5: =ROUND(0.45*O5+0.4*P5+0.15*IF(H5<>K5,100,0),1) -> 67.1 | R5: INC | S5: YES | T5: =IFS( AND(G5="AAP", OR(F5="Stronghold", F5="Lean")), "Defend", OR( AND(G5="AAP", OR(F5="Battleground", F5="Highly Volatile", F5="Opposition Lean")), AND(R5="AAP", OR(F5="Battleground", F5="Highly Volatile", F5="Opposition Lean")) ), "Battleground", OR(K5="AAP", M5="AAP", R5="AAP"), "Expand", TRUE, "Long Shot" ) -> Battleground | U5: =IFS( AND(G5="INC", OR(F5="Stronghold", F5="Lean")), "Defend", OR( AND(G5="INC", OR(F5="Battleground", F5="Highly Volatile", F5="Opposition Lean")), AND(R5="INC", OR(F5="Battleground", F5="Highly Volatile", F5="Opposition Lean")) ), "Battleground", OR(K5="INC", M5="INC", R5="INC"), "Expand", TRUE, "Long Shot" ) -> Battleground | V5: =IFS( AND(G5="SAD", OR(F5="Stronghold", F5="Lean")), "Defend", OR( AND(G5="SAD", OR(F5="Battleground", F5="Highly Volatile", F5="Opposition Lean")), AND(R5="SAD", OR(F5="Battleground", F5="Highly Volatile", F5="Opposition Lean")) ), "Battleground", OR(K5="SAD", M5="SAD", R5="SAD"), "Expand", TRUE, "Long Shot" ) -> Long Shot | W5: =IFS( AND(G5="BJP", OR(F5="Stronghold", F5="Lean")), "Defend", OR( AND(G5="BJP", OR(F5="Battleground", F5="Highly Volatile", F5="Opposition Lean")), AND(R5="BJP", OR(F5="Battleground", F5="Highly Volatile", F5="Opposition Lean")) ), "Battleground", OR(K5="BJP", M5="BJP", R5="BJP"), "Expand", TRUE, "Long Shot" ) -> Expand | X5: =IFS(K5="EMERGING", "YES", COUNTIFS(T5:W5, "<>Long Shot", T5:W5, "<>") >= 3, "YES", TRUE, "") -> YES
A6: 3 | B6: Pathankot | C6: Pathankot | D6: Majha | E6: Ashwani Kumar Sharma | F6: =IFS( OR(P6>=75, ((H6<>J6)+(J6<>I6)+(I6<>K6))>=3), "Highly Volatile", AND(COUNTIF(H6:K6, G6)+1>=4, O6<55, P6<65), "Stronghold", AND(COUNTIF(H6:K6, G6)+1>=3, O6<70, P6<75), "Lean", AND(R6<>G6, ((H6=R6)+(J6=R6)+(K6=R6))>=2, O6<60, P6<70), "Opposition Lean", TRUE, "Battleground" ) -> Stronghold | G6: BJP | H6: INC | I6: BJP | J6: BJP | K6: BJP | M6: INC | N6: 6.88 | O6: {=_xlfn.XLOOKUP(B6, 'Assembly Competitiveness'!$B$4:$B$120,'Assembly Competitiveness'!$O$4:$O$120, "-")} -> 40.672 | P6: {=_xlfn.XLOOKUP(B6,'Assembly Volatality'!$B$4:$B$120,'Assembly Volatality'!$L$4:$L$120, "-")} -> 34.97 | Q6: =ROUND(0.45*O6+0.4*P6+0.15*IF(H6<>K6,100,0),1) -> 47.3 | R6: INC | T6: =IFS(AND(G6="AAP", OR(F6="Stronghold", F6="Lean")), "Defend", OR( AND(G6="AAP", OR(F6="Battleground", F6="Highly Volatile", F6="Opposition Lean")),AND(R6="AAP", OR(F6="Battleground", F6="Highly Volatile", F6="Opposition Lean"))), "Battleground", OR(K6="AAP", M6="AAP", R6="AAP"), "Expand", TRUE, "Long Shot") -> Long Shot | U6: =IFS( AND(G6="INC", OR(F6="Stronghold", F6="Lean")), "Defend", OR( AND(G6="INC", OR(F6="Battleground", F6="Highly Volatile", F6="Opposition Lean")), AND(R6="INC", OR(F6="Battleground", F6="Highly Volatile", F6="Opposition Lean")) ), "Battleground", OR(K6="INC", M6="INC", R6="INC"), "Expand", TRUE, "Long Shot" ) -> Expand | V6: =IFS( AND(G6="SAD", OR(F6="Stronghold", F6="Lean")), "Defend", OR( AND(G6="SAD", OR(F6="Battleground", F6="Highly Volatile", F6="Opposition Lean")), AND(R6="SAD", OR(F6="Battleground", F6="Highly Volatile", F6="Opposition Lean")) ), "Battleground", OR(K6="SAD", M6="SAD", R6="SAD"), "Expand", TRUE, "Long Shot" ) -> Long Shot | W6: =IFS( AND(G6="BJP", OR(F6="Stronghold", F6="Lean")), "Defend", OR( AND(G6="BJP", OR(F6="Battleground", F6="Highly Volatile", F6="Opposition Lean")), AND(R6="BJP", OR(F6="Battleground", F6="Highly Volatile", F6="Opposition Lean")) ), "Battleground", OR(K6="BJP", M6="BJP", R6="BJP"), "Expand", TRUE, "Long Shot" ) -> Defend | X6: =IFS(K6="EMERGING", "YES", COUNTIFS(T6:W6, "<>Long Shot", T6:W6, "<>") >= 3, "YES", TRUE, "")
A7: 4 | B7: Gurdaspur | C7: Gurdaspur | D7: Majha | E7: Barindermeet Singh Pahra | F7: =IFS( OR(P7>=75, ((H7<>J7)+(J7<>I7)+(I7<>K7))>=3), "Highly Volatile", AND(COUNTIF(H7:K7, G7)+1>=4, O7<55, P7<65), "Stronghold", AND(COUNTIF(H7:K7, G7)+1>=3, O7<70, P7<75), "Lean", AND(R7<>G7, ((H7=R7)+(J7=R7)+(K7=R7))>=2, O7<60, P7<70), "Opposition Lean", TRUE, "Battleground" ) -> Stronghold | G7: INC | H7: INC | I7: INC | J7: BJP | K7: INC | M7: SAD | N7: 5.94 | O7: {=_xlfn.XLOOKUP(B7, 'Assembly Competitiveness'!$B$4:$B$120,'Assembly Competitiveness'!$O$4:$O$120, "-")} -> 39.175 | P7: {=_xlfn.XLOOKUP(B7,'Assembly Volatality'!$B$4:$B$120,'Assembly Volatality'!$L$4:$L$120, "-")} -> 21.72 | Q7: =ROUND(0.45*O7+0.4*P7+0.15*IF(H7<>K7,100,0),1) -> 26.3 | R7: SAD | T7: =IFS( AND(G7="AAP", OR(F7="Stronghold", F7="Lean")), "Defend", OR( AND(G7="AAP", OR(F7="Battleground", F7="Highly Volatile", F7="Opposition Lean")), AND(R7="AAP", OR(F7="Battleground", F7="Highly Volatile", F7="Opposition Lean")) ), "Battleground", OR(K7="AAP", M7="AAP", R7="AAP"), "Expand", TRUE, "Long Shot" ) -> Long Shot | U7: =IFS( AND(G7="INC", OR(F7="Stronghold", F7="Lean")), "Defend", OR( AND(G7="INC", OR(F7="Battleground", F7="Highly Volatile", F7="Opposition Lean")), AND(R7="INC", OR(F7="Battleground", F7="Highly Volatile", F7="Opposition Lean")) ), "Battleground", OR(K7="INC", M7="INC", R7="INC"), "Expand", TRUE, "Long Shot" ) -> Defend | V7: =IFS( AND(G7="SAD", OR(F7="Stronghold", F7="Lean")), "Defend", OR( AND(G7="SAD", OR(F7="Battleground", F7="Highly Volatile", F7="Opposition Lean")), AND(R7="SAD", OR(F7="Battleground", F7="Highly Volatile", F7="Opposition Lean")) ), "Battleground", OR(K7="SAD", M7="SAD", R7="SAD"), "Expand", TRUE, "Long Shot" ) -> Expand | W7: =IFS( AND(G7="BJP", OR(F7="Stronghold", F7="Lean")), "Defend", OR( AND(G7="BJP", OR(F7="Battleground", F7="Highly Volatile", F7="Opposition Lean")), AND(R7="BJP", OR(F7="Battleground", F7="Highly Volatile", F7="Opposition Lean")) ), "Battleground", OR(K7="BJP", M7="BJP", R7="BJP"), "Expand", TRUE, "Long Shot" ) -> Long Shot | X7: =IFS(K7="EMERGING", "YES", COUNTIFS(T7:W7, "<>Long Shot", T7:W7, "<>") >= 3, "YES", TRUE, "")
A8: 5 | B8: Dina Nagar | C8: Gurdaspur | D8: Majha | E8: Aruna Chaudhary | F8: =IFS( OR(P8>=75, ((H8<>J8)+(J8<>I8)+(I8<>K8))>=3), "Highly Volatile", AND(COUNTIF(H8:K8, G8)+1>=4, O8<55, P8<65), "Stronghold", AND(COUNTIF(H8:K8, G8)+1>=3, O8<70, P8<75), "Lean", AND(R8<>G8, ((H8=R8)+(J8=R8)+(K8=R8))>=2, O8<60, P8<70), "Opposition Lean", TRUE, "Battleground" ) -> Stronghold | G8: INC | H8: INC | I8: INC | J8: BJP | K8: INC | M8: AAP | N8: 0.81 | O8: {=_xlfn.XLOOKUP(B8, 'Assembly Competitiveness'!$B$4:$B$120,'Assembly Competitiveness'!$O$4:$O$120, "-")} -> 52.7295 | P8: {=_xlfn.XLOOKUP(B8,'Assembly Volatality'!$B$4:$B$120,'Assembly Volatality'!$L$4:$L$120, "-")} -> 23.98 | Q8: =ROUND(0.45*O8+0.4*P8+0.15*IF(H8<>K8,100,0),1) -> 33.3 | R8: AAP | T8: =IFS( AND(G8="AAP", OR(F8="Stronghold", F8="Lean")), "Defend", OR( AND(G8="AAP", OR(F8="Battleground", F8="Highly Volatile", F8="Opposition Lean")), AND(R8="AAP", OR(F8="Battleground", F8="Highly Volatile", F8="Opposition Lean")) ), "Battleground", OR(K8="AAP", M8="AAP", R8="AAP"), "Expand", TRUE, "Long Shot" ) -> Expand | U8: =IFS( AND(G8="INC", OR(F8="Stronghold", F8="Lean")), "Defend", OR( AND(G8="INC", OR(F8="Battleground", F8="Highly Volatile", F8="Opposition Lean")), AND(R8="INC", OR(F8="Battleground", F8="Highly Volatile", F8="Opposition Lean")) ), "Battleground", OR(K8="INC", M8="INC", R8="INC"), "Expand", TRUE, "Long Shot" ) -> Defend | V8: =IFS( AND(G8="SAD", OR(F8="Stronghold", F8="Lean")), "Defend", OR( AND(G8="SAD", OR(F8="Battleground", F8="Highly Volatile", F8="Opposition Lean")), AND(R8="SAD", OR(F8="Battleground", F8="Highly Volatile", F8="Opposition Lean")) ), "Battleground", OR(K8="SAD", M8="SAD", R8="SAD"), "Expand", TRUE, "Long Shot" ) -> Long Shot | W8: =IFS( AND(G8="BJP", OR(F8="Stronghold", F8="Lean")), "Defend", OR( AND(G8="BJP", OR(F8="Battleground", F8="Highly Volatile", F8="Opposition Lean")), AND(R8="BJP", OR(F8="Battleground", F8="Highly Volatile", F8="Opposition Lean")) ), "Battleground", OR(K8="BJP", M8="BJP", R8="BJP"), "Expand", TRUE, "Long Shot" ) -> Long Shot | X8: =IFS(K8="EMERGING", "YES", COUNTIFS(T8:W8, "<>Long Shot", T8:W8, "<>") >= 3, "YES", TRUE, "")
A9: 6 | B9: Qadian | C9: Gurdaspur | D9: Majha | E9: Partap Singh Bajwa | F9: =IFS( OR(P9>=75, ((H9<>J9)+(J9<>I9)+(I9<>K9))>=3), "Highly Volatile", AND(COUNTIF(H9:K9, G9)+1>=4, O9<55, P9<65), "Stronghold", AND(COUNTIF(H9:K9, G9)+1>=3, O9<70, P9<75), "Lean", AND(R9<>G9, ((H9=R9)+(J9=R9)+(K9=R9))>=2, O9<60, P9<70), "Opposition Lean", TRUE, "Battleground" ) -> Stronghold | G9: INC | H9: INC | I9: INC | J9: BJP | K9: INC | M9: SAD | N9: 5.42 | O9: {=_xlfn.XLOOKUP(B9, 'Assembly Competitiveness'!$B$4:$B$120,'Assembly Competitiveness'!$O$4:$O$120, "-")} -> 45.255 | P9: {=_xlfn.XLOOKUP(B9,'Assembly Volatality'!$B$4:$B$120,'Assembly Volatality'!$L$4:$L$120, "-")} -> 5.61 | Q9: =ROUND(0.45*O9+0.4*P9+0.15*IF(H9<>K9,100,0),1) -> 22.6 | R9: SAD | T9: =IFS( AND(G9="AAP", OR(F9="Stronghold", F9="Lean")), "Defend", OR( AND(G9="AAP", OR(F9="Battleground", F9="Highly Volatile", F9="Opposition Lean")), AND(R9="AAP", OR(F9="Battleground", F9="Highly Volatile", F9="Opposition Lean")) ), "Battleground", OR(K9="AAP", M9="AAP", R9="AAP"), "Expand", TRUE, "Long Shot" ) -> Long Shot | U9: =IFS( AND(G9="INC", OR(F9="Stronghold", F9="Lean")), "Defend", OR( AND(G9="INC", OR(F9="Battleground", F9="Highly Volatile", F9="Opposition Lean")), AND(R9="INC", OR(F9="Battleground", F9="Highly Volatile", F9="Opposition Lean")) ), "Battleground", OR(K9="INC", M9="INC", R9="INC"), "Expand", TRUE, "Long Shot" ) -> Defend | V9: =IFS( AND(G9="SAD", OR(F9="Stronghold", F9="Lean")), "Defend", OR( AND(G9="SAD", OR(F9="Battleground", F9="Highly Volatile", F9="Opposition Lean")), AND(R9="SAD", OR(F9="Battleground", F9="Highly Volatile", F9="Opposition Lean")) ), "Battleground", OR(K9="SAD", M9="SAD", R9="SAD"), "Expand", TRUE, "Long Shot" ) -> Expand | W9: =IFS( AND(G9="BJP", OR(F9="Stronghold", F9="Lean")), "Defend", OR( AND(G9="BJP", OR(F9="Battleground", F9="Highly Volatile", F9="Opposition Lean")), AND(R9="BJP", OR(F9="Battleground", F9="Highly Volatile", F9="Opposition Lean")) ), "Battleground", OR(K9="BJP", M9="BJP", R9="BJP"), "Expand", TRUE, "Long Shot" ) -> Long Shot | X9: =IFS(K9="EMERGING", "YES", COUNTIFS(T9:W9, "<>Long Shot", T9:W9, "<>") >= 3, "YES", TRUE, "")
A10: 7 | B10: Batala | C10: Gurdaspur | D10: Majha | E10: Amansher Singh (Shery Kalsi) | F10: =IFS( OR(P10>=75, ((H10<>J10)+(J10<>I10)+(I10<>K10))>=3), "Highly Volatile", AND(COUNTIF(H10:K10, G10)+1>=4, O10<55, P10<65), "Stronghold", AND(COUNTIF(H10:K10, G10)+1>=3, O10<70, P10<75), "Lean", AND(R10<>G10, ((H10=R10)+(J10=R10)+(K10=R10))>=2, O10<60, P10<70), "Opposition Lean", TRUE, "Battleground" ) -> Highly Volatile | G10: AAP | H10: SAD | I10: AAP | J10: BJP | K10: INC | M10: INC | N10: 22.44 | O10: {=_xlfn.XLOOKUP(B10, 'Assembly Competitiveness'!$B$4:$B$120,'Assembly Competitiveness'!$O$4:$O$120, "-")} -> 38.416 | P10: {=_xlfn.XLOOKUP(B10,'Assembly Volatality'!$B$4:$B$120,'Assembly Volatality'!$L$4:$L$120, "-")} -> 64.25 | Q10: =ROUND(0.45*O10+0.4*P10+0.15*IF(H10<>K10,100,0),1) -> 58 | R10: INC | S10: YES | T10: =IFS( AND(G10="AAP", OR(F10="Stronghold", F10="Lean")), "Defend", OR( AND(G10="AAP", OR(F10="Battleground", F10="Highly Volatile", F10="Opposition Lean")), AND(R10="AAP", OR(F10="Battleground", F10="Highly Volatile", F10="Opposition Lean")) ), "Battleground", OR(K10="AAP", M10="AAP", R10="AAP"), "Expand", TRUE, "Long Shot" ) -> Battleground | U10: =IFS( AND(G10="INC", OR(F10="Stronghold", F10="Lean")), "Defend", OR( AND(G10="INC", OR(F10="Battleground", F10="Highly Volatile", F10="Opposition Lean")), AND(R10="INC", OR(F10="Battleground", F10="Highly Volatile", F10="Opposition Lean")) ), "Battleground", OR(K10="INC", M10="INC", R10="INC"), "Expand", TRUE, "Long Shot" ) -> Battleground | V10: =IFS( AND(G10="SAD", OR(F10="Stronghold", F10="Lean")), "Defend", OR( AND(G10="SAD", OR(F10="Battleground", F10="Highly Volatile", F10="Opposition Lean")), AND(R10="SAD", OR(F10="Battleground", F10="Highly Volatile", F10="Opposition Lean")) ), "Battleground", OR(K10="SAD", M10="SAD", R10="SAD"), "Expand", TRUE, "Long Shot" ) -> Long Shot | W10: =IFS( AND(G10="BJP", OR(F10="Stronghold", F10="Lean")), "Defend", OR( AND(G10="BJP", OR(F10="Battleground", F10="Highly Volatile", F10="Opposition Lean")), AND(R10="BJP", OR(F10="Battleground", F10="Highly Volatile", F10="Opposition Lean")) ), "Battleground", OR(K10="BJP", M10="BJP", R10="BJP"), "Expand", TRUE, "Long Shot" ) -> Long Shot | X10: =IFS(K10="EMERGING", "YES", COUNTIFS(T10:W10, "<>Long Shot", T10:W10, "<>") >= 3, "YES", TRUE, "")
A11: 8 | B11: Sri Hargobindpur | C11: Gurdaspur | D11: Majha | E11: Amarpal Singh | F11: =IFS( OR(P11>=75, ((H11<>J11)+(J11<>I11)+(I11<>K11))>=3), "Highly Volatile", AND(COUNTIF(H11:K11, G11)+1>=4, O11<55, P11<65), "Stronghold", AND(COUNTIF(H11:K11, G11)+1>=3, O11<70, P11<75), "Lean", AND(R11<>G11, ((H11=R11)+(J11=R11)+(K11=R11))>=2, O11<60, P11<70), "Opposition Lean", TRUE, "Battleground" ) -> Battleground | G11: AAP | H11: INC | I11: AAP | J11: INC | K11: INC | M11: SAD | N11: 13.78 | O11: {=_xlfn.XLOOKUP(B11, 'Assembly Competitiveness'!$B$4:$B$120,'Assembly Competitiveness'!$O$4:$O$120, "-")} -> 29.723 | P11: {=_xlfn.XLOOKUP(B11,'Assembly Volatality'!$B$4:$B$120,'Assembly Volatality'!$L$4:$L$120, "-")} -> 44.69 | Q11: =ROUND(0.45*O11+0.4*P11+0.15*IF(H11<>K11,100,0),1) -> 31.3 | R11: SAD | S11: YES | T11: =IFS( AND(G11="AAP", OR(F11="Stronghold", F11="Lean")), "Defend", OR( AND(G11="AAP", OR(F11="Battleground", F11="Highly Volatile", F11="Opposition Lean")), AND(R11="AAP", OR(F11="Battleground", F11="Highly Volatile", F11="Opposition Lean")) ), "Battleground", OR(K11="AAP", M11="AAP", R11="AAP"), "Expand", TRUE, "Long Shot" ) -> Battleground | U11: =IFS( AND(G11="INC", OR(F11="Stronghold", F11="Lean")), "Defend", OR( AND(G11="INC", OR(F11="Battleground", F11="Highly Volatile", F11="Opposition Lean")), AND(R11="INC", OR(F11="Battleground", F11="Highly Volatile", F11="Opposition Lean")) ), "Battleground", OR(K11="INC", M11="INC", R11="INC"), "Expand", TRUE, "Long Shot" ) -> Expand | V11: =IFS( AND(G11="SAD", OR(F11="Stronghold", F11="Lean")), "Defend", OR( AND(G11="SAD", OR(F11="Battleground", F11="Highly Volatile", F11="Opposition Lean")), AND(R11="SAD", OR(F11="Battleground", F11="Highly Volatile", F11="Opposition Lean")) ), "Battleground", OR(K11="SAD", M11="SAD", R11="SAD"), "Expand", TRUE, "Long Shot" ) -> Battleground | W11: =IFS( AND(G11="BJP", OR(F11="Stronghold", F11="Lean")), "Defend", OR( AND(G11="BJP", OR(F11="Battleground", F11="Highly Volatile", F11="Opposition Lean")), AND(R11="BJP", OR(F11="Battleground", F11="Highly Volatile", F11="Opposition Lean")) ), "Battleground", OR(K11="BJP", M11="BJP", R11="BJP"), "Expand", TRUE, "Long Shot" ) -> Long Shot | X11: =IFS(K11="EMERGING", "YES", COUNTIFS(T11:W11, "<>Long Shot", T11:W11, "<>") >= 3, "YES", TRUE, "") -> YES
A12: 9 | B12: Fatehgarh Churian | C12: Gurdaspur | D12: Majha | E12: Tript Rajinder Singh Bajwa | F12: =IFS( OR(P12>=75, ((H12<>J12)+(J12<>I12)+(I12<>K12))>=3), "Highly Volatile", AND(COUNTIF(H12:K12, G12)+1>=4, O12<55, P12<65), "Stronghold", AND(COUNTIF(H12:K12, G12)+1>=3, O12<70, P12<75), "Lean", AND(R12<>G12, ((H12=R12)+(J12=R12)+(K12=R12))>=2, O12<60, P12<70), "Opposition Lean", TRUE, "Battleground" ) -> Stronghold | G12: INC | H12: INC | I12: INC | J12: INC | K12: INC | M12: SAD | N12: 4.33 | O12: {=_xlfn.XLOOKUP(B12, 'Assembly Competitiveness'!$B$4:$B$120,'Assembly Competitiveness'!$O$4:$O$120, "-")} -> 54.7215 | P12: {=_xlfn.XLOOKUP(B12,'Assembly Volatality'!$B$4:$B$120,'Assembly Volatality'!$L$4:$L$120, "-")} -> 5.02 | Q12: =ROUND(0.45*O12+0.4*P12+0.15*IF(H12<>K12,100,0),1) -> 26.6 | R12: SAD | T12: =IFS( AND(G12="AAP", OR(F12="Stronghold", F12="Lean")), "Defend", OR( AND(G12="AAP", OR(F12="Battleground", F12="Highly Volatile", F12="Opposition Lean")), AND(R12="AAP", OR(F12="Battleground", F12="Highly Volatile", F12="Opposition Lean")) ), "Battleground", OR(K12="AAP", M12="AAP", R12="AAP"), "Expand", TRUE, "Long Shot" ) -> Long Shot | U12: =IFS( AND(G12="INC", OR(F12="Stronghold", F12="Lean")), "Defend", OR( AND(G12="INC", OR(F12="Battleground", F12="Highly Volatile", F12="Opposition Lean")), AND(R12="INC", OR(F12="Battleground", F12="Highly Volatile", F12="Opposition Lean")) ), "Battleground", OR(K12="INC", M12="INC", R12="INC"), "Expand", TRUE, "Long Shot" ) -> Defend | V12: =IFS( AND(G12="SAD", OR(F12="Stronghold", F12="Lean")), "Defend", OR( AND(G12="SAD", OR(F12="Battleground", F12="Highly Volatile", F12="Opposition Lean")), AND(R12="SAD", OR(F12="Battleground", F12="Highly Volatile", F12="Opposition Lean")) ), "Battleground", OR(K12="SAD", M12="SAD", R12="SAD"), "Expand", TRUE, "Long Shot" ) -> Expand | W12: =IFS( AND(G12="BJP", OR(F12="Stronghold", F12="Lean")), "Defend", OR( AND(G12="BJP", OR(F12="Battleground", F12="Highly Volatile", F12="Opposition Lean")), AND(R12="BJP", OR(F12="Battleground", F12="Highly Volatile", F12="Opposition Lean")) ), "Battleground", OR(K12="BJP", M12="BJP", R12="BJP"), "Expand", TRUE, "Long Shot" ) -> Long Shot | X12: =IFS(K12="EMERGING", "YES", COUNTIFS(T12:W12, "<>Long Shot", T12:W12, "<>") >= 3, "YES", TRUE, "")
A13: 10 | B13: Dera Baba Nanak | C13: Gurdaspur | D13: Majha | E13: Gurdeep Singh Randhawa | F13: =IFS( OR(P13>=75, ((H13<>J13)+(J13<>I13)+(I13<>K13))>=3), "Highly Volatile", AND(COUNTIF(H13:K13, G13)+1>=4, O13<55, P13<65), "Stronghold", AND(COUNTIF(H13:K13, G13)+1>=3, O13<70, P13<75), "Lean", AND(R13<>G13, ((H13=R13)+(J13=R13)+(K13=R13))>=2, O13<60, P13<70), "Opposition Lean", TRUE, "Battleground" ) -> Battleground | G13: AAP | H13: INC | I13: INC | J13: INC | K13: INC | L13: 2024 bypoll AAP gain from INC | M13: SAD | N13: 0.33 | O13: {=_xlfn.XLOOKUP(B13, 'Assembly Competitiveness'!$B$4:$B$120,'Assembly Competitiveness'!$O$4:$O$120, "-")} -> 78.6155 | P13: {=_xlfn.XLOOKUP(B13,'Assembly Volatality'!$B$4:$B$120,'Assembly Volatality'!$L$4:$L$120, "-")} -> 28.76 | Q13: =ROUND(0.45*O13+0.4*P13+0.15*IF(H13<>L13,100,0),1) -> 61.9 | R13: INC | T13: =IFS( AND(G13="AAP", OR(F13="Stronghold", F13="Lean")), "Defend", OR( AND(G13="AAP", OR(F13="Battleground", F13="Highly Volatile", F13="Opposition Lean")), AND(R13="AAP", OR(F13="Battleground", F13="Highly Volatile", F13="Opposition Lean")) ), "Battleground", OR(K13="AAP", M13="AAP", R13="AAP"), "Expand", TRUE, "Long Shot" ) -> Battleground | U13: =IFS( AND(G13="INC", OR(F13="Stronghold", F13="Lean")), "Defend", OR( AND(G13="INC", OR(F13="Battleground", F13="Highly Volatile", F13="Opposition Lean")), AND(R13="INC", OR(F13="Battleground", F13="Highly Volatile", F13="Opposition Lean")) ), "Battleground", OR(K13="INC", M13="INC", R13="INC"), "Expand", TRUE, "Long Shot" ) -> Battleground | V13: =IFS( AND(G13="SAD", OR(F13="Stronghold", F13="Lean")), "Defend", OR( AND(G13="SAD", OR(F13="Battleground", F13="Highly Volatile", F13="Opposition Lean")), AND(R13="SAD", OR(F13="Battleground", F13="Highly Volatile", F13="Opposition Lean")) ), "Battleground", OR(K13="SAD", M13="SAD", R13="SAD"), "Expand", TRUE, "Long Shot" ) -> Expand | W13: =IFS( AND(G13="BJP", OR(F13="Stronghold", F13="Lean")), "Defend", OR( AND(G13="BJP", OR(F13="Battleground", F13="Highly Volatile", F13="Opposition Lean")), AND(R13="BJP", OR(F13="Battleground", F13="Highly Volatile", F13="Opposition Lean")) ), "Battleground", OR(K13="BJP", M13="BJP", R13="BJP"), "Expand", TRUE, "Long Shot" ) -> Long Shot | X13: =IFS(K13="EMERGING", "YES", COUNTIFS(T13:W13, "<>Long Shot", T13:W13, "<>") >= 3, "YES", TRUE, "") -> YES
A14: 11 | B14: Ajnala | C14: Amritsar | D14: Majha | E14: Kuldeep Singh Dhaliwal | F14: =IFS( OR(P14>=75, ((H14<>J14)+(J14<>I14)+(I14<>K14))>=3), "Highly Volatile", AND(COUNTIF(H14:K14, G14)+1>=4, O14<55, P14<65), "Stronghold", AND(COUNTIF(H14:K14, G14)+1>=3, O14<70, P14<75), "Lean", AND(R14<>G14, ((H14=R14)+(J14=R14)+(K14=R14))>=2, O14<60, P14<70), "Opposition Lean", TRUE, "Battleground" ) -> Lean | G14: AAP | H14: INC | I14: AAP | J14: INC | K14: AAP | M14: SAD | N14: 6.47 | O14: {=_xlfn.XLOOKUP(B14, 'Assembly Competitiveness'!$B$4:$B$120,'Assembly Competitiveness'!$O$4:$O$120, "-")} -> 38.5665 | P14: {=_xlfn.XLOOKUP(B14,'Assembly Volatality'!$B$4:$B$120,'Assembly Volatality'!$L$4:$L$120, "-")} -> 44.06 | Q14: =ROUND(0.45*O14+0.4*P14+0.15*IF(H14<>K14,100,0),1) -> 50 | R14: SAD | T14: =IFS( AND(G14="AAP", OR(F14="Stronghold", F14="Lean")), "Defend", OR( AND(G14="AAP", OR(F14="Battleground", F14="Highly Volatile", F14="Opposition Lean")), AND(R14="AAP", OR(F14="Battleground", F14="Highly Volatile", F14="Opposition Lean")) ), "Battleground", OR(K14="AAP", M14="AAP", R14="AAP"), "Expand", TRUE, "Long Shot" ) -> Defend | U14: =IFS( AND(G14="INC", OR(F14="Stronghold", F14="Lean")), "Defend", OR( AND(G14="INC", OR(F14="Battleground", F14="Highly Volatile", F14="Opposition Lean")), AND(R14="INC", OR(F14="Battleground", F14="Highly Volatile", F14="Opposition Lean")) ), "Battleground", OR(K14="INC", M14="INC", R14="INC"), "Expand", TRUE, "Long Shot" ) -> Long Shot | V14: =IFS( AND(G14="SAD", OR(F14="Stronghold", F14="Lean")), "Defend", OR( AND(G14="SAD", OR(F14="Battleground", F14="Highly Volatile", F14="Opposition Lean")), AND(R14="SAD", OR(F14="Battleground", F14="Highly Volatile", F14="Opposition Lean")) ), "Battleground", OR(K14="SAD", M14="SAD", R14="SAD"), "Expand", TRUE, "Long Shot" ) -> Expand | W14: =IFS( AND(G14="BJP", OR(F14="Stronghold", F14="Lean")), "Defend", OR( AND(G14="BJP", OR(F14="Battleground", F14="Highly Volatile", F14="Opposition Lean")), AND(R14="BJP", OR(F14="Battleground", F14="Highly Volatile", F14="Opposition Lean")) ), "Battleground", OR(K14="BJP", M14="BJP", R14="BJP"), "Expand", TRUE, "Long Shot" ) -> Long Shot | X14: =IFS(K14="EMERGING", "YES", COUNTIFS(T14:W14, "<>Long Shot", T14:W14, "<>") >= 3, "YES", TRUE, "")
A15: 12 | B15: Raja Sansi | C15: Amritsar | D15: Majha | E15: Sukhbinder Singh Sarkaria | F15: =IFS( OR(P15>=75, ((H15<>J15)+(J15<>I15)+(I15<>K15))>=3), "Highly Volatile", AND(COUNTIF(H15:K15, G15)+1>=4, O15<55, P15<65), "Stronghold", AND(COUNTIF(H15:K15, G15)+1>=3, O15<70, P15<75), "Lean", AND(R15<>G15, ((H15=R15)+(J15=R15)+(K15=R15))>=2, O15<60, P15<70), "Opposition Lean", TRUE, "Battleground" ) -> Stronghold | G15: INC | H15: INC | I15: INC | J15: INC | K15: INC | M15: SAD | N15: 4.14 | O15: {=_xlfn.XLOOKUP(B15, 'Assembly Competitiveness'!$B$4:$B$120,'Assembly Competitiveness'!$O$4:$O$120, "-")} -> 51.407 | P15: {=_xlfn.XLOOKUP(B15,'Assembly Volatality'!$B$4:$B$120,'Assembly Volatality'!$L$4:$L$120, "-")} -> 3.92 | Q15: =ROUND(0.45*O15+0.4*P15+0.15*IF(H15<>K15,100,0),1) -> 24.7 | R15: SAD | T15: =IFS( AND(G15="AAP", OR(F15="Stronghold", F15="Lean")), "Defend", OR( AND(G15="AAP", OR(F15="Battleground", F15="Highly Volatile", F15="Opposition Lean")), AND(R15="AAP", OR(F15="Battleground", F15="Highly Volatile", F15="Opposition Lean")) ), "Battleground", OR(K15="AAP", M15="AAP", R15="AAP"), "Expand", TRUE, "Long Shot" ) -> Long Shot | U15: =IFS( AND(G15="INC", OR(F15="Stronghold", F15="Lean")), "Defend", OR( AND(G15="INC", OR(F15="Battleground", F15="Highly Volatile", F15="Opposition Lean")), AND(R15="INC", OR(F15="Battleground", F15="Highly Volatile", F15="Opposition Lean")) ), "Battleground", OR(K15="INC", M15="INC", R15="INC"), "Expand", TRUE, "Long Shot" ) -> Defend | V15: =IFS( AND(G15="SAD", OR(F15="Stronghold", F15="Lean")), "Defend", OR( AND(G15="SAD", OR(F15="Battleground", F15="Highly Volatile", F15="Opposition Lean")), AND(R15="SAD", OR(F15="Battleground", F15="Highly Volatile", F15="Opposition Lean")) ), "Battleground", OR(K15="SAD", M15="SAD", R15="SAD"), "Expand", TRUE, "Long Shot" ) -> Expand | W15: =IFS( AND(G15="BJP", OR(F15="Stronghold", F15="Lean")), "Defend", OR( AND(G15="BJP", OR(F15="Battleground", F15="Highly Volatile", F15="Opposition Lean")), AND(R15="BJP", OR(F15="Battleground", F15="Highly Volatile", F15="Opposition Lean")) ), "Battleground", OR(K15="BJP", M15="BJP", R15="BJP"), "Expand", TRUE, "Long Shot" ) -> Long Shot | X15: =IFS(K15="EMERGING", "YES", COUNTIFS(T15:W15, "<>Long Shot", T15:W15, "<>") >= 3, "YES", TRUE, "")
A16: 13 | B16: Majitha | C16: Amritsar | D16: Majha | E16: Ganieve Kaur Majithia | F16: =IFS( OR(P16>=75, ((H16<>J16)+(J16<>I16)+(I16<>K16))>=3), "Highly Volatile", AND(COUNTIF(H16:K16, G16)+1>=4, O16<55, P16<65), "Stronghold", AND(COUNTIF(H16:K16, G16)+1>=3, O16<70, P16<75), "Lean", AND(R16<>G16, ((H16=R16)+(J16=R16)+(K16=R16))>=2, O16<60, P16<70), "Opposition Lean", TRUE, "Battleground" ) -> Stronghold | G16: SAD | H16: SAD | I16: SAD | J16: BJP | K16: SAD | M16: AAP | N16: 21.48 | O16: {=_xlfn.XLOOKUP(B16, 'Assembly Competitiveness'!$B$4:$B$120,'Assembly Competitiveness'!$O$4:$O$120, "-")} -> 2.258 | P16: {=_xlfn.XLOOKUP(B16,'Assembly Volatality'!$B$4:$B$120,'Assembly Volatality'!$L$4:$L$120, "-")} -> 6.42 | Q16: =ROUND(0.45*O16+0.4*P16+0.15*IF(H16<>K16,100,0),1) -> 3.6 | R16: AAP | T16: =IFS( AND(G16="AAP", OR(F16="Stronghold", F16="Lean")), "Defend", OR( AND(G16="AAP", OR(F16="Battleground", F16="Highly Volatile", F16="Opposition Lean")), AND(R16="AAP", OR(F16="Battleground", F16="Highly Volatile", F16="Opposition Lean")) ), "Battleground", OR(K16="AAP", M16="AAP", R16="AAP"), "Expand", TRUE, "Long Shot" ) -> Expand | U16: =IFS( AND(G16="INC", OR(F16="Stronghold", F16="Lean")), "Defend", OR( AND(G16="INC", OR(F16="Battleground", F16="Highly Volatile", F16="Opposition Lean")), AND(R16="INC", OR(F16="Battleground", F16="Highly Volatile", F16="Opposition Lean")) ), "Battleground", OR(K16="INC", M16="INC", R16="INC"), "Expand", TRUE, "Long Shot" ) -> Long Shot | V16: =IFS( AND(G16="SAD", OR(F16="Stronghold", F16="Lean")), "Defend", OR( AND(G16="SAD", OR(F16="Battleground", F16="Highly Volatile", F16="Opposition Lean")), AND(R16="SAD", OR(F16="Battleground", F16="Highly Volatile", F16="Opposition Lean")) ), "Battleground", OR(K16="SAD", M16="SAD", R16="SAD"), "Expand", TRUE, "Long Shot" ) -> Defend | W16: =IFS( AND(G16="BJP", OR(F16="Stronghold", F16="Lean")), "Defend", OR( AND(G16="BJP", OR(F16="Battleground", F16="Highly Volatile", F16="Opposition Lean")), AND(R16="BJP", OR(F16="Battleground", F16="Highly Volatile", F16="Opposition Lean")) ), "Battleground", OR(K16="BJP", M16="BJP", R16="BJP"), "Expand", TRUE, "Long Shot" ) -> Long Shot | X16: =IFS(K16="EMERGING", "YES", COUNTIFS(T16:W16, "<>Long Shot", T16:W16, "<>") >= 3, "YES", TRUE, "")
A17: 14 | B17: Jandiala | C17: Amritsar | D17: Majha | E17: Harbhajan Singh E.T.O. | F17: =IFS( OR(P17>=75, ((H17<>J17)+(J17<>I17)+(I17<>K17))>=3), "Highly Volatile", AND(COUNTIF(H17:K17, G17)+1>=4, O17<55, P17<65), "Stronghold", AND(COUNTIF(H17:K17, G17)+1>=3, O17<70, P17<75), "Lean", AND(R17<>G17, ((H17=R17)+(J17=R17)+(K17=R17))>=2, O17<60, P17<70), "Opposition Lean", TRUE, "Battleground" ) -> Opposition Lean | G17: AAP | H17: INC | I17: AAP | J17: INC | K17: EMERGING | M17: INC | N17: 19.87 | O17: {=_xlfn.XLOOKUP(B17, 'Assembly Competitiveness'!$B$4:$B$120,'Assembly Competitiveness'!$O$4:$O$120, "-")} -> 17.5765 | P17: {=_xlfn.XLOOKUP(B17,'Assembly Volatality'!$B$4:$B$120,'Assembly Volatality'!$L$4:$L$120, "-")} -> 48.08 | Q17: =ROUND(0.45*O17+0.4*P17+0.15*IF(H17<>K17,100,0),1) -> 42.1 | R17: INC | S17: YES | T17: =IFS( AND(G17="AAP", OR(F17="Stronghold", F17="Lean")), "Defend", OR( AND(G17="AAP", OR(F17="Battleground", F17="Highly Volatile", F17="Opposition Lean")), AND(R17="AAP", OR(F17="Battleground", F17="Highly Volatile", F17="Opposition Lean")) ), "Battleground", OR(K17="AAP", M17="AAP", R17="AAP"), "Expand", TRUE, "Long Shot" ) -> Battleground | U17: =IFS( AND(G17="INC", OR(F17="Stronghold", F17="Lean")), "Defend", OR( AND(G17="INC", OR(F17="Battleground", F17="Highly Volatile", F17="Opposition Lean")), AND(R17="INC", OR(F17="Battleground", F17="Highly Volatile", F17="Opposition Lean")) ), "Battleground", OR(K17="INC", M17="INC", R17="INC"), "Expand", TRUE, "Long Shot" ) -> Battleground | V17: =IFS( AND(G17="SAD", OR(F17="Stronghold", F17="Lean")), "Defend", OR( AND(G17="SAD", OR(F17="Battleground", F17="Highly Volatile", F17="Opposition Lean")), AND(R17="SAD", OR(F17="Battleground", F17="Highly Volatile", F17="Opposition Lean")) ), "Battleground", OR(K17="SAD", M17="SAD", R17="SAD"), "Expand", TRUE, "Long Shot" ) -> Long Shot | W17: =IFS( AND(G17="BJP", OR(F17="Stronghold", F17="Lean")), "Defend", OR( AND(G17="BJP", OR(F17="Battleground", F17="Highly Volatile", F17="Opposition Lean")), AND(R17="BJP", OR(F17="Battleground", F17="Highly Volatile", F17="Opposition Lean")) ), "Battleground", OR(K17="BJP", M17="BJP", R17="BJP"), "Expand", TRUE, "Long Shot" ) -> Long Shot | X17: =IFS(K17="EMERGING", "YES", COUNTIFS(T17:W17, "<>Long Shot", T17:W17, "<>") >= 3, "YES", TRUE, "") -> YES
A18: 15 | B18: Amritsar North | C18: Amritsar | D18: Majha | E18: Kunwar Vijay Pratap Singh | F18: =IFS( OR(P18>=75, ((H18<>J18)+(J18<>I18)+(I18<>K18))>=3), "Highly Volatile", AND(COUNTIF(H18:K18, G18)+1>=4, O18<55, P18<65), "Stronghold", AND(COUNTIF(H18:K18, G18)+1>=3, O18<70, P18<75), "Lean", AND(R18<>G18, ((H18=R18)+(J18=R18)+(K18=R18))>=2, O18<60, P18<70), "Opposition Lean", TRUE, "Battleground" ) -> Battleground | G18: AAP | H18: INC | I18: AAP | J18: INC | K18: BJP | M18: SAD | N18: 23.03 | O18: {=_xlfn.XLOOKUP(B18, 'Assembly Competitiveness'!$B$4:$B$120,'Assembly Competitiveness'!$O$4:$O$120, "-")} -> 22.188 | P18: {=_xlfn.XLOOKUP(B18,'Assembly Volatality'!$B$4:$B$120,'Assembly Volatality'!$L$4:$L$120, "-")} -> 56.29 | Q18: =ROUND(0.45*O18+0.4*P18+0.15*IF(H18<>K18,100,0),1) -> 47.5 | R18: SAD | S18: YES | T18: =IFS( AND(G18="AAP", OR(F18="Stronghold", F18="Lean")), "Defend", OR( AND(G18="AAP", OR(F18="Battleground", F18="Highly Volatile", F18="Opposition Lean")), AND(R18="AAP", OR(F18="Battleground", F18="Highly Volatile", F18="Opposition Lean")) ), "Battleground", OR(K18="AAP", M18="AAP", R18="AAP"), "Expand", TRUE, "Long Shot" ) -> Battleground | U18: =IFS( AND(G18="INC", OR(F18="Stronghold", F18="Lean")), "Defend", OR( AND(G18="INC", OR(F18="Battleground", F18="Highly Volatile", F18="Opposition Lean")), AND(R18="INC", OR(F18="Battleground", F18="Highly Volatile", F18="Opposition Lean")) ), "Battleground", OR(K18="INC", M18="INC", R18="INC"), "Expand", TRUE, "Long Shot" ) -> Long Shot | V18: =IFS( AND(G18="SAD", OR(F18="Stronghold", F18="Lean")), "Defend", OR( AND(G18="SAD", OR(F18="Battleground", F18="Highly Volatile", F18="Opposition Lean")), AND(R18="SAD", OR(F18="Battleground", F18="Highly Volatile", F18="Opposition Lean")) ), "Battleground", OR(K18="SAD", M18="SAD", R18="SAD"), "Expand", TRUE, "Long Shot" ) -> Battleground | W18: =IFS( AND(G18="BJP", OR(F18="Stronghold", F18="Lean")), "Defend", OR( AND(G18="BJP", OR(F18="Battleground", F18="Highly Volatile", F18="Opposition Lean")), AND(R18="BJP", OR(F18="Battleground", F18="Highly Volatile", F18="Opposition Lean")) ), "Battleground", OR(K18="BJP", M18="BJP", R18="BJP"), "Expand", TRUE, "Long Shot" ) -> Expand | X18: =IFS(K18="EMERGING", "YES", COUNTIFS(T18:W18, "<>Long Shot", T18:W18, "<>") >= 3, "YES", TRUE, "") -> YES
A19: 16 | B19: Amritsar West | C19: Amritsar | D19: Majha | E19: Dr. Jasbir Singh Sandhu | F19: =IFS( OR(P19>=75, ((H19<>J19)+(J19<>I19)+(I19<>K19))>=3), "Highly Volatile", AND(COUNTIF(H19:K19, G19)+1>=4, O19<55, P19<65), "Stronghold", AND(COUNTIF(H19:K19, G19)+1>=3, O19<70, P19<75), "Lean", AND(R19<>G19, ((H19=R19)+(J19=R19)+(K19=R19))>=2, O19<60, P19<70), "Opposition Lean", TRUE, "Battleground" ) -> Opposition Lean | G19: AAP | H19: INC | I19: AAP | J19: INC | K19: INC | M19: INC | N19: 37.33 | O19: {=_xlfn.XLOOKUP(B19, 'Assembly Competitiveness'!$B$4:$B$120,'Assembly Competitiveness'!$O$4:$O$120, "-")} -> 14.872 | P19: {=_xlfn.XLOOKUP(B19,'Assembly Volatality'!$B$4:$B$120,'Assembly Volatality'!$L$4:$L$120, "-")} -> 56.28 | Q19: =ROUND(0.45*O19+0.4*P19+0.15*IF(H19<>K19,100,0),1) -> 29.2 | R19: INC | S19: YES | T19: =IFS( AND(G19="AAP", OR(F19="Stronghold", F19="Lean")), "Defend", OR( AND(G19="AAP", OR(F19="Battleground", F19="Highly Volatile", F19="Opposition Lean")), AND(R19="AAP", OR(F19="Battleground", F19="Highly Volatile", F19="Opposition Lean")) ), "Battleground", OR(K19="AAP", M19="AAP", R19="AAP"), "Expand", TRUE, "Long Shot" ) -> Battleground | U19: =IFS( AND(G19="INC", OR(F19="Stronghold", F19="Lean")), "Defend", OR( AND(G19="INC", OR(F19="Battleground", F19="Highly Volatile", F19="Opposition Lean")), AND(R19="INC", OR(F19="Battleground", F19="Highly Volatile", F19="Opposition Lean")) ), "Battleground", OR(K19="INC", M19="INC", R19="INC"), "Expand", TRUE, "Long Shot" ) -> Battleground | V19: =IFS( AND(G19="SAD", OR(F19="Stronghold", F19="Lean")), "Defend", OR( AND(G19="SAD", OR(F19="Battleground", F19="Highly Volatile", F19="Opposition Lean")), AND(R19="SAD", OR(F19="Battleground", F19="Highly Volatile", F19="Opposition Lean")) ), "Battleground", OR(K19="SAD", M19="SAD", R19="SAD"), "Expand", TRUE, "Long Shot" ) -> Long Shot | W19: =IFS( AND(G19="BJP", OR(F19="Stronghold", F19="Lean")), "Defend", OR( AND(G19="BJP", OR(F19="Battleground", F19="Highly Volatile", F19="Opposition Lean")), AND(R19="BJP", OR(F19="Battleground", F19="Highly Volatile", F19="Opposition Lean")) ), "Battleground", OR(K19="BJP", M19="BJP", R19="BJP"), "Expand", TRUE, "Long Shot" ) -> Long Shot | X19: =IFS(K19="EMERGING", "YES", COUNTIFS(T19:W19, "<>Long Shot", T19:W19, "<>") >= 3, "YES", TRUE, "")
A20: 17 | B20: Amritsar Central | C20: Amritsar | D20: Majha | E20: Ajay Gupta | F20: =IFS( OR(P20>=75, ((H20<>J20)+(J20<>I20)+(I20<>K20))>=3), "Highly Volatile", AND(COUNTIF(H20:K20, G20)+1>=4, O20<55, P20<65), "Stronghold", AND(COUNTIF(H20:K20, G20)+1>=3, O20<70, P20<75), "Lean", AND(R20<>G20, ((H20=R20)+(J20=R20)+(K20=R20))>=2, O20<60, P20<70), "Opposition Lean", TRUE, "Battleground" ) -> Opposition Lean | G20: AAP | H20: INC | I20: AAP | J20: INC | K20: BJP | M20: INC | N20: 16.21 | O20: {=_xlfn.XLOOKUP(B20, 'Assembly Competitiveness'!$B$4:$B$120,'Assembly Competitiveness'!$O$4:$O$120, "-")} -> 21.4515 | P20: {=_xlfn.XLOOKUP(B20,'Assembly Volatality'!$B$4:$B$120,'Assembly Volatality'!$L$4:$L$120, "-")} -> 54.11 | Q20: =ROUND(0.45*O20+0.4*P20+0.15*IF(H20<>K20,100,0),1) -> 46.3 | R20: INC | S20: YES | T20: =IFS( AND(G20="AAP", OR(F20="Stronghold", F20="Lean")), "Defend", OR( AND(G20="AAP", OR(F20="Battleground", F20="Highly Volatile", F20="Opposition Lean")), AND(R20="AAP", OR(F20="Battleground", F20="Highly Volatile", F20="Opposition Lean")) ), "Battleground", OR(K20="AAP", M20="AAP", R20="AAP"), "Expand", TRUE, "Long Shot" ) -> Battleground | U20: =IFS( AND(G20="INC", OR(F20="Stronghold", F20="Lean")), "Defend", OR( AND(G20="INC", OR(F20="Battleground", F20="Highly Volatile", F20="Opposition Lean")), AND(R20="INC", OR(F20="Battleground", F20="Highly Volatile", F20="Opposition Lean")) ), "Battleground", OR(K20="INC", M20="INC", R20="INC"), "Expand", TRUE, "Long Shot" ) -> Battleground | V20: =IFS( AND(G20="SAD", OR(F20="Stronghold", F20="Lean")), "Defend", OR( AND(G20="SAD", OR(F20="Battleground", F20="Highly Volatile", F20="Opposition Lean")), AND(R20="SAD", OR(F20="Battleground", F20="Highly Volatile", F20="Opposition Lean")) ), "Battleground", OR(K20="SAD", M20="SAD", R20="SAD"), "Expand", TRUE, "Long Shot" ) -> Long Shot | W20: =IFS( AND(G20="BJP", OR(F20="Stronghold", F20="Lean")), "Defend", OR( AND(G20="BJP", OR(F20="Battleground", F20="Highly Volatile", F20="Opposition Lean")), AND(R20="BJP", OR(F20="Battleground", F20="Highly Volatile", F20="Opposition Lean")) ), "Battleground", OR(K20="BJP", M20="BJP", R20="BJP"), "Expand", TRUE, "Long Shot" ) -> Expand | X20: =IFS(K20="EMERGING", "YES", COUNTIFS(T20:W20, "<>Long Shot", T20:W20, "<>") >= 3, "YES", TRUE, "") -> YES
A21: 18 | B21: Amritsar East | C21: Amritsar | D21: Majha | E21: Jeevan Jyot Kaur | F21: =IFS( OR(P21>=75, ((H21<>J21)+(J21<>I21)+(I21<>K21))>=3), "Highly Volatile", AND(COUNTIF(H21:K21, G21)+1>=4, O21<55, P21<65), "Stronghold", AND(COUNTIF(H21:K21, G21)+1>=3, O21<70, P21<75), "Lean", AND(R21<>G21, ((H21=R21)+(J21=R21)+(K21=R21))>=2, O21<60, P21<70), "Opposition Lean", TRUE, "Battleground" ) -> Opposition Lean | G21: AAP | H21: INC | I21: AAP | J21: INC | K21: BJP | M21: INC | N21: 6.29 | O21: {=_xlfn.XLOOKUP(B21, 'Assembly Competitiveness'!$B$4:$B$120,'Assembly Competitiveness'!$O$4:$O$120, "-")} -> 50.8475 | P21: {=_xlfn.XLOOKUP(B21,'Assembly Volatality'!$B$4:$B$120,'Assembly Volatality'!$L$4:$L$120, "-")} -> 65.35 | Q21: =ROUND(0.45*O21+0.4*P21+0.15*IF(H21<>K21,100,0),1) -> 64 | R21: INC | S21: YES | T21: =IFS( AND(G21="AAP", OR(F21="Stronghold", F21="Lean")), "Defend", OR( AND(G21="AAP", OR(F21="Battleground", F21="Highly Volatile", F21="Opposition Lean")), AND(R21="AAP", OR(F21="Battleground", F21="Highly Volatile", F21="Opposition Lean")) ), "Battleground", OR(K21="AAP", M21="AAP", R21="AAP"), "Expand", TRUE, "Long Shot" ) -> Battleground | U21: =IFS( AND(G21="INC", OR(F21="Stronghold", F21="Lean")), "Defend", OR( AND(G21="INC", OR(F21="Battleground", F21="Highly Volatile", F21="Opposition Lean")), AND(R21="INC", OR(F21="Battleground", F21="Highly Volatile", F21="Opposition Lean")) ), "Battleground", OR(K21="INC", M21="INC", R21="INC"), "Expand", TRUE, "Long Shot" ) -> Battleground | V21: =IFS( AND(G21="SAD", OR(F21="Stronghold", F21="Lean")), "Defend", OR( AND(G21="SAD", OR(F21="Battleground", F21="Highly Volatile", F21="Opposition Lean")), AND(R21="SAD", OR(F21="Battleground", F21="Highly Volatile", F21="Opposition Lean")) ), "Battleground", OR(K21="SAD", M21="SAD", R21="SAD"), "Expand", TRUE, "Long Shot" ) -> Long Shot | W21: =IFS( AND(G21="BJP", OR(F21="Stronghold", F21="Lean")), "Defend", OR( AND(G21="BJP", OR(F21="Battleground", F21="Highly Volatile", F21="Opposition Lean")), AND(R21="BJP", OR(F21="Battleground", F21="Highly Volatile", F21="Opposition Lean")) ), "Battleground", OR(K21="BJP", M21="BJP", R21="BJP"), "Expand", TRUE, "Long Shot" ) -> Expand | X21: =IFS(K21="EMERGING", "YES", COUNTIFS(T21:W21, "<>Long Shot", T21:W21, "<>") >= 3, "YES", TRUE, "") -> YES
A22: 19 | B22: Amritsar South | C22: Amritsar | D22: Majha | E22: Inderbir Singh Nijjar | F22: =IFS( OR(P22>=75, ((H22<>J22)+(J22<>I22)+(I22<>K22))>=3), "Highly Volatile", AND(COUNTIF(H22:K22, G22)+1>=4, O22<55, P22<65), "Stronghold", AND(COUNTIF(H22:K22, G22)+1>=3, O22<70, P22<75), "Lean", AND(R22<>G22, ((H22=R22)+(J22=R22)+(K22=R22))>=2, O22<60, P22<70), "Opposition Lean", TRUE, "Battleground" ) -> Lean | G22: AAP | H22: INC | I22: AAP | J22: INC | K22: AAP | M22: SAD | N22: 26.13 | O22: {=_xlfn.XLOOKUP(B22, 'Assembly Competitiveness'!$B$4:$B$120,'Assembly Competitiveness'!$O$4:$O$120, "-")} -> 0.668 | P22: {=_xlfn.XLOOKUP(B22,'Assembly Volatality'!$B$4:$B$120,'Assembly Volatality'!$L$4:$L$120, "-")} -> 34.34 | Q22: =ROUND(0.45*O22+0.4*P22+0.15*IF(H22<>K22,100,0),1) -> 29 | R22: SAD | T22: =IFS( AND(G22="AAP", OR(F22="Stronghold", F22="Lean")), "Defend", OR( AND(G22="AAP", OR(F22="Battleground", F22="Highly Volatile", F22="Opposition Lean")), AND(R22="AAP", OR(F22="Battleground", F22="Highly Volatile", F22="Opposition Lean")) ), "Battleground", OR(K22="AAP", M22="AAP", R22="AAP"), "Expand", TRUE, "Long Shot" ) -> Defend | U22: =IFS( AND(G22="INC", OR(F22="Stronghold", F22="Lean")), "Defend", OR( AND(G22="INC", OR(F22="Battleground", F22="Highly Volatile", F22="Opposition Lean")), AND(R22="INC", OR(F22="Battleground", F22="Highly Volatile", F22="Opposition Lean")) ), "Battleground", OR(K22="INC", M22="INC", R22="INC"), "Expand", TRUE, "Long Shot" ) -> Long Shot | V22: =IFS( AND(G22="SAD", OR(F22="Stronghold", F22="Lean")), "Defend", OR( AND(G22="SAD", OR(F22="Battleground", F22="Highly Volatile", F22="Opposition Lean")), AND(R22="SAD", OR(F22="Battleground", F22="Highly Volatile", F22="Opposition Lean")) ), "Battleground", OR(K22="SAD", M22="SAD", R22="SAD"), "Expand", TRUE, "Long Shot" ) -> Expand | W22: =IFS( AND(G22="BJP", OR(F22="Stronghold", F22="Lean")), "Defend", OR( AND(G22="BJP", OR(F22="Battleground", F22="Highly Volatile", F22="Opposition Lean")), AND(R22="BJP", OR(F22="Battleground", F22="Highly Volatile", F22="Opposition Lean")) ), "Battleground", OR(K22="BJP", M22="BJP", R22="BJP"), "Expand", TRUE, "Long Shot" ) -> Long Shot | X22: =IFS(K22="EMERGING", "YES", COUNTIFS(T22:W22, "<>Long Shot", T22:W22, "<>") >= 3, "YES", TRUE, "")
A23: 20 | B23: Attari | C23: Amritsar | D23: Majha | E23: Jaswinder Singh | F23: =IFS( OR(P23>=75, ((H23<>J23)+(J23<>I23)+(I23<>K23))>=3), "Highly Volatile", AND(COUNTIF(H23:K23, G23)+1>=4, O23<55, P23<65), "Stronghold", AND(COUNTIF(H23:K23, G23)+1>=3, O23<70, P23<75), "Lean", AND(R23<>G23, ((H23=R23)+(J23=R23)+(K23=R23))>=2, O23<60, P23<70), "Opposition Lean", TRUE, "Battleground" ) -> Battleground | G23: AAP | H23: INC | I23: AAP | J23: INC | K23: INC | M23: SAD | N23: 15.61 | O23: {=_xlfn.XLOOKUP(B23, 'Assembly Competitiveness'!$B$4:$B$120,'Assembly Competitiveness'!$O$4:$O$120, "-")} -> 35.0615 | P23: {=_xlfn.XLOOKUP(B23,'Assembly Volatality'!$B$4:$B$120,'Assembly Volatality'!$L$4:$L$120, "-")} -> 54.91 | Q23: =ROUND(0.45*O23+0.4*P23+0.15*IF(H23<>K23,100,0),1) -> 37.7 | R23: SAD | S23: YES | T23: =IFS( AND(G23="AAP", OR(F23="Stronghold", F23="Lean")), "Defend", OR( AND(G23="AAP", OR(F23="Battleground", F23="Highly Volatile", F23="Opposition Lean")), AND(R23="AAP", OR(F23="Battleground", F23="Highly Volatile", F23="Opposition Lean")) ), "Battleground", OR(K23="AAP", M23="AAP", R23="AAP"), "Expand", TRUE, "Long Shot" ) -> Battleground | U23: =IFS( AND(G23="INC", OR(F23="Stronghold", F23="Lean")), "Defend", OR( AND(G23="INC", OR(F23="Battleground", F23="Highly Volatile", F23="Opposition Lean")), AND(R23="INC", OR(F23="Battleground", F23="Highly Volatile", F23="Opposition Lean")) ), "Battleground", OR(K23="INC", M23="INC", R23="INC"), "Expand", TRUE, "Long Shot" ) -> Expand | V23: =IFS( AND(G23="SAD", OR(F23="Stronghold", F23="Lean")), "Defend", OR( AND(G23="SAD", OR(F23="Battleground", F23="Highly Volatile", F23="Opposition Lean")), AND(R23="SAD", OR(F23="Battleground", F23="Highly Volatile", F23="Opposition Lean")) ), "Battleground", OR(K23="SAD", M23="SAD", R23="SAD"), "Expand", TRUE, "Long Shot" ) -> Battleground | W23: =IFS( AND(G23="BJP", OR(F23="Stronghold", F23="Lean")), "Defend", OR( AND(G23="BJP", OR(F23="Battleground", F23="Highly Volatile", F23="Opposition Lean")), AND(R23="BJP", OR(F23="Battleground", F23="Highly Volatile", F23="Opposition Lean")) ), "Battleground", OR(K23="BJP", M23="BJP", R23="BJP"), "Expand", TRUE, "Long Shot" ) -> Long Shot | X23: =IFS(K23="EMERGING", "YES", COUNTIFS(T23:W23, "<>Long Shot", T23:W23, "<>") >= 3, "YES", TRUE, "") -> YES
A24: 21 | B24: Tarn Taran | C24: Tarn Taran | D24: Majha | E24: Harmeet Singh Sandhu | F24: =IFS( OR(P24>=75, ((H24<>J24)+(J24<>I24)+(I24<>K24))>=3), "Highly Volatile", AND(COUNTIF(H24:K24, G24)+1>=4, O24<55, P24<65), "Stronghold", AND(COUNTIF(H24:K24, G24)+1>=3, O24<70, P24<75), "Lean", AND(R24<>G24, ((H24=R24)+(J24=R24)+(K24=R24))>=2, O24<60, P24<70), "Opposition Lean", TRUE, "Battleground" ) -> Battleground | G24: AAP | H24: INC | I24: AAP | J24: INC | K24: EMERGING | L24: 2025 bypoll - AAP retained | M24: SAD | N24: 10.48 | O24: {=_xlfn.XLOOKUP(B24, 'Assembly Competitiveness'!$B$4:$B$120,'Assembly Competitiveness'!$O$4:$O$120, "-")} -> 45.068 | P24: {=_xlfn.XLOOKUP(B24,'Assembly Volatality'!$B$4:$B$120,'Assembly Volatality'!$L$4:$L$120, "-")} -> 53.93 | Q24: =ROUND(0.45*O24+0.4*P24+0.15*IF(H24<>K24,100,0),1) -> 56.9 | R24: SAD | S24: YES | T24: =IFS( AND(G24="AAP", OR(F24="Stronghold", F24="Lean")), "Defend", OR( AND(G24="AAP", OR(F24="Battleground", F24="Highly Volatile", F24="Opposition Lean")), AND(R24="AAP", OR(F24="Battleground", F24="Highly Volatile", F24="Opposition Lean")) ), "Battleground", OR(K24="AAP", M24="AAP", R24="AAP"), "Expand", TRUE, "Long Shot" ) -> Battleground | U24: =IFS( AND(G24="INC", OR(F24="Stronghold", F24="Lean")), "Defend", OR( AND(G24="INC", OR(F24="Battleground", F24="Highly Volatile", F24="Opposition Lean")), AND(R24="INC", OR(F24="Battleground", F24="Highly Volatile", F24="Opposition Lean")) ), "Battleground", OR(K24="INC", M24="INC", R24="INC"), "Expand", TRUE, "Long Shot" ) -> Long Shot | V24: =IFS( AND(G24="SAD", OR(F24="Stronghold", F24="Lean")), "Defend", OR( AND(G24="SAD", OR(F24="Battleground", F24="Highly Volatile", F24="Opposition Lean")), AND(R24="SAD", OR(F24="Battleground", F24="Highly Volatile", F24="Opposition Lean")) ), "Battleground", OR(K24="SAD", M24="SAD", R24="SAD"), "Expand", TRUE, "Long Shot" ) -> Battleground | W24: =IFS( AND(G24="BJP", OR(F24="Stronghold", F24="Lean")), "Defend", OR( AND(G24="BJP", OR(F24="Battleground", F24="Highly Volatile", F24="Opposition Lean")), AND(R24="BJP", OR(F24="Battleground", F24="Highly Volatile", F24="Opposition Lean")) ), "Battleground", OR(K24="BJP", M24="BJP", R24="BJP"), "Expand", TRUE, "Long Shot" ) -> Long Shot | X24: =IFS(K24="EMERGING", "YES", COUNTIFS(T24:W24, "<>Long Shot", T24:W24, "<>") >= 3, "YES", TRUE, "") -> YES
A25: 22 | B25: Khem Karan | C25: Tarn Taran | D25: Majha | E25: Sarvan Singh Dhun | F25: =IFS( OR(P25>=75, ((H25<>J25)+(J25<>I25)+(I25<>K25))>=3), "Highly Volatile", AND(COUNTIF(H25:K25, G25)+1>=4, O25<55, P25<65), "Stronghold", AND(COUNTIF(H25:K25, G25)+1>=3, O25<70, P25<75), "Lean", AND(R25<>G25, ((H25=R25)+(J25=R25)+(K25=R25))>=2, O25<60, P25<70), "Opposition Lean", TRUE, "Battleground" ) -> Battleground | G25: AAP | H25: INC | I25: AAP | J25: INC | K25: EMERGING | M25: SAD | N25: 7.76 | O25: {=_xlfn.XLOOKUP(B25, 'Assembly Competitiveness'!$B$4:$B$120,'Assembly Competitiveness'!$O$4:$O$120, "-")} -> 46.75 | P25: {=_xlfn.XLOOKUP(B25,'Assembly Volatality'!$B$4:$B$120,'Assembly Volatality'!$L$4:$L$120, "-")} -> 50.78 | Q25: =ROUND(0.45*O25+0.4*P25+0.15*IF(H25<>K25,100,0),1) -> 56.3 | R25: SAD | S25: YES | T25: =IFS( AND(G25="AAP", OR(F25="Stronghold", F25="Lean")), "Defend", OR( AND(G25="AAP", OR(F25="Battleground", F25="Highly Volatile", F25="Opposition Lean")), AND(R25="AAP", OR(F25="Battleground", F25="Highly Volatile", F25="Opposition Lean")) ), "Battleground", OR(K25="AAP", M25="AAP", R25="AAP"), "Expand", TRUE, "Long Shot" ) -> Battleground | U25: =IFS( AND(G25="INC", OR(F25="Stronghold", F25="Lean")), "Defend", OR( AND(G25="INC", OR(F25="Battleground", F25="Highly Volatile", F25="Opposition Lean")), AND(R25="INC", OR(F25="Battleground", F25="Highly Volatile", F25="Opposition Lean")) ), "Battleground", OR(K25="INC", M25="INC", R25="INC"), "Expand", TRUE, "Long Shot" ) -> Long Shot | V25: =IFS( AND(G25="SAD", OR(F25="Stronghold", F25="Lean")), "Defend", OR( AND(G25="SAD", OR(F25="Battleground", F25="Highly Volatile", F25="Opposition Lean")), AND(R25="SAD", OR(F25="Battleground", F25="Highly Volatile", F25="Opposition Lean")) ), "Battleground", OR(K25="SAD", M25="SAD", R25="SAD"), "Expand", TRUE, "Long Shot" ) -> Battleground | W25: =IFS( AND(G25="BJP", OR(F25="Stronghold", F25="Lean")), "Defend", OR( AND(G25="BJP", OR(F25="Battleground", F25="Highly Volatile", F25="Opposition Lean")), AND(R25="BJP", OR(F25="Battleground", F25="Highly Volatile", F25="Opposition Lean")) ), "Battleground", OR(K25="BJP", M25="BJP", R25="BJP"), "Expand", TRUE, "Long Shot" ) -> Long Shot | X25: =IFS(K25="EMERGING", "YES", COUNTIFS(T25:W25, "<>Long Shot", T25:W25, "<>") >= 3, "YES", TRUE, "") -> YES
A26: 23 | B26: Patti | C26: Tarn Taran | D26: Majha | E26: Laljit Singh Bhullar | F26: =IFS( OR(P26>=75, ((H26<>J26)+(J26<>I26)+(I26<>K26))>=3), "Highly Volatile", AND(COUNTIF(H26:K26, G26)+1>=4, O26<55, P26<65), "Stronghold", AND(COUNTIF(H26:K26, G26)+1>=3, O26<70, P26<75), "Lean", AND(R26<>G26, ((H26=R26)+(J26=R26)+(K26=R26))>=2, O26<60, P26<70), "Opposition Lean", TRUE, "Battleground" ) -> Battleground | G26: AAP | H26: INC | I26: AAP | J26: INC | K26: EMERGING | M26: SAD | N26: 7.65 | O26: {=_xlfn.XLOOKUP(B26, 'Assembly Competitiveness'!$B$4:$B$120,'Assembly Competitiveness'!$O$4:$O$120, "-")} -> 52.6435 | P26: {=_xlfn.XLOOKUP(B26,'Assembly Volatality'!$B$4:$B$120,'Assembly Volatality'!$L$4:$L$120, "-")} -> 46.03 | Q26: =ROUND(0.45*O26+0.4*P26+0.15*IF(H26<>K26,100,0),1) -> 57.1 | R26: SAD | S26: YES | T26: =IFS( AND(G26="AAP", OR(F26="Stronghold", F26="Lean")), "Defend", OR( AND(G26="AAP", OR(F26="Battleground", F26="Highly Volatile", F26="Opposition Lean")), AND(R26="AAP", OR(F26="Battleground", F26="Highly Volatile", F26="Opposition Lean")) ), "Battleground", OR(K26="AAP", M26="AAP", R26="AAP"), "Expand", TRUE, "Long Shot" ) -> Battleground | U26: =IFS( AND(G26="INC", OR(F26="Stronghold", F26="Lean")), "Defend", OR( AND(G26="INC", OR(F26="Battleground", F26="Highly Volatile", F26="Opposition Lean")), AND(R26="INC", OR(F26="Battleground", F26="Highly Volatile", F26="Opposition Lean")) ), "Battleground", OR(K26="INC", M26="INC", R26="INC"), "Expand", TRUE, "Long Shot" ) -> Long Shot | V26: =IFS( AND(G26="SAD", OR(F26="Stronghold", F26="Lean")), "Defend", OR( AND(G26="SAD", OR(F26="Battleground", F26="Highly Volatile", F26="Opposition Lean")), AND(R26="SAD", OR(F26="Battleground", F26="Highly Volatile", F26="Opposition Lean")) ), "Battleground", OR(K26="SAD", M26="SAD", R26="SAD"), "Expand", TRUE, "Long Shot" ) -> Battleground | W26: =IFS( AND(G26="BJP", OR(F26="Stronghold", F26="Lean")), "Defend", OR( AND(G26="BJP", OR(F26="Battleground", F26="Highly Volatile", F26="Opposition Lean")), AND(R26="BJP", OR(F26="Battleground", F26="Highly Volatile", F26="Opposition Lean")) ), "Battleground", OR(K26="BJP", M26="BJP", R26="BJP"), "Expand", TRUE, "Long Shot" ) -> Long Shot | X26: =IFS(K26="EMERGING", "YES", COUNTIFS(T26:W26, "<>Long Shot", T26:W26, "<>") >= 3, "YES", TRUE, "") -> YES
A27: 24 | B27: Khadoor Sahib | C27: Tarn Taran | D27: Majha | E27: Manjinder Singh Lalpura | F27: =IFS( OR(P27>=75, ((H27<>J27)+(J27<>I27)+(I27<>K27))>=3), "Highly Volatile", AND(COUNTIF(H27:K27, G27)+1>=4, O27<55, P27<65), "Stronghold", AND(COUNTIF(H27:K27, G27)+1>=3, O27<70, P27<75), "Lean", AND(R27<>G27, ((H27=R27)+(J27=R27)+(K27=R27))>=2, O27<60, P27<70), "Opposition Lean", TRUE, "Battleground" ) -> Opposition Lean | G27: AAP | H27: INC | I27: AAP | J27: INC | K27: EMERGING | M27: INC | N27: 11.44 | O27: {=_xlfn.XLOOKUP(B27, 'Assembly Competitiveness'!$B$4:$B$120,'Assembly Competitiveness'!$O$4:$O$120, "-")} -> 37.652 | P27: {=_xlfn.XLOOKUP(B27,'Assembly Volatality'!$B$4:$B$120,'Assembly Volatality'!$L$4:$L$120, "-")} -> 43.79 | Q27: =ROUND(0.45*O27+0.4*P27+0.15*IF(H27<>K27,100,0),1) -> 49.5 | R27: INC | S27: YES | T27: =IFS( AND(G27="AAP", OR(F27="Stronghold", F27="Lean")), "Defend", OR( AND(G27="AAP", OR(F27="Battleground", F27="Highly Volatile", F27="Opposition Lean")), AND(R27="AAP", OR(F27="Battleground", F27="Highly Volatile", F27="Opposition Lean")) ), "Battleground", OR(K27="AAP", M27="AAP", R27="AAP"), "Expand", TRUE, "Long Shot" ) -> Battleground | U27: =IFS( AND(G27="INC", OR(F27="Stronghold", F27="Lean")), "Defend", OR( AND(G27="INC", OR(F27="Battleground", F27="Highly Volatile", F27="Opposition Lean")), AND(R27="INC", OR(F27="Battleground", F27="Highly Volatile", F27="Opposition Lean")) ), "Battleground", OR(K27="INC", M27="INC", R27="INC"), "Expand", TRUE, "Long Shot" ) -> Battleground | V27: =IFS( AND(G27="SAD", OR(F27="Stronghold", F27="Lean")), "Defend", OR( AND(G27="SAD", OR(F27="Battleground", F27="Highly Volatile", F27="Opposition Lean")), AND(R27="SAD", OR(F27="Battleground", F27="Highly Volatile", F27="Opposition Lean")) ), "Battleground", OR(K27="SAD", M27="SAD", R27="SAD"), "Expand", TRUE, "Long Shot" ) -> Long Shot | W27: =IFS( AND(G27="BJP", OR(F27="Stronghold", F27="Lean")), "Defend", OR( AND(G27="BJP", OR(F27="Battleground", F27="Highly Volatile", F27="Opposition Lean")), AND(R27="BJP", OR(F27="Battleground", F27="Highly Volatile", F27="Opposition Lean")) ), "Battleground", OR(K27="BJP", M27="BJP", R27="BJP"), "Expand", TRUE, "Long Shot" ) -> Long Shot | X27: =IFS(K27="EMERGING", "YES", COUNTIFS(T27:W27, "<>Long Shot", T27:W27, "<>") >= 3, "YES", TRUE, "") -> YES
A28: 25 | B28: Baba Bakala | C28: Amritsar | D28: Majha | E28: Dalbir Singh Tong | F28: =IFS( OR(P28>=75, ((H28<>J28)+(J28<>I28)+(I28<>K28))>=3), "Highly Volatile", AND(COUNTIF(H28:K28, G28)+1>=4, O28<55, P28<65), "Stronghold", AND(COUNTIF(H28:K28, G28)+1>=3, O28<70, P28<75), "Lean", AND(R28<>G28, ((H28=R28)+(J28=R28)+(K28=R28))>=2, O28<60, P28<70), "Opposition Lean", TRUE, "Battleground" ) -> Opposition Lean | G28: AAP | H28: INC | I28: AAP | J28: INC | K28: EMERGING | M28: INC | N28: 15 | O28: {=_xlfn.XLOOKUP(B28, 'Assembly Competitiveness'!$B$4:$B$120,'Assembly Competitiveness'!$O$4:$O$120, "-")} -> 40.138 | P28: {=_xlfn.XLOOKUP(B28,'Assembly Volatality'!$B$4:$B$120,'Assembly Volatality'!$L$4:$L$120, "-")} -> 53.84 | Q28: =ROUND(0.45*O28+0.4*P28+0.15*IF(H28<>K28,100,0),1) -> 54.6 | R28: INC | S28: YES | T28: =IFS( AND(G28="AAP", OR(F28="Stronghold", F28="Lean")), "Defend", OR( AND(G28="AAP", OR(F28="Battleground", F28="Highly Volatile", F28="Opposition Lean")), AND(R28="AAP", OR(F28="Battleground", F28="Highly Volatile", F28="Opposition Lean")) ), "Battleground", OR(K28="AAP", M28="AAP", R28="AAP"), "Expand", TRUE, "Long Shot" ) -> Battleground | U28: =IFS( AND(G28="INC", OR(F28="Stronghold", F28="Lean")), "Defend", OR( AND(G28="INC", OR(F28="Battleground", F28="Highly Volatile", F28="Opposition Lean")), AND(R28="INC", OR(F28="Battleground", F28="Highly Volatile", F28="Opposition Lean")) ), "Battleground", OR(K28="INC", M28="INC", R28="INC"), "Expand", TRUE, "Long Shot" ) -> Battleground | V28: =IFS( AND(G28="SAD", OR(F28="Stronghold", F28="Lean")), "Defend", OR( AND(G28="SAD", OR(F28="Battleground", F28="Highly Volatile", F28="Opposition Lean")), AND(R28="SAD", OR(F28="Battleground", F28="Highly Volatile", F28="Opposition Lean")) ), "Battleground", OR(K28="SAD", M28="SAD", R28="SAD"), "Expand", TRUE, "Long Shot" ) -> Long Shot | W28: =IFS( AND(G28="BJP", OR(F28="Stronghold", F28="Lean")), "Defend", OR( AND(G28="BJP", OR(F28="Battleground", F28="Highly Volatile", F28="Opposition Lean")), AND(R28="BJP", OR(F28="Battleground", F28="Highly Volatile", F28="Opposition Lean")) ), "Battleground", OR(K28="BJP", M28="BJP", R28="BJP"), "Expand", TRUE, "Long Shot" ) -> Long Shot | X28: =IFS(K28="EMERGING", "YES", COUNTIFS(T28:W28, "<>Long Shot", T28:W28, "<>") >= 3, "YES", TRUE, "") -> YES
A29: 26 | B29: Bholath | C29: Kapurthala | D29: Doaba | E29: Sukhpal Singh Khaira | F29: =IFS( OR(P29>=75, ((H29<>J29)+(J29<>I29)+(I29<>K29))>=3), "Highly Volatile", AND(COUNTIF(H29:K29, G29)+1>=4, O29<55, P29<65), "Stronghold", AND(COUNTIF(H29:K29, G29)+1>=3, O29<70, P29<75), "Lean", AND(R29<>G29, ((H29=R29)+(J29=R29)+(K29=R29))>=2, O29<60, P29<70), "Opposition Lean", TRUE, "Battleground" ) -> Lean | G29: INC | H29: AAP | I29: INC | J29: INC | K29: AAP | M29: SAD | N29: 10.27 | O29: {=_xlfn.XLOOKUP(B29, 'Assembly Competitiveness'!$B$4:$B$120,'Assembly Competitiveness'!$O$4:$O$120, "-")} -> 44.2265 | P29: {=_xlfn.XLOOKUP(B29,'Assembly Volatality'!$B$4:$B$120,'Assembly Volatality'!$L$4:$L$120, "-")} -> 50.3 | Q29: =ROUND(0.45*O29+0.4*P29+0.15*IF(H29<>K29,100,0),1) -> 40 | R29: SAD | S29: YES | T29: =IFS( AND(G29="AAP", OR(F29="Stronghold", F29="Lean")), "Defend", OR( AND(G29="AAP", OR(F29="Battleground", F29="Highly Volatile", F29="Opposition Lean")), AND(R29="AAP", OR(F29="Battleground", F29="Highly Volatile", F29="Opposition Lean")) ), "Battleground", OR(K29="AAP", M29="AAP", R29="AAP"), "Expand", TRUE, "Long Shot" ) -> Expand | U29: =IFS( AND(G29="INC", OR(F29="Stronghold", F29="Lean")), "Defend", OR( AND(G29="INC", OR(F29="Battleground", F29="Highly Volatile", F29="Opposition Lean")), AND(R29="INC", OR(F29="Battleground", F29="Highly Volatile", F29="Opposition Lean")) ), "Battleground", OR(K29="INC", M29="INC", R29="INC"), "Expand", TRUE, "Long Shot" ) -> Defend | V29: =IFS( AND(G29="SAD", OR(F29="Stronghold", F29="Lean")), "Defend", OR( AND(G29="SAD", OR(F29="Battleground", F29="Highly Volatile", F29="Opposition Lean")), AND(R29="SAD", OR(F29="Battleground", F29="Highly Volatile", F29="Opposition Lean")) ), "Battleground", OR(K29="SAD", M29="SAD", R29="SAD"), "Expand", TRUE, "Long Shot" ) -> Expand | W29: =IFS( AND(G29="BJP", OR(F29="Stronghold", F29="Lean")), "Defend", OR( AND(G29="BJP", OR(F29="Battleground", F29="Highly Volatile", F29="Opposition Lean")), AND(R29="BJP", OR(F29="Battleground", F29="Highly Volatile", F29="Opposition Lean")) ), "Battleground", OR(K29="BJP", M29="BJP", R29="BJP"), "Expand", TRUE, "Long Shot" ) -> Long Shot | X29: =IFS(K29="EMERGING", "YES", COUNTIFS(T29:W29, "<>Long Shot", T29:W29, "<>") >= 3, "YES", TRUE, "") -> YES
A30: 27 | B30: Kapurthala | C30: Kapurthala | D30: Doaba | E30: Rana Gurjeet Singh | F30: =IFS( OR(P30>=75, ((H30<>J30)+(J30<>I30)+(I30<>K30))>=3), "Highly Volatile", AND(COUNTIF(H30:K30, G30)+1>=4, O30<55, P30<65), "Stronghold", AND(COUNTIF(H30:K30, G30)+1>=3, O30<70, P30<75), "Lean", AND(R30<>G30, ((H30=R30)+(J30=R30)+(K30=R30))>=2, O30<60, P30<70), "Opposition Lean", TRUE, "Battleground" ) -> Stronghold | G30: INC | H30: INC | I30: INC | J30: INC | K30: INC | M30: AAP | N30: 7.16 | O30: {=_xlfn.XLOOKUP(B30, 'Assembly Competitiveness'!$B$4:$B$120,'Assembly Competitiveness'!$O$4:$O$120, "-")} -> 37.014 | P30: {=_xlfn.XLOOKUP(B30,'Assembly Volatality'!$B$4:$B$120,'Assembly Volatality'!$L$4:$L$120, "-")} -> 26.13 | Q30: =ROUND(0.45*O30+0.4*P30+0.15*IF(H30<>K30,100,0),1) -> 27.1 | R30: AAP | T30: =IFS( AND(G30="AAP", OR(F30="Stronghold", F30="Lean")), "Defend", OR( AND(G30="AAP", OR(F30="Battleground", F30="Highly Volatile", F30="Opposition Lean")), AND(R30="AAP", OR(F30="Battleground", F30="Highly Volatile", F30="Opposition Lean")) ), "Battleground", OR(K30="AAP", M30="AAP", R30="AAP"), "Expand", TRUE, "Long Shot" ) -> Expand | U30: =IFS( AND(G30="INC", OR(F30="Stronghold", F30="Lean")), "Defend", OR( AND(G30="INC", OR(F30="Battleground", F30="Highly Volatile", F30="Opposition Lean")), AND(R30="INC", OR(F30="Battleground", F30="Highly Volatile", F30="Opposition Lean")) ), "Battleground", OR(K30="INC", M30="INC", R30="INC"), "Expand", TRUE, "Long Shot" ) -> Defend | V30: =IFS( AND(G30="SAD", OR(F30="Stronghold", F30="Lean")), "Defend", OR( AND(G30="SAD", OR(F30="Battleground", F30="Highly Volatile", F30="Opposition Lean")), AND(R30="SAD", OR(F30="Battleground", F30="Highly Volatile", F30="Opposition Lean")) ), "Battleground", OR(K30="SAD", M30="SAD", R30="SAD"), "Expand", TRUE, "Long Shot" ) -> Long Shot | W30: =IFS( AND(G30="BJP", OR(F30="Stronghold", F30="Lean")), "Defend", OR( AND(G30="BJP", OR(F30="Battleground", F30="Highly Volatile", F30="Opposition Lean")), AND(R30="BJP", OR(F30="Battleground", F30="Highly Volatile", F30="Opposition Lean")) ), "Battleground", OR(K30="BJP", M30="BJP", R30="BJP"), "Expand", TRUE, "Long Shot" ) -> Long Shot | X30: =IFS(K30="EMERGING", "YES", COUNTIFS(T30:W30, "<>Long Shot", T30:W30, "<>") >= 3, "YES", TRUE, "")
A31: 28 | B31: Sultanpur Lodhi | C31: Kapurthala | D31: Doaba | E31: Rana Inder Partap Singh | F31: =IFS( OR(P31>=75, ((H31<>J31)+(J31<>I31)+(I31<>K31))>=3), "Highly Volatile", AND(COUNTIF(H31:K31, G31)+1>=4, O31<55, P31<65), "Stronghold", AND(COUNTIF(H31:K31, G31)+1>=3, O31<70, P31<75), "Lean", AND(R31<>G31, ((H31=R31)+(J31=R31)+(K31=R31))>=2, O31<60, P31<70), "Opposition Lean", TRUE, "Battleground" ) -> Lean | G31: EMERGING | H31: INC | I31: EMERGING | J31: INC | K31: EMERGING | M31: AAP | N31: 10.65 | O31: {=_xlfn.XLOOKUP(B31, 'Assembly Competitiveness'!$B$4:$B$120,'Assembly Competitiveness'!$O$4:$O$120, "-")} -> 34.6995 | P31: {=_xlfn.XLOOKUP(B31,'Assembly Volatality'!$B$4:$B$120,'Assembly Volatality'!$L$4:$L$120, "-")} -> 36.78 | Q31: =ROUND(0.45*O31+0.4*P31+0.15*IF(H31<>K31,100,0),1) -> 45.3 | R31: AAP | T31: =IFS( AND(G31="AAP", OR(F31="Stronghold", F31="Lean")), "Defend", OR( AND(G31="AAP", OR(F31="Battleground", F31="Highly Volatile", F31="Opposition Lean")), AND(R31="AAP", OR(F31="Battleground", F31="Highly Volatile", F31="Opposition Lean")) ), "Battleground", OR(K31="AAP", M31="AAP", R31="AAP"), "Expand", TRUE, "Long Shot" ) -> Expand | U31: =IFS( AND(G31="INC", OR(F31="Stronghold", F31="Lean")), "Defend", OR( AND(G31="INC", OR(F31="Battleground", F31="Highly Volatile", F31="Opposition Lean")), AND(R31="INC", OR(F31="Battleground", F31="Highly Volatile", F31="Opposition Lean")) ), "Battleground", OR(K31="INC", M31="INC", R31="INC"), "Expand", TRUE, "Long Shot" ) -> Long Shot | V31: =IFS( AND(G31="SAD", OR(F31="Stronghold", F31="Lean")), "Defend", OR( AND(G31="SAD", OR(F31="Battleground", F31="Highly Volatile", F31="Opposition Lean")), AND(R31="SAD", OR(F31="Battleground", F31="Highly Volatile", F31="Opposition Lean")) ), "Battleground", OR(K31="SAD", M31="SAD", R31="SAD"), "Expand", TRUE, "Long Shot" ) -> Long Shot | W31: =IFS( AND(G31="BJP", OR(F31="Stronghold", F31="Lean")), "Defend", OR( AND(G31="BJP", OR(F31="Battleground", F31="Highly Volatile", F31="Opposition Lean")), AND(R31="BJP", OR(F31="Battleground", F31="Highly Volatile", F31="Opposition Lean")) ), "Battleground", OR(K31="BJP", M31="BJP", R31="BJP"), "Expand", TRUE, "Long Shot" ) -> Long Shot | X31: =IFS(K31="EMERGING", "YES", COUNTIFS(T31:W31, "<>Long Shot", T31:W31, "<>") >= 3, "YES", TRUE, "") -> YES
A32: 29 | B32: Phagwara | C32: Kapurthala | D32: Doaba | E32: Balwinder Singh Dhaliwal | F32: =IFS( OR(P32>=75, ((H32<>J32)+(J32<>I32)+(I32<>K32))>=3), "Highly Volatile", AND(COUNTIF(H32:K32, G32)+1>=4, O32<55, P32<65), "Stronghold", AND(COUNTIF(H32:K32, G32)+1>=3, O32<70, P32<75), "Lean", AND(R32<>G32, ((H32=R32)+(J32=R32)+(K32=R32))>=2, O32<60, P32<70), "Opposition Lean", TRUE, "Battleground" ) -> Battleground | G32: INC | H32: BJP | I32: INC | J32: BJP | K32: AAP | M32: AAP | N32: 2.14 | O32: {=_xlfn.XLOOKUP(B32, 'Assembly Competitiveness'!$B$4:$B$120,'Assembly Competitiveness'!$O$4:$O$120, "-")} -> 68.857 | P32: {=_xlfn.XLOOKUP(B32,'Assembly Volatality'!$B$4:$B$120,'Assembly Volatality'!$L$4:$L$120, "-")} -> 46.49 | Q32: =ROUND(0.45*O32+0.4*P32+0.15*IF(H32<>K32,100,0),1) -> 64.6 | R32: AAP | S32: YES | T32: =IFS( AND(G32="AAP", OR(F32="Stronghold", F32="Lean")), "Defend", OR( AND(G32="AAP", OR(F32="Battleground", F32="Highly Volatile", F32="Opposition Lean")), AND(R32="AAP", OR(F32="Battleground", F32="Highly Volatile", F32="Opposition Lean")) ), "Battleground", OR(K32="AAP", M32="AAP", R32="AAP"), "Expand", TRUE, "Long Shot" ) -> Battleground | U32: =IFS( AND(G32="INC", OR(F32="Stronghold", F32="Lean")), "Defend", OR( AND(G32="INC", OR(F32="Battleground", F32="Highly Volatile", F32="Opposition Lean")), AND(R32="INC", OR(F32="Battleground", F32="Highly Volatile", F32="Opposition Lean")) ), "Battleground", OR(K32="INC", M32="INC", R32="INC"), "Expand", TRUE, "Long Shot" ) -> Battleground | V32: =IFS( AND(G32="SAD", OR(F32="Stronghold", F32="Lean")), "Defend", OR( AND(G32="SAD", OR(F32="Battleground", F32="Highly Volatile", F32="Opposition Lean")), AND(R32="SAD", OR(F32="Battleground", F32="Highly Volatile", F32="Opposition Lean")) ), "Battleground", OR(K32="SAD", M32="SAD", R32="SAD"), "Expand", TRUE, "Long Shot" ) -> Long Shot | W32: =IFS( AND(G32="BJP", OR(F32="Stronghold", F32="Lean")), "Defend", OR( AND(G32="BJP", OR(F32="Battleground", F32="Highly Volatile", F32="Opposition Lean")), AND(R32="BJP", OR(F32="Battleground", F32="Highly Volatile", F32="Opposition Lean")) ), "Battleground", OR(K32="BJP", M32="BJP", R32="BJP"), "Expand", TRUE, "Long Shot" ) -> Long Shot | X32: =IFS(K32="EMERGING", "YES", COUNTIFS(T32:W32, "<>Long Shot", T32:W32, "<>") >= 3, "YES", TRUE, "")
A33: 30 | B33: Phillaur | C33: Jalandhar | D33: Doaba | E33: Vikramjit Singh Chaudhary | F33: =IFS( OR(P33>=75, ((H33<>J33)+(J33<>I33)+(I33<>K33))>=3), "Highly Volatile", AND(COUNTIF(H33:K33, G33)+1>=4, O33<55, P33<65), "Stronghold", AND(COUNTIF(H33:K33, G33)+1>=3, O33<70, P33<75), "Lean", AND(R33<>G33, ((H33=R33)+(J33=R33)+(K33=R33))>=2, O33<60, P33<70), "Opposition Lean", TRUE, "Battleground" ) -> Stronghold | G33: INC | H33: SAD | I33: INC | J33: INC | K33: INC | M33: SAD | N33: 8.85 | O33: {=_xlfn.XLOOKUP(B33, 'Assembly Competitiveness'!$B$4:$B$120,'Assembly Competitiveness'!$O$4:$O$120, "-")} -> 45.2955 | P33: {=_xlfn.XLOOKUP(B33,'Assembly Volatality'!$B$4:$B$120,'Assembly Volatality'!$L$4:$L$120, "-")} -> 44.25 | Q33: =ROUND(0.45*O33+0.4*P33+0.15*IF(H33<>K33,100,0),1) -> 53.1 | R33: SAD | T33: =IFS( AND(G33="AAP", OR(F33="Stronghold", F33="Lean")), "Defend", OR( AND(G33="AAP", OR(F33="Battleground", F33="Highly Volatile", F33="Opposition Lean")), AND(R33="AAP", OR(F33="Battleground", F33="Highly Volatile", F33="Opposition Lean")) ), "Battleground", OR(K33="AAP", M33="AAP", R33="AAP"), "Expand", TRUE, "Long Shot" ) -> Long Shot | U33: =IFS( AND(G33="INC", OR(F33="Stronghold", F33="Lean")), "Defend", OR( AND(G33="INC", OR(F33="Battleground", F33="Highly Volatile", F33="Opposition Lean")), AND(R33="INC", OR(F33="Battleground", F33="Highly Volatile", F33="Opposition Lean")) ), "Battleground", OR(K33="INC", M33="INC", R33="INC"), "Expand", TRUE, "Long Shot" ) -> Defend | V33: =IFS( AND(G33="SAD", OR(F33="Stronghold", F33="Lean")), "Defend", OR( AND(G33="SAD", OR(F33="Battleground", F33="Highly Volatile", F33="Opposition Lean")), AND(R33="SAD", OR(F33="Battleground", F33="Highly Volatile", F33="Opposition Lean")) ), "Battleground", OR(K33="SAD", M33="SAD", R33="SAD"), "Expand", TRUE, "Long Shot" ) -> Expand | W33: =IFS( AND(G33="BJP", OR(F33="Stronghold", F33="Lean")), "Defend", OR( AND(G33="BJP", OR(F33="Battleground", F33="Highly Volatile", F33="Opposition Lean")), AND(R33="BJP", OR(F33="Battleground", F33="Highly Volatile", F33="Opposition Lean")) ), "Battleground", OR(K33="BJP", M33="BJP", R33="BJP"), "Expand", TRUE, "Long Shot" ) -> Long Shot | X33: =IFS(K33="EMERGING", "YES", COUNTIFS(T33:W33, "<>Long Shot", T33:W33, "<>") >= 3, "YES", TRUE, "")
A34: 31 | B34: Nakodar | C34: Jalandhar | D34: Doaba | E34: Inderjit Kaur Mann | F34: =IFS( OR(P34>=75, ((H34<>J34)+(J34<>I34)+(I34<>K34))>=3), "Highly Volatile", AND(COUNTIF(H34:K34, G34)+1>=4, O34<55, P34<65), "Stronghold", AND(COUNTIF(H34:K34, G34)+1>=3, O34<70, P34<75), "Lean", AND(R34<>G34, ((H34=R34)+(J34=R34)+(K34=R34))>=2, O34<60, P34<70), "Opposition Lean", TRUE, "Battleground" ) -> Battleground | G34: AAP | H34: SAD | I34: AAP | J34: SAD | K34: INC | M34: SAD | N34: 2.16 | O34: {=_xlfn.XLOOKUP(B34, 'Assembly Competitiveness'!$B$4:$B$120,'Assembly Competitiveness'!$O$4:$O$120, "-")} -> 61.512 | P34: {=_xlfn.XLOOKUP(B34,'Assembly Volatality'!$B$4:$B$120,'Assembly Volatality'!$L$4:$L$120, "-")} -> 58.83 | Q34: =ROUND(0.45*O34+0.4*P34+0.15*IF(H34<>K34,100,0),1) -> 66.2 | R34: SAD | S34: YES | T34: =IFS( AND(G34="AAP", OR(F34="Stronghold", F34="Lean")), "Defend", OR( AND(G34="AAP", OR(F34="Battleground", F34="Highly Volatile", F34="Opposition Lean")), AND(R34="AAP", OR(F34="Battleground", F34="Highly Volatile", F34="Opposition Lean")) ), "Battleground", OR(K34="AAP", M34="AAP", R34="AAP"), "Expand", TRUE, "Long Shot" ) -> Battleground | U34: =IFS( AND(G34="INC", OR(F34="Stronghold", F34="Lean")), "Defend", OR( AND(G34="INC", OR(F34="Battleground", F34="Highly Volatile", F34="Opposition Lean")), AND(R34="INC", OR(F34="Battleground", F34="Highly Volatile", F34="Opposition Lean")) ), "Battleground", OR(K34="INC", M34="INC", R34="INC"), "Expand", TRUE, "Long Shot" ) -> Expand | V34: =IFS( AND(G34="SAD", OR(F34="Stronghold", F34="Lean")), "Defend", OR( AND(G34="SAD", OR(F34="Battleground", F34="Highly Volatile", F34="Opposition Lean")), AND(R34="SAD", OR(F34="Battleground", F34="Highly Volatile", F34="Opposition Lean")) ), "Battleground", OR(K34="SAD", M34="SAD", R34="SAD"), "Expand", TRUE, "Long Shot" ) -> Battleground | W34: =IFS( AND(G34="BJP", OR(F34="Stronghold", F34="Lean")), "Defend", OR( AND(G34="BJP", OR(F34="Battleground", F34="Highly Volatile", F34="Opposition Lean")), AND(R34="BJP", OR(F34="Battleground", F34="Highly Volatile", F34="Opposition Lean")) ), "Battleground", OR(K34="BJP", M34="BJP", R34="BJP"), "Expand", TRUE, "Long Shot" ) -> Long Shot | X34: =IFS(K34="EMERGING", "YES", COUNTIFS(T34:W34, "<>Long Shot", T34:W34, "<>") >= 3, "YES", TRUE, "") -> YES
A35: 32 | B35: Shahkot | C35: Jalandhar | D35: Doaba | E35: Hardev Singh Laddi | F35: =IFS( OR(P35>=75, ((H35<>J35)+(J35<>I35)+(I35<>K35))>=3), "Highly Volatile", AND(COUNTIF(H35:K35, G35)+1>=4, O35<55, P35<65), "Stronghold", AND(COUNTIF(H35:K35, G35)+1>=3, O35<70, P35<75), "Lean", AND(R35<>G35, ((H35=R35)+(J35=R35)+(K35=R35))>=2, O35<60, P35<70), "Opposition Lean", TRUE, "Battleground" ) -> Stronghold | G35: INC | H35: SAD | I35: INC | J35: INC | K35: INC | M35: SAD | N35: 9.18 | O35: {=_xlfn.XLOOKUP(B35, 'Assembly Competitiveness'!$B$4:$B$120,'Assembly Competitiveness'!$O$4:$O$120, "-")} -> 42.907 | P35: {=_xlfn.XLOOKUP(B35,'Assembly Volatality'!$B$4:$B$120,'Assembly Volatality'!$L$4:$L$120, "-")} -> 40.85 | Q35: =ROUND(0.45*O35+0.4*P35+0.15*IF(H35<>K35,100,0),1) -> 50.6 | R35: SAD | T35: =IFS( AND(G35="AAP", OR(F35="Stronghold", F35="Lean")), "Defend", OR( AND(G35="AAP", OR(F35="Battleground", F35="Highly Volatile", F35="Opposition Lean")), AND(R35="AAP", OR(F35="Battleground", F35="Highly Volatile", F35="Opposition Lean")) ), "Battleground", OR(K35="AAP", M35="AAP", R35="AAP"), "Expand", TRUE, "Long Shot" ) -> Long Shot | U35: =IFS( AND(G35="INC", OR(F35="Stronghold", F35="Lean")), "Defend", OR( AND(G35="INC", OR(F35="Battleground", F35="Highly Volatile", F35="Opposition Lean")), AND(R35="INC", OR(F35="Battleground", F35="Highly Volatile", F35="Opposition Lean")) ), "Battleground", OR(K35="INC", M35="INC", R35="INC"), "Expand", TRUE, "Long Shot" ) -> Defend | V35: =IFS( AND(G35="SAD", OR(F35="Stronghold", F35="Lean")), "Defend", OR( AND(G35="SAD", OR(F35="Battleground", F35="Highly Volatile", F35="Opposition Lean")), AND(R35="SAD", OR(F35="Battleground", F35="Highly Volatile", F35="Opposition Lean")) ), "Battleground", OR(K35="SAD", M35="SAD", R35="SAD"), "Expand", TRUE, "Long Shot" ) -> Expand | W35: =IFS( AND(G35="BJP", OR(F35="Stronghold", F35="Lean")), "Defend", OR( AND(G35="BJP", OR(F35="Battleground", F35="Highly Volatile", F35="Opposition Lean")), AND(R35="BJP", OR(F35="Battleground", F35="Highly Volatile", F35="Opposition Lean")) ), "Battleground", OR(K35="BJP", M35="BJP", R35="BJP"), "Expand", TRUE, "Long Shot" ) -> Long Shot | X35: =IFS(K35="EMERGING", "YES", COUNTIFS(T35:W35, "<>Long Shot", T35:W35, "<>") >= 3, "YES", TRUE, "")
A36: 33 | B36: Kartarpur | C36: Jalandhar | D36: Doaba | E36: Balkar Singh | F36: =IFS( OR(P36>=75, ((H36<>J36)+(J36<>I36)+(I36<>K36))>=3), "Highly Volatile", AND(COUNTIF(H36:K36, G36)+1>=4, O36<55, P36<65), "Stronghold", AND(COUNTIF(H36:K36, G36)+1>=3, O36<70, P36<75), "Lean", AND(R36<>G36, ((H36=R36)+(J36=R36)+(K36=R36))>=2, O36<60, P36<70), "Opposition Lean", TRUE, "Battleground" ) -> Battleground | G36: AAP | H36: INC | I36: AAP | J36: INC | K36: INC | M36: INC | N36: 3.69 | O36: {=_xlfn.XLOOKUP(B36, 'Assembly Competitiveness'!$B$4:$B$120,'Assembly Competitiveness'!$O$4:$O$120, "-")} -> 62.3355 | P36: {=_xlfn.XLOOKUP(B36,'Assembly Volatality'!$B$4:$B$120,'Assembly Volatality'!$L$4:$L$120, "-")} -> 46.79 | Q36: =ROUND(0.45*O36+0.4*P36+0.15*IF(H36<>K36,100,0),1) -> 46.8 | R36: INC | S36: YES | T36: =IFS( AND(G36="AAP", OR(F36="Stronghold", F36="Lean")), "Defend", OR( AND(G36="AAP", OR(F36="Battleground", F36="Highly Volatile", F36="Opposition Lean")), AND(R36="AAP", OR(F36="Battleground", F36="Highly Volatile", F36="Opposition Lean")) ), "Battleground", OR(K36="AAP", M36="AAP", R36="AAP"), "Expand", TRUE, "Long Shot" ) -> Battleground | U36: =IFS( AND(G36="INC", OR(F36="Stronghold", F36="Lean")), "Defend", OR( AND(G36="INC", OR(F36="Battleground", F36="Highly Volatile", F36="Opposition Lean")), AND(R36="INC", OR(F36="Battleground", F36="Highly Volatile", F36="Opposition Lean")) ), "Battleground", OR(K36="INC", M36="INC", R36="INC"), "Expand", TRUE, "Long Shot" ) -> Battleground | V36: =IFS( AND(G36="SAD", OR(F36="Stronghold", F36="Lean")), "Defend", OR( AND(G36="SAD", OR(F36="Battleground", F36="Highly Volatile", F36="Opposition Lean")), AND(R36="SAD", OR(F36="Battleground", F36="Highly Volatile", F36="Opposition Lean")) ), "Battleground", OR(K36="SAD", M36="SAD", R36="SAD"), "Expand", TRUE, "Long Shot" ) -> Long Shot | W36: =IFS( AND(G36="BJP", OR(F36="Stronghold", F36="Lean")), "Defend", OR( AND(G36="BJP", OR(F36="Battleground", F36="Highly Volatile", F36="Opposition Lean")), AND(R36="BJP", OR(F36="Battleground", F36="Highly Volatile", F36="Opposition Lean")) ), "Battleground", OR(K36="BJP", M36="BJP", R36="BJP"), "Expand", TRUE, "Long Shot" ) -> Long Shot | X36: =IFS(K36="EMERGING", "YES", COUNTIFS(T36:W36, "<>Long Shot", T36:W36, "<>") >= 3, "YES", TRUE, "")
A37: 34 | B37: Jalandhar West | C37: Jalandhar | D37: Doaba | E37: Sheetal Angural | F37: =IFS( OR(P37>=75, ((H37<>J37)+(J37<>I37)+(I37<>K37))>=3), "Highly Volatile", AND(COUNTIF(H37:K37, G37)+1>=4, O37<55, P37<65), "Stronghold", AND(COUNTIF(H37:K37, G37)+1>=3, O37<70, P37<75), "Lean", AND(R37<>G37, ((H37=R37)+(J37=R37)+(K37=R37))>=2, O37<60, P37<70), "Opposition Lean", TRUE, "Battleground" ) -> Opposition Lean | G37: AAP | H37: INC | I37: AAP | J37: INC | K37: INC | M37: INC | N37: 3.69 | O37: {=_xlfn.XLOOKUP(B37, 'Assembly Competitiveness'!$B$4:$B$120,'Assembly Competitiveness'!$O$4:$O$120, "-")} -> 55.7175 | P37: {=_xlfn.XLOOKUP(B37,'Assembly Volatality'!$B$4:$B$120,'Assembly Volatality'!$L$4:$L$120, "-")} -> 56.49 | Q37: =ROUND(0.45*O37+0.4*P37+0.15*IF(H37<>K37,100,0),1) -> 47.7 | R37: INC | S37: YES | T37: =IFS( AND(G37="AAP", OR(F37="Stronghold", F37="Lean")), "Defend", OR( AND(G37="AAP", OR(F37="Battleground", F37="Highly Volatile", F37="Opposition Lean")), AND(R37="AAP", OR(F37="Battleground", F37="Highly Volatile", F37="Opposition Lean")) ), "Battleground", OR(K37="AAP", M37="AAP", R37="AAP"), "Expand", TRUE, "Long Shot" ) -> Battleground | U37: =IFS( AND(G37="INC", OR(F37="Stronghold", F37="Lean")), "Defend", OR( AND(G37="INC", OR(F37="Battleground", F37="Highly Volatile", F37="Opposition Lean")), AND(R37="INC", OR(F37="Battleground", F37="Highly Volatile", F37="Opposition Lean")) ), "Battleground", OR(K37="INC", M37="INC", R37="INC"), "Expand", TRUE, "Long Shot" ) -> Battleground | V37: =IFS( AND(G37="SAD", OR(F37="Stronghold", F37="Lean")), "Defend", OR( AND(G37="SAD", OR(F37="Battleground", F37="Highly Volatile", F37="Opposition Lean")), AND(R37="SAD", OR(F37="Battleground", F37="Highly Volatile", F37="Opposition Lean")) ), "Battleground", OR(K37="SAD", M37="SAD", R37="SAD"), "Expand", TRUE, "Long Shot" ) -> Long Shot | W37: =IFS( AND(G37="BJP", OR(F37="Stronghold", F37="Lean")), "Defend", OR( AND(G37="BJP", OR(F37="Battleground", F37="Highly Volatile", F37="Opposition Lean")), AND(R37="BJP", OR(F37="Battleground", F37="Highly Volatile", F37="Opposition Lean")) ), "Battleground", OR(K37="BJP", M37="BJP", R37="BJP"), "Expand", TRUE, "Long Shot" ) -> Long Shot | X37: =IFS(K37="EMERGING", "YES", COUNTIFS(T37:W37, "<>Long Shot", T37:W37, "<>") >= 3, "YES", TRUE, "")
A38: 35 | B38: Jalandhar Central | C38: Jalandhar | D38: Doaba | E38: Raman Arora | F38: =IFS( OR(P38>=75, ((H38<>J38)+(J38<>I38)+(I38<>K38))>=3), "Highly Volatile", AND(COUNTIF(H38:K38, G38)+1>=4, O38<55, P38<65), "Stronghold", AND(COUNTIF(H38:K38, G38)+1>=3, O38<70, P38<75), "Lean", AND(R38<>G38, ((H38=R38)+(J38=R38)+(K38=R38))>=2, O38<60, P38<70), "Opposition Lean", TRUE, "Battleground" ) -> Highly Volatile | G38: AAP | H38: INC | I38: AAP | J38: SAD | K38: BJP | M38: INC | N38: 0.23 | O38: {=_xlfn.XLOOKUP(B38, 'Assembly Competitiveness'!$B$4:$B$120,'Assembly Competitiveness'!$O$4:$O$120, "-")} -> 63.5385 | P38: {=_xlfn.XLOOKUP(B38,'Assembly Volatality'!$B$4:$B$120,'Assembly Volatality'!$L$4:$L$120, "-")} -> 69.04 | Q38: =ROUND(0.45*O38+0.4*P38+0.15*IF(H38<>K38,100,0),1) -> 71.2 | R38: INC | S38: YES | T38: =IFS( AND(G38="AAP", OR(F38="Stronghold", F38="Lean")), "Defend", OR( AND(G38="AAP", OR(F38="Battleground", F38="Highly Volatile", F38="Opposition Lean")), AND(R38="AAP", OR(F38="Battleground", F38="Highly Volatile", F38="Opposition Lean")) ), "Battleground", OR(K38="AAP", M38="AAP", R38="AAP"), "Expand", TRUE, "Long Shot" ) -> Battleground | U38: =IFS( AND(G38="INC", OR(F38="Stronghold", F38="Lean")), "Defend", OR( AND(G38="INC", OR(F38="Battleground", F38="Highly Volatile", F38="Opposition Lean")), AND(R38="INC", OR(F38="Battleground", F38="Highly Volatile", F38="Opposition Lean")) ), "Battleground", OR(K38="INC", M38="INC", R38="INC"), "Expand", TRUE, "Long Shot" ) -> Battleground | V38: =IFS( AND(G38="SAD", OR(F38="Stronghold", F38="Lean")), "Defend", OR( AND(G38="SAD", OR(F38="Battleground", F38="Highly Volatile", F38="Opposition Lean")), AND(R38="SAD", OR(F38="Battleground", F38="Highly Volatile", F38="Opposition Lean")) ), "Battleground", OR(K38="SAD", M38="SAD", R38="SAD"), "Expand", TRUE, "Long Shot" ) -> Long Shot | W38: =IFS( AND(G38="BJP", OR(F38="Stronghold", F38="Lean")), "Defend", OR( AND(G38="BJP", OR(F38="Battleground", F38="Highly Volatile", F38="Opposition Lean")), AND(R38="BJP", OR(F38="Battleground", F38="Highly Volatile", F38="Opposition Lean")) ), "Battleground", OR(K38="BJP", M38="BJP", R38="BJP"), "Expand", TRUE, "Long Shot" ) -> Expand | X38: =IFS(K38="EMERGING", "YES", COUNTIFS(T38:W38, "<>Long Shot", T38:W38, "<>") >= 3, "YES", TRUE, "") -> YES
A39: 36 | B39: Jalandhar North | C39: Jalandhar | D39: Doaba | E39: Avtar Singh Junior | F39: =IFS( OR(P39>=75, ((H39<>J39)+(J39<>I39)+(I39<>K39))>=3), "Highly Volatile", AND(COUNTIF(H39:K39, G39)+1>=4, O39<55, P39<65), "Stronghold", AND(COUNTIF(H39:K39, G39)+1>=3, O39<70, P39<75), "Lean", AND(R39<>G39, ((H39=R39)+(J39=R39)+(K39=R39))>=2, O39<60, P39<70), "Opposition Lean", TRUE, "Battleground" ) -> Highly Volatile | G39: INC | H39: INC | I39: INC | J39: SAD | K39: BJP | M39: BJP | N39: 7.46 | O39: {=_xlfn.XLOOKUP(B39, 'Assembly Competitiveness'!$B$4:$B$120,'Assembly Competitiveness'!$O$4:$O$120, "-")} -> 45.707 | P39: {=_xlfn.XLOOKUP(B39,'Assembly Volatality'!$B$4:$B$120,'Assembly Volatality'!$L$4:$L$120, "-")} -> 33.55 | Q39: =ROUND(0.45*O39+0.4*P39+0.15*IF(H39<>K39,100,0),1) -> 49 | R39: BJP | S39: YES | T39: =IFS( AND(G39="AAP", OR(F39="Stronghold", F39="Lean")), "Defend", OR( AND(G39="AAP", OR(F39="Battleground", F39="Highly Volatile", F39="Opposition Lean")), AND(R39="AAP", OR(F39="Battleground", F39="Highly Volatile", F39="Opposition Lean")) ), "Battleground", OR(K39="AAP", M39="AAP", R39="AAP"), "Expand", TRUE, "Long Shot" ) -> Long Shot | U39: =IFS( AND(G39="INC", OR(F39="Stronghold", F39="Lean")), "Defend", OR( AND(G39="INC", OR(F39="Battleground", F39="Highly Volatile", F39="Opposition Lean")), AND(R39="INC", OR(F39="Battleground", F39="Highly Volatile", F39="Opposition Lean")) ), "Battleground", OR(K39="INC", M39="INC", R39="INC"), "Expand", TRUE, "Long Shot" ) -> Battleground | V39: =IFS( AND(G39="SAD", OR(F39="Stronghold", F39="Lean")), "Defend", OR( AND(G39="SAD", OR(F39="Battleground", F39="Highly Volatile", F39="Opposition Lean")), AND(R39="SAD", OR(F39="Battleground", F39="Highly Volatile", F39="Opposition Lean")) ), "Battleground", OR(K39="SAD", M39="SAD", R39="SAD"), "Expand", TRUE, "Long Shot" ) -> Long Shot | W39: =IFS( AND(G39="BJP", OR(F39="Stronghold", F39="Lean")), "Defend", OR( AND(G39="BJP", OR(F39="Battleground", F39="Highly Volatile", F39="Opposition Lean")), AND(R39="BJP", OR(F39="Battleground", F39="Highly Volatile", F39="Opposition Lean")) ), "Battleground", OR(K39="BJP", M39="BJP", R39="BJP"), "Expand", TRUE, "Long Shot" ) -> Battleground | X39: =IFS(K39="EMERGING", "YES", COUNTIFS(T39:W39, "<>Long Shot", T39:W39, "<>") >= 3, "YES", TRUE, "")
A40: 37 | B40: Jalandhar Cantt | C40: Jalandhar | D40: Doaba | E40: Pargat Singh Powar | F40: =IFS( OR(P40>=75, ((H40<>J40)+(J40<>I40)+(I40<>K40))>=3), "Highly Volatile", AND(COUNTIF(H40:K40, G40)+1>=4, O40<55, P40<65), "Stronghold", AND(COUNTIF(H40:K40, G40)+1>=3, O40<70, P40<75), "Lean", AND(R40<>G40, ((H40=R40)+(J40=R40)+(K40=R40))>=2, O40<60, P40<70), "Opposition Lean", TRUE, "Battleground" ) -> Stronghold | G40: INC | H40: INC | I40: INC | J40: INC | K40: INC | M40: AAP | N40: 4.68 | O40: {=_xlfn.XLOOKUP(B40, 'Assembly Competitiveness'!$B$4:$B$120,'Assembly Competitiveness'!$O$4:$O$120, "-")} -> 41.89 | P40: {=_xlfn.XLOOKUP(B40,'Assembly Volatality'!$B$4:$B$120,'Assembly Volatality'!$L$4:$L$120, "-")} -> 22.03 | Q40: =ROUND(0.45*O40+0.4*P40+0.15*IF(H40<>K40,100,0),1) -> 27.7 | R40: AAP | T40: =IFS( AND(G40="AAP", OR(F40="Stronghold", F40="Lean")), "Defend", OR( AND(G40="AAP", OR(F40="Battleground", F40="Highly Volatile", F40="Opposition Lean")), AND(R40="AAP", OR(F40="Battleground", F40="Highly Volatile", F40="Opposition Lean")) ), "Battleground", OR(K40="AAP", M40="AAP", R40="AAP"), "Expand", TRUE, "Long Shot" ) -> Expand | U40: =IFS( AND(G40="INC", OR(F40="Stronghold", F40="Lean")), "Defend", OR( AND(G40="INC", OR(F40="Battleground", F40="Highly Volatile", F40="Opposition Lean")), AND(R40="INC", OR(F40="Battleground", F40="Highly Volatile", F40="Opposition Lean")) ), "Battleground", OR(K40="INC", M40="INC", R40="INC"), "Expand", TRUE, "Long Shot" ) -> Defend | V40: =IFS( AND(G40="SAD", OR(F40="Stronghold", F40="Lean")), "Defend", OR( AND(G40="SAD", OR(F40="Battleground", F40="Highly Volatile", F40="Opposition Lean")), AND(R40="SAD", OR(F40="Battleground", F40="Highly Volatile", F40="Opposition Lean")) ), "Battleground", OR(K40="SAD", M40="SAD", R40="SAD"), "Expand", TRUE, "Long Shot" ) -> Long Shot | W40: =IFS( AND(G40="BJP", OR(F40="Stronghold", F40="Lean")), "Defend", OR( AND(G40="BJP", OR(F40="Battleground", F40="Highly Volatile", F40="Opposition Lean")), AND(R40="BJP", OR(F40="Battleground", F40="Highly Volatile", F40="Opposition Lean")) ), "Battleground", OR(K40="BJP", M40="BJP", R40="BJP"), "Expand", TRUE, "Long Shot" ) -> Long Shot | X40: =IFS(K40="EMERGING", "YES", COUNTIFS(T40:W40, "<>Long Shot", T40:W40, "<>") >= 3, "YES", TRUE, "")
A41: 38 | B41: Adampur | C41: Jalandhar | D41: Doaba | E41: Sukhwinder Singh Kotli | F41: =IFS( OR(P41>=75, ((H41<>J41)+(J41<>I41)+(I41<>K41))>=3), "Highly Volatile", AND(COUNTIF(H41:K41, G41)+1>=4, O41<55, P41<65), "Stronghold", AND(COUNTIF(H41:K41, G41)+1>=3, O41<70, P41<75), "Lean", AND(R41<>G41, ((H41=R41)+(J41=R41)+(K41=R41))>=2, O41<60, P41<70), "Opposition Lean", TRUE, "Battleground" ) -> Lean | G41: INC | H41: SAD | I41: INC | J41: BSP | K41: INC | M41: SAD | N41: 4.06 | O41: {=_xlfn.XLOOKUP(B41, 'Assembly Competitiveness'!$B$4:$B$120,'Assembly Competitiveness'!$O$4:$O$120, "-")} -> 50.245 | P41: {=_xlfn.XLOOKUP(B41,'Assembly Volatality'!$B$4:$B$120,'Assembly Volatality'!$L$4:$L$120, "-")} -> 37.86 | Q41: =ROUND(0.45*O41+0.4*P41+0.15*IF(H41<>K41,100,0),1) -> 52.8 | R41: SAD | T41: =IFS( AND(G41="AAP", OR(F41="Stronghold", F41="Lean")), "Defend", OR( AND(G41="AAP", OR(F41="Battleground", F41="Highly Volatile", F41="Opposition Lean")), AND(R41="AAP", OR(F41="Battleground", F41="Highly Volatile", F41="Opposition Lean")) ), "Battleground", OR(K41="AAP", M41="AAP", R41="AAP"), "Expand", TRUE, "Long Shot" ) -> Long Shot | U41: =IFS( AND(G41="INC", OR(F41="Stronghold", F41="Lean")), "Defend", OR( AND(G41="INC", OR(F41="Battleground", F41="Highly Volatile", F41="Opposition Lean")), AND(R41="INC", OR(F41="Battleground", F41="Highly Volatile", F41="Opposition Lean")) ), "Battleground", OR(K41="INC", M41="INC", R41="INC"), "Expand", TRUE, "Long Shot" ) -> Defend | V41: =IFS( AND(G41="SAD", OR(F41="Stronghold", F41="Lean")), "Defend", OR( AND(G41="SAD", OR(F41="Battleground", F41="Highly Volatile", F41="Opposition Lean")), AND(R41="SAD", OR(F41="Battleground", F41="Highly Volatile", F41="Opposition Lean")) ), "Battleground", OR(K41="SAD", M41="SAD", R41="SAD"), "Expand", TRUE, "Long Shot" ) -> Expand | W41: =IFS( AND(G41="BJP", OR(F41="Stronghold", F41="Lean")), "Defend", OR( AND(G41="BJP", OR(F41="Battleground", F41="Highly Volatile", F41="Opposition Lean")), AND(R41="BJP", OR(F41="Battleground", F41="Highly Volatile", F41="Opposition Lean")) ), "Battleground", OR(K41="BJP", M41="BJP", R41="BJP"), "Expand", TRUE, "Long Shot" ) -> Long Shot | X41: =IFS(K41="EMERGING", "YES", COUNTIFS(T41:W41, "<>Long Shot", T41:W41, "<>") >= 3, "YES", TRUE, "")
A42: 39 | B42: Mukerian | C42: Hoshiarpur | D42: Doaba | E42: Jangi Lal Mahajan | F42: =IFS( OR(P42>=75, ((H42<>J42)+(J42<>I42)+(I42<>K42))>=3), "Highly Volatile", AND(COUNTIF(H42:K42, G42)+1>=4, O42<55, P42<65), "Stronghold", AND(COUNTIF(H42:K42, G42)+1>=3, O42<70, P42<75), "Lean", AND(R42<>G42, ((H42=R42)+(J42=R42)+(K42=R42))>=2, O42<60, P42<70), "Opposition Lean", TRUE, "Battleground" ) -> Stronghold | G42: BJP | H42: INC | I42: BJP | J42: BJP | K42: BJP | M42: AAP | N42: 1.89 | O42: {=_xlfn.XLOOKUP(B42, 'Assembly Competitiveness'!$B$4:$B$120,'Assembly Competitiveness'!$O$4:$O$120, "-")} -> 49.7015 | P42: {=_xlfn.XLOOKUP(B42,'Assembly Volatality'!$B$4:$B$120,'Assembly Volatality'!$L$4:$L$120, "-")} -> 46.56 | Q42: =ROUND(0.45*O42+0.4*P42+0.15*IF(H42<>K42,100,0),1) -> 56 | R42: AAP | T42: =IFS( AND(G42="AAP", OR(F42="Stronghold", F42="Lean")), "Defend", OR( AND(G42="AAP", OR(F42="Battleground", F42="Highly Volatile", F42="Opposition Lean")), AND(R42="AAP", OR(F42="Battleground", F42="Highly Volatile", F42="Opposition Lean")) ), "Battleground", OR(K42="AAP", M42="AAP", R42="AAP"), "Expand", TRUE, "Long Shot" ) -> Expand | U42: =IFS( AND(G42="INC", OR(F42="Stronghold", F42="Lean")), "Defend", OR( AND(G42="INC", OR(F42="Battleground", F42="Highly Volatile", F42="Opposition Lean")), AND(R42="INC", OR(F42="Battleground", F42="Highly Volatile", F42="Opposition Lean")) ), "Battleground", OR(K42="INC", M42="INC", R42="INC"), "Expand", TRUE, "Long Shot" ) -> Long Shot | V42: =IFS( AND(G42="SAD", OR(F42="Stronghold", F42="Lean")), "Defend", OR( AND(G42="SAD", OR(F42="Battleground", F42="Highly Volatile", F42="Opposition Lean")), AND(R42="SAD", OR(F42="Battleground", F42="Highly Volatile", F42="Opposition Lean")) ), "Battleground", OR(K42="SAD", M42="SAD", R42="SAD"), "Expand", TRUE, "Long Shot" ) -> Long Shot | W42: =IFS( AND(G42="BJP", OR(F42="Stronghold", F42="Lean")), "Defend", OR( AND(G42="BJP", OR(F42="Battleground", F42="Highly Volatile", F42="Opposition Lean")), AND(R42="BJP", OR(F42="Battleground", F42="Highly Volatile", F42="Opposition Lean")) ), "Battleground", OR(K42="BJP", M42="BJP", R42="BJP"), "Expand", TRUE, "Long Shot" ) -> Defend | X42: =IFS(K42="EMERGING", "YES", COUNTIFS(T42:W42, "<>Long Shot", T42:W42, "<>") >= 3, "YES", TRUE, "")
A43: 40 | B43: Dasuya | C43: Hoshiarpur | D43: Doaba | E43: Karambir Singh | F43: =IFS( OR(P43>=75, ((H43<>J43)+(J43<>I43)+(I43<>K43))>=3), "Highly Volatile", AND(COUNTIF(H43:K43, G43)+1>=4, O43<55, P43<65), "Stronghold", AND(COUNTIF(H43:K43, G43)+1>=3, O43<70, P43<75), "Lean", AND(R43<>G43, ((H43=R43)+(J43=R43)+(K43=R43))>=2, O43<60, P43<70), "Opposition Lean", TRUE, "Battleground" ) -> Highly Volatile | G43: AAP | H43: INC | I43: AAP | J43: BJP | K43: BJP | M43: INC | N43: 6.47 | O43: {=_xlfn.XLOOKUP(B43, 'Assembly Competitiveness'!$B$4:$B$120,'Assembly Competitiveness'!$O$4:$O$120, "-")} -> 49.6885 | P43: {=_xlfn.XLOOKUP(B43,'Assembly Volatality'!$B$4:$B$120,'Assembly Volatality'!$L$4:$L$120, "-")} -> 49.28 | Q43: =ROUND(0.45*O43+0.4*P43+0.15*IF(H43<>K43,100,0),1) -> 57.1 | R43: INC | S43: YES | T43: =IFS( AND(G43="AAP", OR(F43="Stronghold", F43="Lean")), "Defend", OR( AND(G43="AAP", OR(F43="Battleground", F43="Highly Volatile", F43="Opposition Lean")), AND(R43="AAP", OR(F43="Battleground", F43="Highly Volatile", F43="Opposition Lean")) ), "Battleground", OR(K43="AAP", M43="AAP", R43="AAP"), "Expand", TRUE, "Long Shot" ) -> Battleground | U43: =IFS( AND(G43="INC", OR(F43="Stronghold", F43="Lean")), "Defend", OR( AND(G43="INC", OR(F43="Battleground", F43="Highly Volatile", F43="Opposition Lean")), AND(R43="INC", OR(F43="Battleground", F43="Highly Volatile", F43="Opposition Lean")) ), "Battleground", OR(K43="INC", M43="INC", R43="INC"), "Expand", TRUE, "Long Shot" ) -> Battleground | V43: =IFS( AND(G43="SAD", OR(F43="Stronghold", F43="Lean")), "Defend", OR( AND(G43="SAD", OR(F43="Battleground", F43="Highly Volatile", F43="Opposition Lean")), AND(R43="SAD", OR(F43="Battleground", F43="Highly Volatile", F43="Opposition Lean")) ), "Battleground", OR(K43="SAD", M43="SAD", R43="SAD"), "Expand", TRUE, "Long Shot" ) -> Long Shot | W43: =IFS( AND(G43="BJP", OR(F43="Stronghold", F43="Lean")), "Defend", OR( AND(G43="BJP", OR(F43="Battleground", F43="Highly Volatile", F43="Opposition Lean")), AND(R43="BJP", OR(F43="Battleground", F43="Highly Volatile", F43="Opposition Lean")) ), "Battleground", OR(K43="BJP", M43="BJP", R43="BJP"), "Expand", TRUE, "Long Shot" ) -> Expand | X43: =IFS(K43="EMERGING", "YES", COUNTIFS(T43:W43, "<>Long Shot", T43:W43, "<>") >= 3, "YES", TRUE, "") -> YES
A44: 41 | B44: Urmar | C44: Hoshiarpur | D44: Doaba | E44: Jasvir Singh Raja Gill | F44: =IFS( OR(P44>=75, ((H44<>J44)+(J44<>I44)+(I44<>K44))>=3), "Highly Volatile", AND(COUNTIF(H44:K44, G44)+1>=4, O44<55, P44<65), "Stronghold", AND(COUNTIF(H44:K44, G44)+1>=3, O44<70, P44<75), "Lean", AND(R44<>G44, ((H44=R44)+(J44=R44)+(K44=R44))>=2, O44<60, P44<70), "Opposition Lean", TRUE, "Battleground" ) -> Opposition Lean | G44: AAP | H44: INC | I44: AAP | J44: INC | K44: INC | M44: INC | N44: 3.37 | O44: {=_xlfn.XLOOKUP(B44, 'Assembly Competitiveness'!$B$4:$B$120,'Assembly Competitiveness'!$O$4:$O$120, "-")} -> 58.9055 | P44: {=_xlfn.XLOOKUP(B44,'Assembly Volatality'!$B$4:$B$120,'Assembly Volatality'!$L$4:$L$120, "-")} -> 51.22 | Q44: =ROUND(0.45*O44+0.4*P44+0.15*IF(H44<>K44,100,0),1) -> 47 | R44: INC | S44: YES | T44: =IFS( AND(G44="AAP", OR(F44="Stronghold", F44="Lean")), "Defend", OR( AND(G44="AAP", OR(F44="Battleground", F44="Highly Volatile", F44="Opposition Lean")), AND(R44="AAP", OR(F44="Battleground", F44="Highly Volatile", F44="Opposition Lean")) ), "Battleground", OR(K44="AAP", M44="AAP", R44="AAP"), "Expand", TRUE, "Long Shot" ) -> Battleground | U44: =IFS( AND(G44="INC", OR(F44="Stronghold", F44="Lean")), "Defend", OR( AND(G44="INC", OR(F44="Battleground", F44="Highly Volatile", F44="Opposition Lean")), AND(R44="INC", OR(F44="Battleground", F44="Highly Volatile", F44="Opposition Lean")) ), "Battleground", OR(K44="INC", M44="INC", R44="INC"), "Expand", TRUE, "Long Shot" ) -> Battleground | V44: =IFS( AND(G44="SAD", OR(F44="Stronghold", F44="Lean")), "Defend", OR( AND(G44="SAD", OR(F44="Battleground", F44="Highly Volatile", F44="Opposition Lean")), AND(R44="SAD", OR(F44="Battleground", F44="Highly Volatile", F44="Opposition Lean")) ), "Battleground", OR(K44="SAD", M44="SAD", R44="SAD"), "Expand", TRUE, "Long Shot" ) -> Long Shot | W44: =IFS( AND(G44="BJP", OR(F44="Stronghold", F44="Lean")), "Defend", OR( AND(G44="BJP", OR(F44="Battleground", F44="Highly Volatile", F44="Opposition Lean")), AND(R44="BJP", OR(F44="Battleground", F44="Highly Volatile", F44="Opposition Lean")) ), "Battleground", OR(K44="BJP", M44="BJP", R44="BJP"), "Expand", TRUE, "Long Shot" ) -> Long Shot | X44: =IFS(K44="EMERGING", "YES", COUNTIFS(T44:W44, "<>Long Shot", T44:W44, "<>") >= 3, "YES", TRUE, "")
A45: 42 | B45: Sham Chaurasi | C45: Hoshiarpur | D45: Doaba | E45: Dr.Ravjot Singh | F45: =IFS( OR(P45>=75, ((H45<>J45)+(J45<>I45)+(I45<>K45))>=3), "Highly Volatile", AND(COUNTIF(H45:K45, G45)+1>=4, O45<55, P45<65), "Stronghold", AND(COUNTIF(H45:K45, G45)+1>=3, O45<70, P45<75), "Lean", AND(R45<>G45, ((H45=R45)+(J45=R45)+(K45=R45))>=2, O45<60, P45<70), "Opposition Lean", TRUE, "Battleground" ) -> Lean | G45: AAP | H45: INC | I45: AAP | J45: INC | K45: AAP | M45: INC | N45: 17.37 | O45: {=_xlfn.XLOOKUP(B45, 'Assembly Competitiveness'!$B$4:$B$120,'Assembly Competitiveness'!$O$4:$O$120, "-")} -> 28.5255 | P45: {=_xlfn.XLOOKUP(B45,'Assembly Volatality'!$B$4:$B$120,'Assembly Volatality'!$L$4:$L$120, "-")} -> 48.71 | Q45: =ROUND(0.45*O45+0.4*P45+0.15*IF(H45<>K45,100,0),1) -> 47.3 | R45: INC | T45: =IFS( AND(G45="AAP", OR(F45="Stronghold", F45="Lean")), "Defend", OR( AND(G45="AAP", OR(F45="Battleground", F45="Highly Volatile", F45="Opposition Lean")), AND(R45="AAP", OR(F45="Battleground", F45="Highly Volatile", F45="Opposition Lean")) ), "Battleground", OR(K45="AAP", M45="AAP", R45="AAP"), "Expand", TRUE, "Long Shot" ) -> Defend | U45: =IFS( AND(G45="INC", OR(F45="Stronghold", F45="Lean")), "Defend", OR( AND(G45="INC", OR(F45="Battleground", F45="Highly Volatile", F45="Opposition Lean")), AND(R45="INC", OR(F45="Battleground", F45="Highly Volatile", F45="Opposition Lean")) ), "Battleground", OR(K45="INC", M45="INC", R45="INC"), "Expand", TRUE, "Long Shot" ) -> Expand | V45: =IFS( AND(G45="SAD", OR(F45="Stronghold", F45="Lean")), "Defend", OR( AND(G45="SAD", OR(F45="Battleground", F45="Highly Volatile", F45="Opposition Lean")), AND(R45="SAD", OR(F45="Battleground", F45="Highly Volatile", F45="Opposition Lean")) ), "Battleground", OR(K45="SAD", M45="SAD", R45="SAD"), "Expand", TRUE, "Long Shot" ) -> Long Shot | W45: =IFS( AND(G45="BJP", OR(F45="Stronghold", F45="Lean")), "Defend", OR( AND(G45="BJP", OR(F45="Battleground", F45="Highly Volatile", F45="Opposition Lean")), AND(R45="BJP", OR(F45="Battleground", F45="Highly Volatile", F45="Opposition Lean")) ), "Battleground", OR(K45="BJP", M45="BJP", R45="BJP"), "Expand", TRUE, "Long Shot" ) -> Long Shot | X45: =IFS(K45="EMERGING", "YES", COUNTIFS(T45:W45, "<>Long Shot", T45:W45, "<>") >= 3, "YES", TRUE, "")
A46: 43 | B46: Hoshiarpur | C46: Hoshiarpur | D46: Doaba | E46: Bram Shanker (Jimpa) | F46: =IFS( OR(P46>=75, ((H46<>J46)+(J46<>I46)+(I46<>K46))>=3), "Highly Volatile", AND(COUNTIF(H46:K46, G46)+1>=4, O46<55, P46<65), "Stronghold", AND(COUNTIF(H46:K46, G46)+1>=3, O46<70, P46<75), "Lean", AND(R46<>G46, ((H46=R46)+(J46=R46)+(K46=R46))>=2, O46<60, P46<70), "Opposition Lean", TRUE, "Battleground" ) -> Highly Volatile | G46: AAP | H46: INC | I46: AAP | J46: BJP | K46: BJP | M46: INC | N46: 10.93 | O46: {=_xlfn.XLOOKUP(B46, 'Assembly Competitiveness'!$B$4:$B$120,'Assembly Competitiveness'!$O$4:$O$120, "-")} -> 41.9135 | P46: {=_xlfn.XLOOKUP(B46,'Assembly Volatality'!$B$4:$B$120,'Assembly Volatality'!$L$4:$L$120, "-")} -> 44.91 | Q46: =ROUND(0.45*O46+0.4*P46+0.15*IF(H46<>K46,100,0),1) -> 51.8 | R46: INC | S46: YES | T46: =IFS( AND(G46="AAP", OR(F46="Stronghold", F46="Lean")), "Defend", OR( AND(G46="AAP", OR(F46="Battleground", F46="Highly Volatile", F46="Opposition Lean")), AND(R46="AAP", OR(F46="Battleground", F46="Highly Volatile", F46="Opposition Lean")) ), "Battleground", OR(K46="AAP", M46="AAP", R46="AAP"), "Expand", TRUE, "Long Shot" ) -> Battleground | U46: =IFS( AND(G46="INC", OR(F46="Stronghold", F46="Lean")), "Defend", OR( AND(G46="INC", OR(F46="Battleground", F46="Highly Volatile", F46="Opposition Lean")), AND(R46="INC", OR(F46="Battleground", F46="Highly Volatile", F46="Opposition Lean")) ), "Battleground", OR(K46="INC", M46="INC", R46="INC"), "Expand", TRUE, "Long Shot" ) -> Battleground | V46: =IFS( AND(G46="SAD", OR(F46="Stronghold", F46="Lean")), "Defend", OR( AND(G46="SAD", OR(F46="Battleground", F46="Highly Volatile", F46="Opposition Lean")), AND(R46="SAD", OR(F46="Battleground", F46="Highly Volatile", F46="Opposition Lean")) ), "Battleground", OR(K46="SAD", M46="SAD", R46="SAD"), "Expand", TRUE, "Long Shot" ) -> Long Shot | W46: =IFS( AND(G46="BJP", OR(F46="Stronghold", F46="Lean")), "Defend", OR( AND(G46="BJP", OR(F46="Battleground", F46="Highly Volatile", F46="Opposition Lean")), AND(R46="BJP", OR(F46="Battleground", F46="Highly Volatile", F46="Opposition Lean")) ), "Battleground", OR(K46="BJP", M46="BJP", R46="BJP"), "Expand", TRUE, "Long Shot" ) -> Expand | X46: =IFS(K46="EMERGING", "YES", COUNTIFS(T46:W46, "<>Long Shot", T46:W46, "<>") >= 3, "YES", TRUE, "") -> YES
A47: 44 | B47: Chabbewal | C47: Hoshiarpur | D47: Doaba | E47: Ishank Kumar Chabbewal | F47: =IFS( OR(P47>=75, ((H47<>J47)+(J47<>I47)+(I47<>K47))>=3), "Highly Volatile", AND(COUNTIF(H47:K47, G47)+1>=4, O47<55, P47<65), "Stronghold", AND(COUNTIF(H47:K47, G47)+1>=3, O47<70, P47<75), "Lean", AND(R47<>G47, ((H47=R47)+(J47=R47)+(K47=R47))>=2, O47<60, P47<70), "Opposition Lean", TRUE, "Battleground" ) -> Battleground | G47: AAP | H47: INC | I47: INC | J47: INC | K47: AAP | L47: 2024 bypoll - AAP gain from INC | M47: AAP | N47: 6.68 | O47: {=_xlfn.XLOOKUP(B47, 'Assembly Competitiveness'!$B$4:$B$120,'Assembly Competitiveness'!$O$4:$O$120, "-")} -> 62.478 | P47: {=_xlfn.XLOOKUP(B47,'Assembly Volatality'!$B$4:$B$120,'Assembly Volatality'!$L$4:$L$120, "-")} -> 56.19 | Q47: =ROUND(0.45*O47+0.4*P47+0.15*IF(H47<>K47,100,0),1) -> 65.6 | R47: INC | S47: YES | T47: =IFS( AND(G47="AAP", OR(F47="Stronghold", F47="Lean")), "Defend", OR( AND(G47="AAP", OR(F47="Battleground", F47="Highly Volatile", F47="Opposition Lean")), AND(R47="AAP", OR(F47="Battleground", F47="Highly Volatile", F47="Opposition Lean")) ), "Battleground", OR(K47="AAP", M47="AAP", R47="AAP"), "Expand", TRUE, "Long Shot" ) -> Battleground | U47: =IFS( AND(G47="INC", OR(F47="Stronghold", F47="Lean")), "Defend", OR( AND(G47="INC", OR(F47="Battleground", F47="Highly Volatile", F47="Opposition Lean")), AND(R47="INC", OR(F47="Battleground", F47="Highly Volatile", F47="Opposition Lean")) ), "Battleground", OR(K47="INC", M47="INC", R47="INC"), "Expand", TRUE, "Long Shot" ) -> Battleground | V47: =IFS( AND(G47="SAD", OR(F47="Stronghold", F47="Lean")), "Defend", OR( AND(G47="SAD", OR(F47="Battleground", F47="Highly Volatile", F47="Opposition Lean")), AND(R47="SAD", OR(F47="Battleground", F47="Highly Volatile", F47="Opposition Lean")) ), "Battleground", OR(K47="SAD", M47="SAD", R47="SAD"), "Expand", TRUE, "Long Shot" ) -> Long Shot | W47: =IFS( AND(G47="BJP", OR(F47="Stronghold", F47="Lean")), "Defend", OR( AND(G47="BJP", OR(F47="Battleground", F47="Highly Volatile", F47="Opposition Lean")), AND(R47="BJP", OR(F47="Battleground", F47="Highly Volatile", F47="Opposition Lean")) ), "Battleground", OR(K47="BJP", M47="BJP", R47="BJP"), "Expand", TRUE, "Long Shot" ) -> Long Shot | X47: =IFS(K47="EMERGING", "YES", COUNTIFS(T47:W47, "<>Long Shot", T47:W47, "<>") >= 3, "YES", TRUE, "")
A48: 45 | B48: Garhshankar | C48: Hoshiarpur | D48: Doaba | E48: Jai Krishan | F48: =IFS( OR(P48>=75, ((H48<>J48)+(J48<>I48)+(I48<>K48))>=3), "Highly Volatile", AND(COUNTIF(H48:K48, G48)+1>=4, O48<55, P48<65), "Stronghold", AND(COUNTIF(H48:K48, G48)+1>=3, O48<70, P48<75), "Lean", AND(R48<>G48, ((H48=R48)+(J48=R48)+(K48=R48))>=2, O48<60, P48<70), "Opposition Lean", TRUE, "Battleground" ) -> Lean | G48: AAP | H48: AAP | I48: AAP | J48: INC | K48: AAP | M48: INC | N48: 3.44 | O48: {=_xlfn.XLOOKUP(B48, 'Assembly Competitiveness'!$B$4:$B$120,'Assembly Competitiveness'!$O$4:$O$120, "-")} -> 56.788 | P48: {=_xlfn.XLOOKUP(B48,'Assembly Volatality'!$B$4:$B$120,'Assembly Volatality'!$L$4:$L$120, "-")} -> 6.08 | Q48: =ROUND(0.45*O48+0.4*P48+0.15*IF(H48<>K48,100,0),1) -> 28 | R48: INC | T48: =IFS( AND(G48="AAP", OR(F48="Stronghold", F48="Lean")), "Defend", OR( AND(G48="AAP", OR(F48="Battleground", F48="Highly Volatile", F48="Opposition Lean")), AND(R48="AAP", OR(F48="Battleground", F48="Highly Volatile", F48="Opposition Lean")) ), "Battleground", OR(K48="AAP", M48="AAP", R48="AAP"), "Expand", TRUE, "Long Shot" ) -> Defend | U48: =IFS( AND(G48="INC", OR(F48="Stronghold", F48="Lean")), "Defend", OR( AND(G48="INC", OR(F48="Battleground", F48="Highly Volatile", F48="Opposition Lean")), AND(R48="INC", OR(F48="Battleground", F48="Highly Volatile", F48="Opposition Lean")) ), "Battleground", OR(K48="INC", M48="INC", R48="INC"), "Expand", TRUE, "Long Shot" ) -> Expand | V48: =IFS( AND(G48="SAD", OR(F48="Stronghold", F48="Lean")), "Defend", OR( AND(G48="SAD", OR(F48="Battleground", F48="Highly Volatile", F48="Opposition Lean")), AND(R48="SAD", OR(F48="Battleground", F48="Highly Volatile", F48="Opposition Lean")) ), "Battleground", OR(K48="SAD", M48="SAD", R48="SAD"), "Expand", TRUE, "Long Shot" ) -> Long Shot | W48: =IFS( AND(G48="BJP", OR(F48="Stronghold", F48="Lean")), "Defend", OR( AND(G48="BJP", OR(F48="Battleground", F48="Highly Volatile", F48="Opposition Lean")), AND(R48="BJP", OR(F48="Battleground", F48="Highly Volatile", F48="Opposition Lean")) ), "Battleground", OR(K48="BJP", M48="BJP", R48="BJP"), "Expand", TRUE, "Long Shot" ) -> Long Shot | X48: =IFS(K48="EMERGING", "YES", COUNTIFS(T48:W48, "<>Long Shot", T48:W48, "<>") >= 3, "YES", TRUE, "")
A49: 46 | B49: Banga | C49: SBS Nagar | D49: Doaba | E49: Sukhwinder Kumar Sukhi (elected SAD; joined AAP) | F49: =IFS( OR(P49>=75, ((H49<>J49)+(J49<>I49)+(I49<>K49))>=3), "Highly Volatile", AND(COUNTIF(H49:K49, G49)+1>=4, O49<55, P49<65), "Stronghold", AND(COUNTIF(H49:K49, G49)+1>=3, O49<70, P49<75), "Lean", AND(R49<>G49, ((H49=R49)+(J49=R49)+(K49=R49))>=2, O49<60, P49<70), "Opposition Lean", TRUE, "Battleground" ) -> Highly Volatile | G49: AAP | H49: SAD | I49: SAD | J49: BSP | K49: AAP | L49: MLA elected SAD joined AAP; formal/legal membership differs | M49: INC | N49: 4.43 | O49: {=_xlfn.XLOOKUP(B49, 'Assembly Competitiveness'!$B$4:$B$120,'Assembly Competitiveness'!$O$4:$O$120, "-")} -> 79.6345 | P49: {=_xlfn.XLOOKUP(B49,'Assembly Volatality'!$B$4:$B$120,'Assembly Volatality'!$L$4:$L$120, "-")} -> 44.76 | Q49: =ROUND(0.45*O49+0.4*P49+0.15*IF(H49<>K49,100,0),1) -> 68.7 | R49: SAD | S49: YES | T49: =IFS( AND(G49="AAP", OR(F49="Stronghold", F49="Lean")), "Defend", OR( AND(G49="AAP", OR(F49="Battleground", F49="Highly Volatile", F49="Opposition Lean")), AND(R49="AAP", OR(F49="Battleground", F49="Highly Volatile", F49="Opposition Lean")) ), "Battleground", OR(K49="AAP", M49="AAP", R49="AAP"), "Expand", TRUE, "Long Shot" ) -> Battleground | U49: =IFS( AND(G49="INC", OR(F49="Stronghold", F49="Lean")), "Defend", OR( AND(G49="INC", OR(F49="Battleground", F49="Highly Volatile", F49="Opposition Lean")), AND(R49="INC", OR(F49="Battleground", F49="Highly Volatile", F49="Opposition Lean")) ), "Battleground", OR(K49="INC", M49="INC", R49="INC"), "Expand", TRUE, "Long Shot" ) -> Expand | V49: =IFS( AND(G49="SAD", OR(F49="Stronghold", F49="Lean")), "Defend", OR( AND(G49="SAD", OR(F49="Battleground", F49="Highly Volatile", F49="Opposition Lean")), AND(R49="SAD", OR(F49="Battleground", F49="Highly Volatile", F49="Opposition Lean")) ), "Battleground", OR(K49="SAD", M49="SAD", R49="SAD"), "Expand", TRUE, "Long Shot" ) -> Battleground | W49: =IFS( AND(G49="BJP", OR(F49="Stronghold", F49="Lean")), "Defend", OR( AND(G49="BJP", OR(F49="Battleground", F49="Highly Volatile", F49="Opposition Lean")), AND(R49="BJP", OR(F49="Battleground", F49="Highly Volatile", F49="Opposition Lean")) ), "Battleground", OR(K49="BJP", M49="BJP", R49="BJP"), "Expand", TRUE, "Long Shot" ) -> Long Shot | X49: =IFS(K49="EMERGING", "YES", COUNTIFS(T49:W49, "<>Long Shot", T49:W49, "<>") >= 3, "YES", TRUE, "") -> YES
A50: 47 | B50: Nawan Shahr | C50: SBS Nagar | D50: Doaba | E50: Dr. Nachhatar Pal | F50: =IFS( OR(P50>=75, ((H50<>J50)+(J50<>I50)+(I50<>K50))>=3), "Highly Volatile", AND(COUNTIF(H50:K50, G50)+1>=4, O50<55, P50<65), "Stronghold", AND(COUNTIF(H50:K50, G50)+1>=3, O50<70, P50<75), "Lean", AND(R50<>G50, ((H50=R50)+(J50=R50)+(K50=R50))>=2, O50<60, P50<70), "Opposition Lean", TRUE, "Battleground" ) -> Battleground | G50: BSP | H50: INC | I50: BSP | J50: INC | K50: AAP | M50: AAP | N50: 4.36 | O50: {=_xlfn.XLOOKUP(B50, 'Assembly Competitiveness'!$B$4:$B$120,'Assembly Competitiveness'!$O$4:$O$120, "-")} -> 63.294 | P50: {=_xlfn.XLOOKUP(B50,'Assembly Volatality'!$B$4:$B$120,'Assembly Volatality'!$L$4:$L$120, "-")} -> 47.92 | Q50: =ROUND(0.45*O50+0.4*P50+0.15*IF(H50<>K50,100,0),1) -> 62.7 | R50: AAP | S50: YES | T50: =IFS( AND(G50="AAP", OR(F50="Stronghold", F50="Lean")), "Defend", OR( AND(G50="AAP", OR(F50="Battleground", F50="Highly Volatile", F50="Opposition Lean")), AND(R50="AAP", OR(F50="Battleground", F50="Highly Volatile", F50="Opposition Lean")) ), "Battleground", OR(K50="AAP", M50="AAP", R50="AAP"), "Expand", TRUE, "Long Shot" ) -> Battleground | U50: =IFS( AND(G50="INC", OR(F50="Stronghold", F50="Lean")), "Defend", OR( AND(G50="INC", OR(F50="Battleground", F50="Highly Volatile", F50="Opposition Lean")), AND(R50="INC", OR(F50="Battleground", F50="Highly Volatile", F50="Opposition Lean")) ), "Battleground", OR(K50="INC", M50="INC", R50="INC"), "Expand", TRUE, "Long Shot" ) -> Long Shot | V50: =IFS( AND(G50="SAD", OR(F50="Stronghold", F50="Lean")), "Defend", OR( AND(G50="SAD", OR(F50="Battleground", F50="Highly Volatile", F50="Opposition Lean")), AND(R50="SAD", OR(F50="Battleground", F50="Highly Volatile", F50="Opposition Lean")) ), "Battleground", OR(K50="SAD", M50="SAD", R50="SAD"), "Expand", TRUE, "Long Shot" ) -> Long Shot | W50: =IFS( AND(G50="BJP", OR(F50="Stronghold", F50="Lean")), "Defend", OR( AND(G50="BJP", OR(F50="Battleground", F50="Highly Volatile", F50="Opposition Lean")), AND(R50="BJP", OR(F50="Battleground", F50="Highly Volatile", F50="Opposition Lean")) ), "Battleground", OR(K50="BJP", M50="BJP", R50="BJP"), "Expand", TRUE, "Long Shot" ) -> Long Shot | X50: =IFS(K50="EMERGING", "YES", COUNTIFS(T50:W50, "<>Long Shot", T50:W50, "<>") >= 3, "YES", TRUE, "")
A51: 48 | B51: Balachaur | C51: SBS Nagar | D51: Doaba | E51: Santosh Kumari Katariaa | F51: =IFS( OR(P51>=75, ((H51<>J51)+(J51<>I51)+(I51<>K51))>=3), "Highly Volatile", AND(COUNTIF(H51:K51, G51)+1>=4, O51<55, P51<65), "Stronghold", AND(COUNTIF(H51:K51, G51)+1>=3, O51<70, P51<75), "Lean", AND(R51<>G51, ((H51=R51)+(J51=R51)+(K51=R51))>=2, O51<60, P51<70), "Opposition Lean", TRUE, "Battleground" ) -> Highly Volatile | G51: AAP | H51: INC | I51: AAP | J51: SAD | K51: INC | M51: SAD | N51: 3.97 | O51: {=_xlfn.XLOOKUP(B51, 'Assembly Competitiveness'!$B$4:$B$120,'Assembly Competitiveness'!$O$4:$O$120, "-")} -> 54.3695 | P51: {=_xlfn.XLOOKUP(B51,'Assembly Volatality'!$B$4:$B$120,'Assembly Volatality'!$L$4:$L$120, "-")} -> 57.87 | Q51: =ROUND(0.45*O51+0.4*P51+0.15*IF(H51<>K51,100,0),1) -> 47.6 | R51: SAD | S51: YES | T51: =IFS( AND(G51="AAP", OR(F51="Stronghold", F51="Lean")), "Defend", OR( AND(G51="AAP", OR(F51="Battleground", F51="Highly Volatile", F51="Opposition Lean")), AND(R51="AAP", OR(F51="Battleground", F51="Highly Volatile", F51="Opposition Lean")) ), "Battleground", OR(K51="AAP", M51="AAP", R51="AAP"), "Expand", TRUE, "Long Shot" ) -> Battleground | U51: =IFS( AND(G51="INC", OR(F51="Stronghold", F51="Lean")), "Defend", OR( AND(G51="INC", OR(F51="Battleground", F51="Highly Volatile", F51="Opposition Lean")), AND(R51="INC", OR(F51="Battleground", F51="Highly Volatile", F51="Opposition Lean")) ), "Battleground", OR(K51="INC", M51="INC", R51="INC"), "Expand", TRUE, "Long Shot" ) -> Expand | V51: =IFS( AND(G51="SAD", OR(F51="Stronghold", F51="Lean")), "Defend", OR( AND(G51="SAD", OR(F51="Battleground", F51="Highly Volatile", F51="Opposition Lean")), AND(R51="SAD", OR(F51="Battleground", F51="Highly Volatile", F51="Opposition Lean")) ), "Battleground", OR(K51="SAD", M51="SAD", R51="SAD"), "Expand", TRUE, "Long Shot" ) -> Battleground | W51: =IFS( AND(G51="BJP", OR(F51="Stronghold", F51="Lean")), "Defend", OR( AND(G51="BJP", OR(F51="Battleground", F51="Highly Volatile", F51="Opposition Lean")), AND(R51="BJP", OR(F51="Battleground", F51="Highly Volatile", F51="Opposition Lean")) ), "Battleground", OR(K51="BJP", M51="BJP", R51="BJP"), "Expand", TRUE, "Long Shot" ) -> Long Shot | X51: =IFS(K51="EMERGING", "YES", COUNTIFS(T51:W51, "<>Long Shot", T51:W51, "<>") >= 3, "YES", TRUE, "") -> YES
A52: 49 | B52: Anandpur Sahib | C52: Rupnagar | D52: Malwa | E52: Harjot Singh Bains | F52: =IFS( OR(P52>=75, ((H52<>J52)+(J52<>I52)+(I52<>K52))>=3), "Highly Volatile", AND(COUNTIF(H52:K52, G52)+1>=4, O52<55, P52<65), "Stronghold", AND(COUNTIF(H52:K52, G52)+1>=3, O52<70, P52<75), "Lean", AND(R52<>G52, ((H52=R52)+(J52=R52)+(K52=R52))>=2, O52<60, P52<70), "Opposition Lean", TRUE, "Battleground" ) -> Lean | G52: AAP | H52: INC | I52: AAP | J52: SAD | K52: AAP | M52: INC | N52: 32.58 | O52: {=_xlfn.XLOOKUP(B52, 'Assembly Competitiveness'!$B$4:$B$120,'Assembly Competitiveness'!$O$4:$O$120, "-")} -> 8.126 | P52: {=_xlfn.XLOOKUP(B52,'Assembly Volatality'!$B$4:$B$120,'Assembly Volatality'!$L$4:$L$120, "-")} -> 46.07 | Q52: =ROUND(0.45*O52+0.4*P52+0.15*IF(H52<>K52,100,0),1) -> 37.1 | R52: INC | T52: =IFS( AND(G52="AAP", OR(F52="Stronghold", F52="Lean")), "Defend", OR( AND(G52="AAP", OR(F52="Battleground", F52="Highly Volatile", F52="Opposition Lean")), AND(R52="AAP", OR(F52="Battleground", F52="Highly Volatile", F52="Opposition Lean")) ), "Battleground", OR(K52="AAP", M52="AAP", R52="AAP"), "Expand", TRUE, "Long Shot" ) -> Defend | U52: =IFS( AND(G52="INC", OR(F52="Stronghold", F52="Lean")), "Defend", OR( AND(G52="INC", OR(F52="Battleground", F52="Highly Volatile", F52="Opposition Lean")), AND(R52="INC", OR(F52="Battleground", F52="Highly Volatile", F52="Opposition Lean")) ), "Battleground", OR(K52="INC", M52="INC", R52="INC"), "Expand", TRUE, "Long Shot" ) -> Expand | V52: =IFS( AND(G52="SAD", OR(F52="Stronghold", F52="Lean")), "Defend", OR( AND(G52="SAD", OR(F52="Battleground", F52="Highly Volatile", F52="Opposition Lean")), AND(R52="SAD", OR(F52="Battleground", F52="Highly Volatile", F52="Opposition Lean")) ), "Battleground", OR(K52="SAD", M52="SAD", R52="SAD"), "Expand", TRUE, "Long Shot" ) -> Long Shot | W52: =IFS( AND(G52="BJP", OR(F52="Stronghold", F52="Lean")), "Defend", OR( AND(G52="BJP", OR(F52="Battleground", F52="Highly Volatile", F52="Opposition Lean")), AND(R52="BJP", OR(F52="Battleground", F52="Highly Volatile", F52="Opposition Lean")) ), "Battleground", OR(K52="BJP", M52="BJP", R52="BJP"), "Expand", TRUE, "Long Shot" ) -> Long Shot | X52: =IFS(K52="EMERGING", "YES", COUNTIFS(T52:W52, "<>Long Shot", T52:W52, "<>") >= 3, "YES", TRUE, "")
A53: 50 | B53: Rupnagar | C53: Rupnagar | D53: Malwa | E53: Dinesh Kumar Chadha | F53: =IFS( OR(P53>=75, ((H53<>J53)+(J53<>I53)+(I53<>K53))>=3), "Highly Volatile", AND(COUNTIF(H53:K53, G53)+1>=4, O53<55, P53<65), "Stronghold", AND(COUNTIF(H53:K53, G53)+1>=3, O53<70, P53<75), "Lean", AND(R53<>G53, ((H53=R53)+(J53=R53)+(K53=R53))>=2, O53<60, P53<70), "Opposition Lean", TRUE, "Battleground" ) -> Stronghold | G53: AAP | H53: AAP | I53: AAP | J53: INC | K53: AAP | M53: INC | N53: 17.49 | O53: {=_xlfn.XLOOKUP(B53, 'Assembly Competitiveness'!$B$4:$B$120,'Assembly Competitiveness'!$O$4:$O$120, "-")} -> 7.6415 | P53: {=_xlfn.XLOOKUP(B53,'Assembly Volatality'!$B$4:$B$120,'Assembly Volatality'!$L$4:$L$120, "-")} -> 3.82 | Q53: =ROUND(0.45*O53+0.4*P53+0.15*IF(H53<>K53,100,0),1) -> 5 | R53: INC | T53: =IFS( AND(G53="AAP", OR(F53="Stronghold", F53="Lean")), "Defend", OR( AND(G53="AAP", OR(F53="Battleground", F53="Highly Volatile", F53="Opposition Lean")), AND(R53="AAP", OR(F53="Battleground", F53="Highly Volatile", F53="Opposition Lean")) ), "Battleground", OR(K53="AAP", M53="AAP", R53="AAP"), "Expand", TRUE, "Long Shot" ) -> Defend | U53: =IFS( AND(G53="INC", OR(F53="Stronghold", F53="Lean")), "Defend", OR( AND(G53="INC", OR(F53="Battleground", F53="Highly Volatile", F53="Opposition Lean")), AND(R53="INC", OR(F53="Battleground", F53="Highly Volatile", F53="Opposition Lean")) ), "Battleground", OR(K53="INC", M53="INC", R53="INC"), "Expand", TRUE, "Long Shot" ) -> Expand | V53: =IFS( AND(G53="SAD", OR(F53="Stronghold", F53="Lean")), "Defend", OR( AND(G53="SAD", OR(F53="Battleground", F53="Highly Volatile", F53="Opposition Lean")), AND(R53="SAD", OR(F53="Battleground", F53="Highly Volatile", F53="Opposition Lean")) ), "Battleground", OR(K53="SAD", M53="SAD", R53="SAD"), "Expand", TRUE, "Long Shot" ) -> Long Shot | W53: =IFS( AND(G53="BJP", OR(F53="Stronghold", F53="Lean")), "Defend", OR( AND(G53="BJP", OR(F53="Battleground", F53="Highly Volatile", F53="Opposition Lean")), AND(R53="BJP", OR(F53="Battleground", F53="Highly Volatile", F53="Opposition Lean")) ), "Battleground", OR(K53="BJP", M53="BJP", R53="BJP"), "Expand", TRUE, "Long Shot" ) -> Long Shot | X53: =IFS(K53="EMERGING", "YES", COUNTIFS(T53:W53, "<>Long Shot", T53:W53, "<>") >= 3, "YES", TRUE, "")
A54: 51 | B54: Chamkaur Sahib | C54: Rupnagar | D54: Malwa | E54: Charanjit Singh | F54: =IFS( OR(P54>=75, ((H54<>J54)+(J54<>I54)+(I54<>K54))>=3), "Highly Volatile", AND(COUNTIF(H54:K54, G54)+1>=4, O54<55, P54<65), "Stronghold", AND(COUNTIF(H54:K54, G54)+1>=3, O54<70, P54<75), "Lean", AND(R54<>G54, ((H54=R54)+(J54=R54)+(K54=R54))>=2, O54<60, P54<70), "Opposition Lean", TRUE, "Battleground" ) -> Opposition Lean | G54: AAP | H54: INC | I54: AAP | J54: INC | K54: INC | M54: INC | N54: 5.41 | O54: {=_xlfn.XLOOKUP(B54, 'Assembly Competitiveness'!$B$4:$B$120,'Assembly Competitiveness'!$O$4:$O$120, "-")} -> 55.5515 | P54: {=_xlfn.XLOOKUP(B54,'Assembly Volatality'!$B$4:$B$120,'Assembly Volatality'!$L$4:$L$120, "-")} -> 45.97 | Q54: =ROUND(0.45*O54+0.4*P54+0.15*IF(H54<>K54,100,0),1) -> 43.4 | R54: INC | S54: YES | T54: =IFS( AND(G54="AAP", OR(F54="Stronghold", F54="Lean")), "Defend", OR( AND(G54="AAP", OR(F54="Battleground", F54="Highly Volatile", F54="Opposition Lean")), AND(R54="AAP", OR(F54="Battleground", F54="Highly Volatile", F54="Opposition Lean")) ), "Battleground", OR(K54="AAP", M54="AAP", R54="AAP"), "Expand", TRUE, "Long Shot" ) -> Battleground | U54: =IFS( AND(G54="INC", OR(F54="Stronghold", F54="Lean")), "Defend", OR( AND(G54="INC", OR(F54="Battleground", F54="Highly Volatile", F54="Opposition Lean")), AND(R54="INC", OR(F54="Battleground", F54="Highly Volatile", F54="Opposition Lean")) ), "Battleground", OR(K54="INC", M54="INC", R54="INC"), "Expand", TRUE, "Long Shot" ) -> Battleground | V54: =IFS( AND(G54="SAD", OR(F54="Stronghold", F54="Lean")), "Defend", OR( AND(G54="SAD", OR(F54="Battleground", F54="Highly Volatile", F54="Opposition Lean")), AND(R54="SAD", OR(F54="Battleground", F54="Highly Volatile", F54="Opposition Lean")) ), "Battleground", OR(K54="SAD", M54="SAD", R54="SAD"), "Expand", TRUE, "Long Shot" ) -> Long Shot | W54: =IFS( AND(G54="BJP", OR(F54="Stronghold", F54="Lean")), "Defend", OR( AND(G54="BJP", OR(F54="Battleground", F54="Highly Volatile", F54="Opposition Lean")), AND(R54="BJP", OR(F54="Battleground", F54="Highly Volatile", F54="Opposition Lean")) ), "Battleground", OR(K54="BJP", M54="BJP", R54="BJP"), "Expand", TRUE, "Long Shot" ) -> Long Shot | X54: =IFS(K54="EMERGING", "YES", COUNTIFS(T54:W54, "<>Long Shot", T54:W54, "<>") >= 3, "YES", TRUE, "")
A55: 52 | B55: Kharar | C55: SAS Nagar | D55: Malwa | E55: Anmol Gagan Maan | F55: =IFS( OR(P55>=75, ((H55<>J55)+(J55<>I55)+(I55<>K55))>=3), "Highly Volatile", AND(COUNTIF(H55:K55, G55)+1>=4, O55<55, P55<65), "Stronghold", AND(COUNTIF(H55:K55, G55)+1>=3, O55<70, P55<75), "Lean", AND(R55<>G55, ((H55=R55)+(J55=R55)+(K55=R55))>=2, O55<60, P55<70), "Opposition Lean", TRUE, "Battleground" ) -> Highly Volatile | G55: AAP | H55: AAP | I55: AAP | J55: INC | K55: INC | M55: SAD | N55: 21.53 | O55: {=_xlfn.XLOOKUP(B55, 'Assembly Competitiveness'!$B$4:$B$120,'Assembly Competitiveness'!$O$4:$O$120, "-")} -> 36.834 | P55: {=_xlfn.XLOOKUP(B55,'Assembly Volatality'!$B$4:$B$120,'Assembly Volatality'!$L$4:$L$120, "-")} -> 35.47 | Q55: =ROUND(0.45*O55+0.4*P55+0.15*IF(H55<>K55,100,0),1) -> 45.8 | R55: SAD | S55: YES | T55: =IFS( AND(G55="AAP", OR(F55="Stronghold", F55="Lean")), "Defend", OR( AND(G55="AAP", OR(F55="Battleground", F55="Highly Volatile", F55="Opposition Lean")), AND(R55="AAP", OR(F55="Battleground", F55="Highly Volatile", F55="Opposition Lean")) ), "Battleground", OR(K55="AAP", M55="AAP", R55="AAP"), "Expand", TRUE, "Long Shot" ) -> Battleground | U55: =IFS( AND(G55="INC", OR(F55="Stronghold", F55="Lean")), "Defend", OR( AND(G55="INC", OR(F55="Battleground", F55="Highly Volatile", F55="Opposition Lean")), AND(R55="INC", OR(F55="Battleground", F55="Highly Volatile", F55="Opposition Lean")) ), "Battleground", OR(K55="INC", M55="INC", R55="INC"), "Expand", TRUE, "Long Shot" ) -> Expand | V55: =IFS( AND(G55="SAD", OR(F55="Stronghold", F55="Lean")), "Defend", OR( AND(G55="SAD", OR(F55="Battleground", F55="Highly Volatile", F55="Opposition Lean")), AND(R55="SAD", OR(F55="Battleground", F55="Highly Volatile", F55="Opposition Lean")) ), "Battleground", OR(K55="SAD", M55="SAD", R55="SAD"), "Expand", TRUE, "Long Shot" ) -> Battleground | W55: =IFS( AND(G55="BJP", OR(F55="Stronghold", F55="Lean")), "Defend", OR( AND(G55="BJP", OR(F55="Battleground", F55="Highly Volatile", F55="Opposition Lean")), AND(R55="BJP", OR(F55="Battleground", F55="Highly Volatile", F55="Opposition Lean")) ), "Battleground", OR(K55="BJP", M55="BJP", R55="BJP"), "Expand", TRUE, "Long Shot" ) -> Long Shot | X55: =IFS(K55="EMERGING", "YES", COUNTIFS(T55:W55, "<>Long Shot", T55:W55, "<>") >= 3, "YES", TRUE, "") -> YES
A56: 53 | B56: SAS Nagar | C56: SAS Nagar | D56: Malwa | E56: Kulwant Singh | F56: =IFS( OR(P56>=75, ((H56<>J56)+(J56<>I56)+(I56<>K56))>=3), "Highly Volatile", AND(COUNTIF(H56:K56, G56)+1>=4, O56<55, P56<65), "Stronghold", AND(COUNTIF(H56:K56, G56)+1>=3, O56<70, P56<75), "Lean", AND(R56<>G56, ((H56=R56)+(J56=R56)+(K56=R56))>=2, O56<60, P56<70), "Opposition Lean", TRUE, "Battleground" ) -> Opposition Lean | G56: AAP | H56: INC | I56: AAP | J56: INC | K56: INC | M56: INC | N56: 22.14 | O56: {=_xlfn.XLOOKUP(B56, 'Assembly Competitiveness'!$B$4:$B$120,'Assembly Competitiveness'!$O$4:$O$120, "-")} -> 10.912 | P56: {=_xlfn.XLOOKUP(B56,'Assembly Volatality'!$B$4:$B$120,'Assembly Volatality'!$L$4:$L$120, "-")} -> 44.02 | Q56: =ROUND(0.45*O56+0.4*P56+0.15*IF(H56<>K56,100,0),1) -> 22.5 | R56: INC | S56: YES | T56: =IFS( AND(G56="AAP", OR(F56="Stronghold", F56="Lean")), "Defend", OR( AND(G56="AAP", OR(F56="Battleground", F56="Highly Volatile", F56="Opposition Lean")), AND(R56="AAP", OR(F56="Battleground", F56="Highly Volatile", F56="Opposition Lean")) ), "Battleground", OR(K56="AAP", M56="AAP", R56="AAP"), "Expand", TRUE, "Long Shot" ) -> Battleground | U56: =IFS( AND(G56="INC", OR(F56="Stronghold", F56="Lean")), "Defend", OR( AND(G56="INC", OR(F56="Battleground", F56="Highly Volatile", F56="Opposition Lean")), AND(R56="INC", OR(F56="Battleground", F56="Highly Volatile", F56="Opposition Lean")) ), "Battleground", OR(K56="INC", M56="INC", R56="INC"), "Expand", TRUE, "Long Shot" ) -> Battleground | V56: =IFS( AND(G56="SAD", OR(F56="Stronghold", F56="Lean")), "Defend", OR( AND(G56="SAD", OR(F56="Battleground", F56="Highly Volatile", F56="Opposition Lean")), AND(R56="SAD", OR(F56="Battleground", F56="Highly Volatile", F56="Opposition Lean")) ), "Battleground", OR(K56="SAD", M56="SAD", R56="SAD"), "Expand", TRUE, "Long Shot" ) -> Long Shot | W56: =IFS( AND(G56="BJP", OR(F56="Stronghold", F56="Lean")), "Defend", OR( AND(G56="BJP", OR(F56="Battleground", F56="Highly Volatile", F56="Opposition Lean")), AND(R56="BJP", OR(F56="Battleground", F56="Highly Volatile", F56="Opposition Lean")) ), "Battleground", OR(K56="BJP", M56="BJP", R56="BJP"), "Expand", TRUE, "Long Shot" ) -> Long Shot | X56: =IFS(K56="EMERGING", "YES", COUNTIFS(T56:W56, "<>Long Shot", T56:W56, "<>") >= 3, "YES", TRUE, "")
A57: 54 | B57: Bassi Pathana | C57: Fatehgarh Sahib | D57: Malwa | E57: Rupinder Singh | F57: =IFS( OR(P57>=75, ((H57<>J57)+(J57<>I57)+(I57<>K57))>=3), "Highly Volatile", AND(COUNTIF(H57:K57, G57)+1>=4, O57<55, P57<65), "Stronghold", AND(COUNTIF(H57:K57, G57)+1>=3, O57<70, P57<75), "Lean", AND(R57<>G57, ((H57=R57)+(J57=R57)+(K57=R57))>=2, O57<60, P57<70), "Opposition Lean", TRUE, "Battleground" ) -> Lean | G57: AAP | H57: INC | I57: AAP | J57: INC | K57: AAP | M57: INC | N57: 33.98 | O57: {=_xlfn.XLOOKUP(B57, 'Assembly Competitiveness'!$B$4:$B$120,'Assembly Competitiveness'!$O$4:$O$120, "-")} -> 21.12 | P57: {=_xlfn.XLOOKUP(B57,'Assembly Volatality'!$B$4:$B$120,'Assembly Volatality'!$L$4:$L$120, "-")} -> 59.33 | Q57: =ROUND(0.45*O57+0.4*P57+0.15*IF(H57<>K57,100,0),1) -> 48.2 | R57: INC | T57: =IFS( AND(G57="AAP", OR(F57="Stronghold", F57="Lean")), "Defend", OR( AND(G57="AAP", OR(F57="Battleground", F57="Highly Volatile", F57="Opposition Lean")), AND(R57="AAP", OR(F57="Battleground", F57="Highly Volatile", F57="Opposition Lean")) ), "Battleground", OR(K57="AAP", M57="AAP", R57="AAP"), "Expand", TRUE, "Long Shot" ) -> Defend | U57: =IFS( AND(G57="INC", OR(F57="Stronghold", F57="Lean")), "Defend", OR( AND(G57="INC", OR(F57="Battleground", F57="Highly Volatile", F57="Opposition Lean")), AND(R57="INC", OR(F57="Battleground", F57="Highly Volatile", F57="Opposition Lean")) ), "Battleground", OR(K57="INC", M57="INC", R57="INC"), "Expand", TRUE, "Long Shot" ) -> Expand | V57: =IFS( AND(G57="SAD", OR(F57="Stronghold", F57="Lean")), "Defend", OR( AND(G57="SAD", OR(F57="Battleground", F57="Highly Volatile", F57="Opposition Lean")), AND(R57="SAD", OR(F57="Battleground", F57="Highly Volatile", F57="Opposition Lean")) ), "Battleground", OR(K57="SAD", M57="SAD", R57="SAD"), "Expand", TRUE, "Long Shot" ) -> Long Shot | W57: =IFS( AND(G57="BJP", OR(F57="Stronghold", F57="Lean")), "Defend", OR( AND(G57="BJP", OR(F57="Battleground", F57="Highly Volatile", F57="Opposition Lean")), AND(R57="BJP", OR(F57="Battleground", F57="Highly Volatile", F57="Opposition Lean")) ), "Battleground", OR(K57="BJP", M57="BJP", R57="BJP"), "Expand", TRUE, "Long Shot" ) -> Long Shot | X57: =IFS(K57="EMERGING", "YES", COUNTIFS(T57:W57, "<>Long Shot", T57:W57, "<>") >= 3, "YES", TRUE, "")
A58: 55 | B58: Fatehgarh Sahib | C58: Fatehgarh Sahib | D58: Malwa | E58: Lakhbir Singh Rai | F58: =IFS( OR(P58>=75, ((H58<>J58)+(J58<>I58)+(I58<>K58))>=3), "Highly Volatile", AND(COUNTIF(H58:K58, G58)+1>=4, O58<55, P58<65), "Stronghold", AND(COUNTIF(H58:K58, G58)+1>=3, O58<70, P58<75), "Lean", AND(R58<>G58, ((H58=R58)+(J58=R58)+(K58=R58))>=2, O58<60, P58<70), "Opposition Lean", TRUE, "Battleground" ) -> Lean | G58: AAP | H58: INC | I58: AAP | J58: INC | K58: AAP | M58: INC | N58: 25.81 | O58: {=_xlfn.XLOOKUP(B58, 'Assembly Competitiveness'!$B$4:$B$120,'Assembly Competitiveness'!$O$4:$O$120, "-")} -> 3.374 | P58: {=_xlfn.XLOOKUP(B58,'Assembly Volatality'!$B$4:$B$120,'Assembly Volatality'!$L$4:$L$120, "-")} -> 41.99 | Q58: =ROUND(0.45*O58+0.4*P58+0.15*IF(H58<>K58,100,0),1) -> 33.3 | R58: INC | T58: =IFS( AND(G58="AAP", OR(F58="Stronghold", F58="Lean")), "Defend", OR( AND(G58="AAP", OR(F58="Battleground", F58="Highly Volatile", F58="Opposition Lean")), AND(R58="AAP", OR(F58="Battleground", F58="Highly Volatile", F58="Opposition Lean")) ), "Battleground", OR(K58="AAP", M58="AAP", R58="AAP"), "Expand", TRUE, "Long Shot" ) -> Defend | U58: =IFS( AND(G58="INC", OR(F58="Stronghold", F58="Lean")), "Defend", OR( AND(G58="INC", OR(F58="Battleground", F58="Highly Volatile", F58="Opposition Lean")), AND(R58="INC", OR(F58="Battleground", F58="Highly Volatile", F58="Opposition Lean")) ), "Battleground", OR(K58="INC", M58="INC", R58="INC"), "Expand", TRUE, "Long Shot" ) -> Expand | V58: =IFS( AND(G58="SAD", OR(F58="Stronghold", F58="Lean")), "Defend", OR( AND(G58="SAD", OR(F58="Battleground", F58="Highly Volatile", F58="Opposition Lean")), AND(R58="SAD", OR(F58="Battleground", F58="Highly Volatile", F58="Opposition Lean")) ), "Battleground", OR(K58="SAD", M58="SAD", R58="SAD"), "Expand", TRUE, "Long Shot" ) -> Long Shot | W58: =IFS( AND(G58="BJP", OR(F58="Stronghold", F58="Lean")), "Defend", OR( AND(G58="BJP", OR(F58="Battleground", F58="Highly Volatile", F58="Opposition Lean")), AND(R58="BJP", OR(F58="Battleground", F58="Highly Volatile", F58="Opposition Lean")) ), "Battleground", OR(K58="BJP", M58="BJP", R58="BJP"), "Expand", TRUE, "Long Shot" ) -> Long Shot | X58: =IFS(K58="EMERGING", "YES", COUNTIFS(T58:W58, "<>Long Shot", T58:W58, "<>") >= 3, "YES", TRUE, "")
A59: 56 | B59: Amloh | C59: Fatehgarh Sahib | D59: Malwa | E59: Gurinder Singh Garry Birring | F59: =IFS( OR(P59>=75, ((H59<>J59)+(J59<>I59)+(I59<>K59))>=3), "Highly Volatile", AND(COUNTIF(H59:K59, G59)+1>=4, O59<55, P59<65), "Stronghold", AND(COUNTIF(H59:K59, G59)+1>=3, O59<70, P59<75), "Lean", AND(R59<>G59, ((H59=R59)+(J59=R59)+(K59=R59))>=2, O59<60, P59<70), "Opposition Lean", TRUE, "Battleground" ) -> Battleground | G59: AAP | H59: INC | I59: AAP | J59: INC | K59: INC | M59: SAD | N59: 21.74 | O59: {=_xlfn.XLOOKUP(B59, 'Assembly Competitiveness'!$B$4:$B$120,'Assembly Competitiveness'!$O$4:$O$120, "-")} -> 33.796 | P59: {=_xlfn.XLOOKUP(B59,'Assembly Volatality'!$B$4:$B$120,'Assembly Volatality'!$L$4:$L$120, "-")} -> 62.59 | Q59: =ROUND(0.45*O59+0.4*P59+0.15*IF(H59<>K59,100,0),1) -> 40.2 | R59: SAD | S59: YES | T59: =IFS( AND(G59="AAP", OR(F59="Stronghold", F59="Lean")), "Defend", OR( AND(G59="AAP", OR(F59="Battleground", F59="Highly Volatile", F59="Opposition Lean")), AND(R59="AAP", OR(F59="Battleground", F59="Highly Volatile", F59="Opposition Lean")) ), "Battleground", OR(K59="AAP", M59="AAP", R59="AAP"), "Expand", TRUE, "Long Shot" ) -> Battleground | U59: =IFS( AND(G59="INC", OR(F59="Stronghold", F59="Lean")), "Defend", OR( AND(G59="INC", OR(F59="Battleground", F59="Highly Volatile", F59="Opposition Lean")), AND(R59="INC", OR(F59="Battleground", F59="Highly Volatile", F59="Opposition Lean")) ), "Battleground", OR(K59="INC", M59="INC", R59="INC"), "Expand", TRUE, "Long Shot" ) -> Expand | V59: =IFS( AND(G59="SAD", OR(F59="Stronghold", F59="Lean")), "Defend", OR( AND(G59="SAD", OR(F59="Battleground", F59="Highly Volatile", F59="Opposition Lean")), AND(R59="SAD", OR(F59="Battleground", F59="Highly Volatile", F59="Opposition Lean")) ), "Battleground", OR(K59="SAD", M59="SAD", R59="SAD"), "Expand", TRUE, "Long Shot" ) -> Battleground | W59: =IFS( AND(G59="BJP", OR(F59="Stronghold", F59="Lean")), "Defend", OR( AND(G59="BJP", OR(F59="Battleground", F59="Highly Volatile", F59="Opposition Lean")), AND(R59="BJP", OR(F59="Battleground", F59="Highly Volatile", F59="Opposition Lean")) ), "Battleground", OR(K59="BJP", M59="BJP", R59="BJP"), "Expand", TRUE, "Long Shot" ) -> Long Shot | X59: =IFS(K59="EMERGING", "YES", COUNTIFS(T59:W59, "<>Long Shot", T59:W59, "<>") >= 3, "YES", TRUE, "") -> YES
A60: 57 | B60: Khanna | C60: Ludhiana | D60: Malwa | E60: Tarunpreet Singh Sond | F60: =IFS( OR(P60>=75, ((H60<>J60)+(J60<>I60)+(I60<>K60))>=3), "Highly Volatile", AND(COUNTIF(H60:K60, G60)+1>=4, O60<55, P60<65), "Stronghold", AND(COUNTIF(H60:K60, G60)+1>=3, O60<70, P60<75), "Lean", AND(R60<>G60, ((H60=R60)+(J60=R60)+(K60=R60))>=2, O60<60, P60<70), "Opposition Lean", TRUE, "Battleground" ) -> Lean | G60: AAP | H60: INC | I60: AAP | J60: INC | K60: AAP | M60: SAD | N60: 27.85 | O60: {=_xlfn.XLOOKUP(B60, 'Assembly Competitiveness'!$B$4:$B$120,'Assembly Competitiveness'!$O$4:$O$120, "-")} -> 8.208 | P60: {=_xlfn.XLOOKUP(B60,'Assembly Volatality'!$B$4:$B$120,'Assembly Volatality'!$L$4:$L$120, "-")} -> 45.15 | Q60: =ROUND(0.45*O60+0.4*P60+0.15*IF(H60<>K60,100,0),1) -> 36.8 | R60: SAD | T60: =IFS( AND(G60="AAP", OR(F60="Stronghold", F60="Lean")), "Defend", OR( AND(G60="AAP", OR(F60="Battleground", F60="Highly Volatile", F60="Opposition Lean")), AND(R60="AAP", OR(F60="Battleground", F60="Highly Volatile", F60="Opposition Lean")) ), "Battleground", OR(K60="AAP", M60="AAP", R60="AAP"), "Expand", TRUE, "Long Shot" ) -> Defend | U60: =IFS( AND(G60="INC", OR(F60="Stronghold", F60="Lean")), "Defend", OR( AND(G60="INC", OR(F60="Battleground", F60="Highly Volatile", F60="Opposition Lean")), AND(R60="INC", OR(F60="Battleground", F60="Highly Volatile", F60="Opposition Lean")) ), "Battleground", OR(K60="INC", M60="INC", R60="INC"), "Expand", TRUE, "Long Shot" ) -> Long Shot | V60: =IFS( AND(G60="SAD", OR(F60="Stronghold", F60="Lean")), "Defend", OR( AND(G60="SAD", OR(F60="Battleground", F60="Highly Volatile", F60="Opposition Lean")), AND(R60="SAD", OR(F60="Battleground", F60="Highly Volatile", F60="Opposition Lean")) ), "Battleground", OR(K60="SAD", M60="SAD", R60="SAD"), "Expand", TRUE, "Long Shot" ) -> Expand | W60: =IFS( AND(G60="BJP", OR(F60="Stronghold", F60="Lean")), "Defend", OR( AND(G60="BJP", OR(F60="Battleground", F60="Highly Volatile", F60="Opposition Lean")), AND(R60="BJP", OR(F60="Battleground", F60="Highly Volatile", F60="Opposition Lean")) ), "Battleground", OR(K60="BJP", M60="BJP", R60="BJP"), "Expand", TRUE, "Long Shot" ) -> Long Shot | X60: =IFS(K60="EMERGING", "YES", COUNTIFS(T60:W60, "<>Long Shot", T60:W60, "<>") >= 3, "YES", TRUE, "")
A61: 58 | B61: Samrala | C61: Ludhiana | D61: Malwa | E61: Jagtar Singh Diyalpura | F61: =IFS( OR(P61>=75, ((H61<>J61)+(J61<>I61)+(I61<>K61))>=3), "Highly Volatile", AND(COUNTIF(H61:K61, G61)+1>=4, O61<55, P61<65), "Stronghold", AND(COUNTIF(H61:K61, G61)+1>=3, O61<70, P61<75), "Lean", AND(R61<>G61, ((H61=R61)+(J61=R61)+(K61=R61))>=2, O61<60, P61<70), "Opposition Lean", TRUE, "Battleground" ) -> Battleground | G61: AAP | H61: INC | I61: AAP | J61: INC | K61: INC | M61: SAD | N61: 23.3 | O61: {=_xlfn.XLOOKUP(B61, 'Assembly Competitiveness'!$B$4:$B$120,'Assembly Competitiveness'!$O$4:$O$120, "-")} -> 27.812 | P61: {=_xlfn.XLOOKUP(B61,'Assembly Volatality'!$B$4:$B$120,'Assembly Volatality'!$L$4:$L$120, "-")} -> 59.44 | Q61: =ROUND(0.45*O61+0.4*P61+0.15*IF(H61<>K61,100,0),1) -> 36.3 | R61: SAD | S61: YES | T61: =IFS( AND(G61="AAP", OR(F61="Stronghold", F61="Lean")), "Defend", OR( AND(G61="AAP", OR(F61="Battleground", F61="Highly Volatile", F61="Opposition Lean")), AND(R61="AAP", OR(F61="Battleground", F61="Highly Volatile", F61="Opposition Lean")) ), "Battleground", OR(K61="AAP", M61="AAP", R61="AAP"), "Expand", TRUE, "Long Shot" ) -> Battleground | U61: =IFS( AND(G61="INC", OR(F61="Stronghold", F61="Lean")), "Defend", OR( AND(G61="INC", OR(F61="Battleground", F61="Highly Volatile", F61="Opposition Lean")), AND(R61="INC", OR(F61="Battleground", F61="Highly Volatile", F61="Opposition Lean")) ), "Battleground", OR(K61="INC", M61="INC", R61="INC"), "Expand", TRUE, "Long Shot" ) -> Expand | V61: =IFS( AND(G61="SAD", OR(F61="Stronghold", F61="Lean")), "Defend", OR( AND(G61="SAD", OR(F61="Battleground", F61="Highly Volatile", F61="Opposition Lean")), AND(R61="SAD", OR(F61="Battleground", F61="Highly Volatile", F61="Opposition Lean")) ), "Battleground", OR(K61="SAD", M61="SAD", R61="SAD"), "Expand", TRUE, "Long Shot" ) -> Battleground | W61: =IFS( AND(G61="BJP", OR(F61="Stronghold", F61="Lean")), "Defend", OR( AND(G61="BJP", OR(F61="Battleground", F61="Highly Volatile", F61="Opposition Lean")), AND(R61="BJP", OR(F61="Battleground", F61="Highly Volatile", F61="Opposition Lean")) ), "Battleground", OR(K61="BJP", M61="BJP", R61="BJP"), "Expand", TRUE, "Long Shot" ) -> Long Shot | X61: =IFS(K61="EMERGING", "YES", COUNTIFS(T61:W61, "<>Long Shot", T61:W61, "<>") >= 3, "YES", TRUE, "") -> YES
A62: 59 | B62: Sahnewal | C62: Ludhiana | D62: Malwa | E62: Hardeep Singh Mundian | F62: =IFS( OR(P62>=75, ((H62<>J62)+(J62<>I62)+(I62<>K62))>=3), "Highly Volatile", AND(COUNTIF(H62:K62, G62)+1>=4, O62<55, P62<65), "Stronghold", AND(COUNTIF(H62:K62, G62)+1>=3, O62<70, P62<75), "Lean", AND(R62<>G62, ((H62=R62)+(J62=R62)+(K62=R62))>=2, O62<60, P62<70), "Opposition Lean", TRUE, "Battleground" ) -> Battleground | G62: AAP | H62: SAD | I62: AAP | J62: SAD | K62: INC | M62: INC | N62: 8.51 | O62: {=_xlfn.XLOOKUP(B62, 'Assembly Competitiveness'!$B$4:$B$120,'Assembly Competitiveness'!$O$4:$O$120, "-")} -> 55.4205 | P62: {=_xlfn.XLOOKUP(B62,'Assembly Volatality'!$B$4:$B$120,'Assembly Volatality'!$L$4:$L$120, "-")} -> 53.74 | Q62: =ROUND(0.45*O62+0.4*P62+0.15*IF(H62<>K62,100,0),1) -> 61.4 | R62: INC | S62: YES | T62: =IFS( AND(G62="AAP", OR(F62="Stronghold", F62="Lean")), "Defend", OR( AND(G62="AAP", OR(F62="Battleground", F62="Highly Volatile", F62="Opposition Lean")), AND(R62="AAP", OR(F62="Battleground", F62="Highly Volatile", F62="Opposition Lean")) ), "Battleground", OR(K62="AAP", M62="AAP", R62="AAP"), "Expand", TRUE, "Long Shot" ) -> Battleground | U62: =IFS( AND(G62="INC", OR(F62="Stronghold", F62="Lean")), "Defend", OR( AND(G62="INC", OR(F62="Battleground", F62="Highly Volatile", F62="Opposition Lean")), AND(R62="INC", OR(F62="Battleground", F62="Highly Volatile", F62="Opposition Lean")) ), "Battleground", OR(K62="INC", M62="INC", R62="INC"), "Expand", TRUE, "Long Shot" ) -> Battleground | V62: =IFS( AND(G62="SAD", OR(F62="Stronghold", F62="Lean")), "Defend", OR( AND(G62="SAD", OR(F62="Battleground", F62="Highly Volatile", F62="Opposition Lean")), AND(R62="SAD", OR(F62="Battleground", F62="Highly Volatile", F62="Opposition Lean")) ), "Battleground", OR(K62="SAD", M62="SAD", R62="SAD"), "Expand", TRUE, "Long Shot" ) -> Long Shot | W62: =IFS( AND(G62="BJP", OR(F62="Stronghold", F62="Lean")), "Defend", OR( AND(G62="BJP", OR(F62="Battleground", F62="Highly Volatile", F62="Opposition Lean")), AND(R62="BJP", OR(F62="Battleground", F62="Highly Volatile", F62="Opposition Lean")) ), "Battleground", OR(K62="BJP", M62="BJP", R62="BJP"), "Expand", TRUE, "Long Shot" ) -> Long Shot | X62: =IFS(K62="EMERGING", "YES", COUNTIFS(T62:W62, "<>Long Shot", T62:W62, "<>") >= 3, "YES", TRUE, "")
A63: 60 | B63: Ludhiana East | C63: Ludhiana | D63: Malwa | E63: Daljit Singh Grewal (Bhola) | F63: =IFS( OR(P63>=75, ((H63<>J63)+(J63<>I63)+(I63<>K63))>=3), "Highly Volatile", AND(COUNTIF(H63:K63, G63)+1>=4, O63<55, P63<65), "Stronghold", AND(COUNTIF(H63:K63, G63)+1>=3, O63<70, P63<75), "Lean", AND(R63<>G63, ((H63=R63)+(J63=R63)+(K63=R63))>=2, O63<60, P63<70), "Opposition Lean", TRUE, "Battleground" ) -> Opposition Lean | G63: AAP | H63: INC | I63: AAP | J63: INC | K63: BJP | M63: INC | N63: 25 | O63: {=_xlfn.XLOOKUP(B63, 'Assembly Competitiveness'!$B$4:$B$120,'Assembly Competitiveness'!$O$4:$O$120, "-")} -> 38.292 | P63: {=_xlfn.XLOOKUP(B63,'Assembly Volatality'!$B$4:$B$120,'Assembly Volatality'!$L$4:$L$120, "-")} -> 68.31 | Q63: =ROUND(0.45*O63+0.4*P63+0.15*IF(H63<>K63,100,0),1) -> 59.6 | R63: INC | S63: YES | T63: =IFS( AND(G63="AAP", OR(F63="Stronghold", F63="Lean")), "Defend", OR( AND(G63="AAP", OR(F63="Battleground", F63="Highly Volatile", F63="Opposition Lean")), AND(R63="AAP", OR(F63="Battleground", F63="Highly Volatile", F63="Opposition Lean")) ), "Battleground", OR(K63="AAP", M63="AAP", R63="AAP"), "Expand", TRUE, "Long Shot" ) -> Battleground | U63: =IFS( AND(G63="INC", OR(F63="Stronghold", F63="Lean")), "Defend", OR( AND(G63="INC", OR(F63="Battleground", F63="Highly Volatile", F63="Opposition Lean")), AND(R63="INC", OR(F63="Battleground", F63="Highly Volatile", F63="Opposition Lean")) ), "Battleground", OR(K63="INC", M63="INC", R63="INC"), "Expand", TRUE, "Long Shot" ) -> Battleground | V63: =IFS( AND(G63="SAD", OR(F63="Stronghold", F63="Lean")), "Defend", OR( AND(G63="SAD", OR(F63="Battleground", F63="Highly Volatile", F63="Opposition Lean")), AND(R63="SAD", OR(F63="Battleground", F63="Highly Volatile", F63="Opposition Lean")) ), "Battleground", OR(K63="SAD", M63="SAD", R63="SAD"), "Expand", TRUE, "Long Shot" ) -> Long Shot | W63: =IFS( AND(G63="BJP", OR(F63="Stronghold", F63="Lean")), "Defend", OR( AND(G63="BJP", OR(F63="Battleground", F63="Highly Volatile", F63="Opposition Lean")), AND(R63="BJP", OR(F63="Battleground", F63="Highly Volatile", F63="Opposition Lean")) ), "Battleground", OR(K63="BJP", M63="BJP", R63="BJP"), "Expand", TRUE, "Long Shot" ) -> Expand | X63: =IFS(K63="EMERGING", "YES", COUNTIFS(T63:W63, "<>Long Shot", T63:W63, "<>") >= 3, "YES", TRUE, "") -> YES
A64: 61 | B64: Ludhiana South | C64: Ludhiana | D64: Malwa | E64: Rajinder Pal Kaur | F64: =IFS( OR(P64>=75, ((H64<>J64)+(J64<>I64)+(I64<>K64))>=3), "Highly Volatile", AND(COUNTIF(H64:K64, G64)+1>=4, O64<55, P64<65), "Stronghold", AND(COUNTIF(H64:K64, G64)+1>=3, O64<70, P64<75), "Lean", AND(R64<>G64, ((H64=R64)+(J64=R64)+(K64=R64))>=2, O64<60, P64<70), "Opposition Lean", TRUE, "Battleground" ) -> Battleground | G64: AAP | H64: EMERGING | I64: AAP | J64: EMERGING | K64: BJP | M64: BJP | N64: 24.92 | O64: {=_xlfn.XLOOKUP(B64, 'Assembly Competitiveness'!$B$4:$B$120,'Assembly Competitiveness'!$O$4:$O$120, "-")} -> 12.304 | P64: {=_xlfn.XLOOKUP(B64,'Assembly Volatality'!$B$4:$B$120,'Assembly Volatality'!$L$4:$L$120, "-")} -> 54 | Q64: =ROUND(0.45*O64+0.4*P64+0.15*IF(H64<>K64,100,0),1) -> 42.1 | R64: BJP | S64: YES | T64: =IFS( AND(G64="AAP", OR(F64="Stronghold", F64="Lean")), "Defend", OR( AND(G64="AAP", OR(F64="Battleground", F64="Highly Volatile", F64="Opposition Lean")), AND(R64="AAP", OR(F64="Battleground", F64="Highly Volatile", F64="Opposition Lean")) ), "Battleground", OR(K64="AAP", M64="AAP", R64="AAP"), "Expand", TRUE, "Long Shot" ) -> Battleground | U64: =IFS( AND(G64="INC", OR(F64="Stronghold", F64="Lean")), "Defend", OR( AND(G64="INC", OR(F64="Battleground", F64="Highly Volatile", F64="Opposition Lean")), AND(R64="INC", OR(F64="Battleground", F64="Highly Volatile", F64="Opposition Lean")) ), "Battleground", OR(K64="INC", M64="INC", R64="INC"), "Expand", TRUE, "Long Shot" ) -> Long Shot | V64: =IFS( AND(G64="SAD", OR(F64="Stronghold", F64="Lean")), "Defend", OR( AND(G64="SAD", OR(F64="Battleground", F64="Highly Volatile", F64="Opposition Lean")), AND(R64="SAD", OR(F64="Battleground", F64="Highly Volatile", F64="Opposition Lean")) ), "Battleground", OR(K64="SAD", M64="SAD", R64="SAD"), "Expand", TRUE, "Long Shot" ) -> Long Shot | W64: =IFS( AND(G64="BJP", OR(F64="Stronghold", F64="Lean")), "Defend", OR( AND(G64="BJP", OR(F64="Battleground", F64="Highly Volatile", F64="Opposition Lean")), AND(R64="BJP", OR(F64="Battleground", F64="Highly Volatile", F64="Opposition Lean")) ), "Battleground", OR(K64="BJP", M64="BJP", R64="BJP"), "Expand", TRUE, "Long Shot" ) -> Battleground | X64: =IFS(K64="EMERGING", "YES", COUNTIFS(T64:W64, "<>Long Shot", T64:W64, "<>") >= 3, "YES", TRUE, "")
A65: 62 | B65: Atam Nagar | C65: Ludhiana | D65: Malwa | E65: Kulwant Singh Sidhu | F65: =IFS( OR(P65>=75, ((H65<>J65)+(J65<>I65)+(I65<>K65))>=3), "Highly Volatile", AND(COUNTIF(H65:K65, G65)+1>=4, O65<55, P65<65), "Stronghold", AND(COUNTIF(H65:K65, G65)+1>=3, O65<70, P65<75), "Lean", AND(R65<>G65, ((H65=R65)+(J65=R65)+(K65=R65))>=2, O65<60, P65<70), "Opposition Lean", TRUE, "Battleground" ) -> Battleground | G65: AAP | H65: EMERGING | I65: AAP | J65: EMERGING | K65: INC | M65: INC | N65: 15.68 | O65: {=_xlfn.XLOOKUP(B65, 'Assembly Competitiveness'!$B$4:$B$120,'Assembly Competitiveness'!$O$4:$O$120, "-")} -> 23.89 | P65: {=_xlfn.XLOOKUP(B65,'Assembly Volatality'!$B$4:$B$120,'Assembly Volatality'!$L$4:$L$120, "-")} -> 46.06 | Q65: =ROUND(0.45*O65+0.4*P65+0.15*IF(H65<>K65,100,0),1) -> 44.2 | R65: INC | S65: YES | T65: =IFS( AND(G65="AAP", OR(F65="Stronghold", F65="Lean")), "Defend", OR( AND(G65="AAP", OR(F65="Battleground", F65="Highly Volatile", F65="Opposition Lean")), AND(R65="AAP", OR(F65="Battleground", F65="Highly Volatile", F65="Opposition Lean")) ), "Battleground", OR(K65="AAP", M65="AAP", R65="AAP"), "Expand", TRUE, "Long Shot" ) -> Battleground | U65: =IFS( AND(G65="INC", OR(F65="Stronghold", F65="Lean")), "Defend", OR( AND(G65="INC", OR(F65="Battleground", F65="Highly Volatile", F65="Opposition Lean")), AND(R65="INC", OR(F65="Battleground", F65="Highly Volatile", F65="Opposition Lean")) ), "Battleground", OR(K65="INC", M65="INC", R65="INC"), "Expand", TRUE, "Long Shot" ) -> Battleground | V65: =IFS( AND(G65="SAD", OR(F65="Stronghold", F65="Lean")), "Defend", OR( AND(G65="SAD", OR(F65="Battleground", F65="Highly Volatile", F65="Opposition Lean")), AND(R65="SAD", OR(F65="Battleground", F65="Highly Volatile", F65="Opposition Lean")) ), "Battleground", OR(K65="SAD", M65="SAD", R65="SAD"), "Expand", TRUE, "Long Shot" ) -> Long Shot | W65: =IFS( AND(G65="BJP", OR(F65="Stronghold", F65="Lean")), "Defend", OR( AND(G65="BJP", OR(F65="Battleground", F65="Highly Volatile", F65="Opposition Lean")), AND(R65="BJP", OR(F65="Battleground", F65="Highly Volatile", F65="Opposition Lean")) ), "Battleground", OR(K65="BJP", M65="BJP", R65="BJP"), "Expand", TRUE, "Long Shot" ) -> Long Shot | X65: =IFS(K65="EMERGING", "YES", COUNTIFS(T65:W65, "<>Long Shot", T65:W65, "<>") >= 3, "YES", TRUE, "")
A66: 63 | B66: Ludhiana Central | C66: Ludhiana | D66: Malwa | E66: Ashok Parashar (Pappi) | F66: =IFS( OR(P66>=75, ((H66<>J66)+(J66<>I66)+(I66<>K66))>=3), "Highly Volatile", AND(COUNTIF(H66:K66, G66)+1>=4, O66<55, P66<65), "Stronghold", AND(COUNTIF(H66:K66, G66)+1>=3, O66<70, P66<75), "Lean", AND(R66<>G66, ((H66=R66)+(J66=R66)+(K66=R66))>=2, O66<60, P66<70), "Opposition Lean", TRUE, "Battleground" ) -> Battleground | G66: AAP | H66: INC | I66: AAP | J66: INC | K66: BJP | M66: BJP | N66: 4.92 | O66: {=_xlfn.XLOOKUP(B66, 'Assembly Competitiveness'!$B$4:$B$120,'Assembly Competitiveness'!$O$4:$O$120, "-")} -> 49.998 | P66: {=_xlfn.XLOOKUP(B66,'Assembly Volatality'!$B$4:$B$120,'Assembly Volatality'!$L$4:$L$120, "-")} -> 62.3 | Q66: =ROUND(0.45*O66+0.4*P66+0.15*IF(H66<>K66,100,0),1) -> 62.4 | R66: BJP | S66: YES | T66: =IFS( AND(G66="AAP", OR(F66="Stronghold", F66="Lean")), "Defend", OR( AND(G66="AAP", OR(F66="Battleground", F66="Highly Volatile", F66="Opposition Lean")), AND(R66="AAP", OR(F66="Battleground", F66="Highly Volatile", F66="Opposition Lean")) ), "Battleground", OR(K66="AAP", M66="AAP", R66="AAP"), "Expand", TRUE, "Long Shot" ) -> Battleground | U66: =IFS( AND(G66="INC", OR(F66="Stronghold", F66="Lean")), "Defend", OR( AND(G66="INC", OR(F66="Battleground", F66="Highly Volatile", F66="Opposition Lean")), AND(R66="INC", OR(F66="Battleground", F66="Highly Volatile", F66="Opposition Lean")) ), "Battleground", OR(K66="INC", M66="INC", R66="INC"), "Expand", TRUE, "Long Shot" ) -> Long Shot | V66: =IFS( AND(G66="SAD", OR(F66="Stronghold", F66="Lean")), "Defend", OR( AND(G66="SAD", OR(F66="Battleground", F66="Highly Volatile", F66="Opposition Lean")), AND(R66="SAD", OR(F66="Battleground", F66="Highly Volatile", F66="Opposition Lean")) ), "Battleground", OR(K66="SAD", M66="SAD", R66="SAD"), "Expand", TRUE, "Long Shot" ) -> Long Shot | W66: =IFS( AND(G66="BJP", OR(F66="Stronghold", F66="Lean")), "Defend", OR( AND(G66="BJP", OR(F66="Battleground", F66="Highly Volatile", F66="Opposition Lean")), AND(R66="BJP", OR(F66="Battleground", F66="Highly Volatile", F66="Opposition Lean")) ), "Battleground", OR(K66="BJP", M66="BJP", R66="BJP"), "Expand", TRUE, "Long Shot" ) -> Battleground | X66: =IFS(K66="EMERGING", "YES", COUNTIFS(T66:W66, "<>Long Shot", T66:W66, "<>") >= 3, "YES", TRUE, "")
A67: 64 | B67: Ludhiana West | C67: Ludhiana | D67: Malwa | E67: Sanjeev Arora | F67: =IFS( OR(P67>=75, ((H67<>J67)+(J67<>I67)+(I67<>K67))>=3), "Highly Volatile", AND(COUNTIF(H67:K67, G67)+1>=4, O67<55, P67<65), "Stronghold", AND(COUNTIF(H67:K67, G67)+1>=3, O67<70, P67<75), "Lean", AND(R67<>G67, ((H67=R67)+(J67=R67)+(K67=R67))>=2, O67<60, P67<70), "Opposition Lean", TRUE, "Battleground" ) -> Highly Volatile | G67: AAP | H67: INC | I67: AAP | J67: INC | K67: BJP | L67: 2025 bypoll - AAP retained | M67: INC | N67: 6.47 | O67: {=_xlfn.XLOOKUP(B67, 'Assembly Competitiveness'!$B$4:$B$120,'Assembly Competitiveness'!$O$4:$O$120, "-")} -> 54.3825 | P67: {=_xlfn.XLOOKUP(B67,'Assembly Volatality'!$B$4:$B$120,'Assembly Volatality'!$L$4:$L$120, "-")} -> 75.46 | Q67: =ROUND(0.45*O67+0.4*P67+0.15*IF(H67<>K67,100,0),1) -> 69.7 | R67: INC | S67: YES | T67: =IFS( AND(G67="AAP", OR(F67="Stronghold", F67="Lean")), "Defend", OR( AND(G67="AAP", OR(F67="Battleground", F67="Highly Volatile", F67="Opposition Lean")), AND(R67="AAP", OR(F67="Battleground", F67="Highly Volatile", F67="Opposition Lean")) ), "Battleground", OR(K67="AAP", M67="AAP", R67="AAP"), "Expand", TRUE, "Long Shot" ) -> Battleground | U67: =IFS( AND(G67="INC", OR(F67="Stronghold", F67="Lean")), "Defend", OR( AND(G67="INC", OR(F67="Battleground", F67="Highly Volatile", F67="Opposition Lean")), AND(R67="INC", OR(F67="Battleground", F67="Highly Volatile", F67="Opposition Lean")) ), "Battleground", OR(K67="INC", M67="INC", R67="INC"), "Expand", TRUE, "Long Shot" ) -> Battleground | V67: =IFS( AND(G67="SAD", OR(F67="Stronghold", F67="Lean")), "Defend", OR( AND(G67="SAD", OR(F67="Battleground", F67="Highly Volatile", F67="Opposition Lean")), AND(R67="SAD", OR(F67="Battleground", F67="Highly Volatile", F67="Opposition Lean")) ), "Battleground", OR(K67="SAD", M67="SAD", R67="SAD"), "Expand", TRUE, "Long Shot" ) -> Long Shot | W67: =IFS( AND(G67="BJP", OR(F67="Stronghold", F67="Lean")), "Defend", OR( AND(G67="BJP", OR(F67="Battleground", F67="Highly Volatile", F67="Opposition Lean")), AND(R67="BJP", OR(F67="Battleground", F67="Highly Volatile", F67="Opposition Lean")) ), "Battleground", OR(K67="BJP", M67="BJP", R67="BJP"), "Expand", TRUE, "Long Shot" ) -> Expand | X67: =IFS(K67="EMERGING", "YES", COUNTIFS(T67:W67, "<>Long Shot", T67:W67, "<>") >= 3, "YES", TRUE, "") -> YES
A68: 65 | B68: Ludhiana North | C68: Ludhiana | D68: Malwa | E68: Madan Lal Bagga | F68: =IFS( OR(P68>=75, ((H68<>J68)+(J68<>I68)+(I68<>K68))>=3), "Highly Volatile", AND(COUNTIF(H68:K68, G68)+1>=4, O68<55, P68<65), "Stronghold", AND(COUNTIF(H68:K68, G68)+1>=3, O68<70, P68<75), "Lean", AND(R68<>G68, ((H68=R68)+(J68=R68)+(K68=R68))>=2, O68<60, P68<70), "Opposition Lean", TRUE, "Battleground" ) -> Battleground | G68: AAP | H68: INC | I68: AAP | J68: INC | K68: BJP | M68: BJP | N68: 12.23 | O68: {=_xlfn.XLOOKUP(B68, 'Assembly Competitiveness'!$B$4:$B$120,'Assembly Competitiveness'!$O$4:$O$120, "-")} -> 46.5505 | P68: {=_xlfn.XLOOKUP(B68,'Assembly Volatality'!$B$4:$B$120,'Assembly Volatality'!$L$4:$L$120, "-")} -> 54.44 | Q68: =ROUND(0.45*O68+0.4*P68+0.15*IF(H68<>K68,100,0),1) -> 57.7 | R68: BJP | S68: YES | T68: =IFS( AND(G68="AAP", OR(F68="Stronghold", F68="Lean")), "Defend", OR( AND(G68="AAP", OR(F68="Battleground", F68="Highly Volatile", F68="Opposition Lean")), AND(R68="AAP", OR(F68="Battleground", F68="Highly Volatile", F68="Opposition Lean")) ), "Battleground", OR(K68="AAP", M68="AAP", R68="AAP"), "Expand", TRUE, "Long Shot" ) -> Battleground | U68: =IFS( AND(G68="INC", OR(F68="Stronghold", F68="Lean")), "Defend", OR( AND(G68="INC", OR(F68="Battleground", F68="Highly Volatile", F68="Opposition Lean")), AND(R68="INC", OR(F68="Battleground", F68="Highly Volatile", F68="Opposition Lean")) ), "Battleground", OR(K68="INC", M68="INC", R68="INC"), "Expand", TRUE, "Long Shot" ) -> Long Shot | V68: =IFS( AND(G68="SAD", OR(F68="Stronghold", F68="Lean")), "Defend", OR( AND(G68="SAD", OR(F68="Battleground", F68="Highly Volatile", F68="Opposition Lean")), AND(R68="SAD", OR(F68="Battleground", F68="Highly Volatile", F68="Opposition Lean")) ), "Battleground", OR(K68="SAD", M68="SAD", R68="SAD"), "Expand", TRUE, "Long Shot" ) -> Long Shot | W68: =IFS( AND(G68="BJP", OR(F68="Stronghold", F68="Lean")), "Defend", OR( AND(G68="BJP", OR(F68="Battleground", F68="Highly Volatile", F68="Opposition Lean")), AND(R68="BJP", OR(F68="Battleground", F68="Highly Volatile", F68="Opposition Lean")) ), "Battleground", OR(K68="BJP", M68="BJP", R68="BJP"), "Expand", TRUE, "Long Shot" ) -> Battleground | X68: =IFS(K68="EMERGING", "YES", COUNTIFS(T68:W68, "<>Long Shot", T68:W68, "<>") >= 3, "YES", TRUE, "")
A69: 66 | B69: Gill | C69: Ludhiana | D69: Malwa | E69: Jiwan Singh Sangowal | F69: =IFS( OR(P69>=75, ((H69<>J69)+(J69<>I69)+(I69<>K69))>=3), "Highly Volatile", AND(COUNTIF(H69:K69, G69)+1>=4, O69<55, P69<65), "Stronghold", AND(COUNTIF(H69:K69, G69)+1>=3, O69<70, P69<75), "Lean", AND(R69<>G69, ((H69=R69)+(J69=R69)+(K69=R69))>=2, O69<60, P69<70), "Opposition Lean", TRUE, "Battleground" ) -> Highly Volatile | G69: AAP | H69: INC | I69: AAP | J69: EMERGING | K69: INC | M69: SAD | N69: 31.59 | O69: {=_xlfn.XLOOKUP(B69, 'Assembly Competitiveness'!$B$4:$B$120,'Assembly Competitiveness'!$O$4:$O$120, "-")} -> 35.19 | P69: {=_xlfn.XLOOKUP(B69,'Assembly Volatality'!$B$4:$B$120,'Assembly Volatality'!$L$4:$L$120, "-")} -> 72.77 | Q69: =ROUND(0.45*O69+0.4*P69+0.15*IF(H69<>K69,100,0),1) -> 44.9 | R69: SAD | S69: YES | T69: =IFS( AND(G69="AAP", OR(F69="Stronghold", F69="Lean")), "Defend", OR( AND(G69="AAP", OR(F69="Battleground", F69="Highly Volatile", F69="Opposition Lean")), AND(R69="AAP", OR(F69="Battleground", F69="Highly Volatile", F69="Opposition Lean")) ), "Battleground", OR(K69="AAP", M69="AAP", R69="AAP"), "Expand", TRUE, "Long Shot" ) -> Battleground | U69: =IFS( AND(G69="INC", OR(F69="Stronghold", F69="Lean")), "Defend", OR( AND(G69="INC", OR(F69="Battleground", F69="Highly Volatile", F69="Opposition Lean")), AND(R69="INC", OR(F69="Battleground", F69="Highly Volatile", F69="Opposition Lean")) ), "Battleground", OR(K69="INC", M69="INC", R69="INC"), "Expand", TRUE, "Long Shot" ) -> Expand | V69: =IFS( AND(G69="SAD", OR(F69="Stronghold", F69="Lean")), "Defend", OR( AND(G69="SAD", OR(F69="Battleground", F69="Highly Volatile", F69="Opposition Lean")), AND(R69="SAD", OR(F69="Battleground", F69="Highly Volatile", F69="Opposition Lean")) ), "Battleground", OR(K69="SAD", M69="SAD", R69="SAD"), "Expand", TRUE, "Long Shot" ) -> Battleground | W69: =IFS( AND(G69="BJP", OR(F69="Stronghold", F69="Lean")), "Defend", OR( AND(G69="BJP", OR(F69="Battleground", F69="Highly Volatile", F69="Opposition Lean")), AND(R69="BJP", OR(F69="Battleground", F69="Highly Volatile", F69="Opposition Lean")) ), "Battleground", OR(K69="BJP", M69="BJP", R69="BJP"), "Expand", TRUE, "Long Shot" ) -> Long Shot | X69: =IFS(K69="EMERGING", "YES", COUNTIFS(T69:W69, "<>Long Shot", T69:W69, "<>") >= 3, "YES", TRUE, "") -> YES
A70: 67 | B70: Payal | C70: Ludhiana | D70: Malwa | E70: Manwinder Singh Giaspura | F70: =IFS( OR(P70>=75, ((H70<>J70)+(J70<>I70)+(I70<>K70))>=3), "Highly Volatile", AND(COUNTIF(H70:K70, G70)+1>=4, O70<55, P70<65), "Stronghold", AND(COUNTIF(H70:K70, G70)+1>=3, O70<70, P70<75), "Lean", AND(R70<>G70, ((H70=R70)+(J70=R70)+(K70=R70))>=2, O70<60, P70<70), "Opposition Lean", TRUE, "Battleground" ) -> Opposition Lean | G70: AAP | H70: INC | I70: AAP | J70: INC | K70: INC | M70: INC | N70: 26.14 | O70: {=_xlfn.XLOOKUP(B70, 'Assembly Competitiveness'!$B$4:$B$120,'Assembly Competitiveness'!$O$4:$O$120, "-")} -> 17.44 | P70: {=_xlfn.XLOOKUP(B70,'Assembly Volatality'!$B$4:$B$120,'Assembly Volatality'!$L$4:$L$120, "-")} -> 55.33 | Q70: =ROUND(0.45*O70+0.4*P70+0.15*IF(H70<>K70,100,0),1) -> 30 | R70: INC | S70: YES | T70: =IFS( AND(G70="AAP", OR(F70="Stronghold", F70="Lean")), "Defend", OR( AND(G70="AAP", OR(F70="Battleground", F70="Highly Volatile", F70="Opposition Lean")), AND(R70="AAP", OR(F70="Battleground", F70="Highly Volatile", F70="Opposition Lean")) ), "Battleground", OR(K70="AAP", M70="AAP", R70="AAP"), "Expand", TRUE, "Long Shot" ) -> Battleground | U70: =IFS( AND(G70="INC", OR(F70="Stronghold", F70="Lean")), "Defend", OR( AND(G70="INC", OR(F70="Battleground", F70="Highly Volatile", F70="Opposition Lean")), AND(R70="INC", OR(F70="Battleground", F70="Highly Volatile", F70="Opposition Lean")) ), "Battleground", OR(K70="INC", M70="INC", R70="INC"), "Expand", TRUE, "Long Shot" ) -> Battleground | V70: =IFS( AND(G70="SAD", OR(F70="Stronghold", F70="Lean")), "Defend", OR( AND(G70="SAD", OR(F70="Battleground", F70="Highly Volatile", F70="Opposition Lean")), AND(R70="SAD", OR(F70="Battleground", F70="Highly Volatile", F70="Opposition Lean")) ), "Battleground", OR(K70="SAD", M70="SAD", R70="SAD"), "Expand", TRUE, "Long Shot" ) -> Long Shot | W70: =IFS( AND(G70="BJP", OR(F70="Stronghold", F70="Lean")), "Defend", OR( AND(G70="BJP", OR(F70="Battleground", F70="Highly Volatile", F70="Opposition Lean")), AND(R70="BJP", OR(F70="Battleground", F70="Highly Volatile", F70="Opposition Lean")) ), "Battleground", OR(K70="BJP", M70="BJP", R70="BJP"), "Expand", TRUE, "Long Shot" ) -> Long Shot | X70: =IFS(K70="EMERGING", "YES", COUNTIFS(T70:W70, "<>Long Shot", T70:W70, "<>") >= 3, "YES", TRUE, "")
A71: 68 | B71: Dakha | C71: Ludhiana | D71: Malwa | E71: Manpreet Singh Ayali (elected SAD; joined WPD) | F71: =IFS( OR(P71>=75, ((H71<>J71)+(J71<>I71)+(I71<>K71))>=3), "Highly Volatile", AND(COUNTIF(H71:K71, G71)+1>=4, O71<55, P71<65), "Stronghold", AND(COUNTIF(H71:K71, G71)+1>=3, O71<70, P71<75), "Lean", AND(R71<>G71, ((H71=R71)+(J71=R71)+(K71=R71))>=2, O71<60, P71<70), "Opposition Lean", TRUE, "Battleground" ) -> Highly Volatile | G71: EMERGING | H71: AAP | I71: SAD | J71: EMERGING | K71: INC | L71: MLA elected SAD joined WPD; formal/legal membership differs | M71: INC | N71: 4.1 | O71: {=_xlfn.XLOOKUP(B71, 'Assembly Competitiveness'!$B$4:$B$120,'Assembly Competitiveness'!$O$4:$O$120, "-")} -> 78.397 | P71: {=_xlfn.XLOOKUP(B71,'Assembly Volatality'!$B$4:$B$120,'Assembly Volatality'!$L$4:$L$120, "-")} -> 71.43 | Q71: =ROUND(0.45*O71+0.4*P71+0.15*IF(H71<>K71,100,0),1) -> 78.9 | R71: INC | S71: YES | T71: =IFS( AND(G71="AAP", OR(F71="Stronghold", F71="Lean")), "Defend", OR( AND(G71="AAP", OR(F71="Battleground", F71="Highly Volatile", F71="Opposition Lean")), AND(R71="AAP", OR(F71="Battleground", F71="Highly Volatile", F71="Opposition Lean")) ), "Battleground", OR(K71="AAP", M71="AAP", R71="AAP"), "Expand", TRUE, "Long Shot" ) -> Long Shot | U71: =IFS( AND(G71="INC", OR(F71="Stronghold", F71="Lean")), "Defend", OR( AND(G71="INC", OR(F71="Battleground", F71="Highly Volatile", F71="Opposition Lean")), AND(R71="INC", OR(F71="Battleground", F71="Highly Volatile", F71="Opposition Lean")) ), "Battleground", OR(K71="INC", M71="INC", R71="INC"), "Expand", TRUE, "Long Shot" ) -> Battleground | V71: =IFS( AND(G71="SAD", OR(F71="Stronghold", F71="Lean")), "Defend", OR( AND(G71="SAD", OR(F71="Battleground", F71="Highly Volatile", F71="Opposition Lean")), AND(R71="SAD", OR(F71="Battleground", F71="Highly Volatile", F71="Opposition Lean")) ), "Battleground", OR(K71="SAD", M71="SAD", R71="SAD"), "Expand", TRUE, "Long Shot" ) -> Long Shot | W71: =IFS( AND(G71="BJP", OR(F71="Stronghold", F71="Lean")), "Defend", OR( AND(G71="BJP", OR(F71="Battleground", F71="Highly Volatile", F71="Opposition Lean")), AND(R71="BJP", OR(F71="Battleground", F71="Highly Volatile", F71="Opposition Lean")) ), "Battleground", OR(K71="BJP", M71="BJP", R71="BJP"), "Expand", TRUE, "Long Shot" ) -> Long Shot | X71: =IFS(K71="EMERGING", "YES", COUNTIFS(T71:W71, "<>Long Shot", T71:W71, "<>") >= 3, "YES", TRUE, "")
A72: 69 | B72: Raikot | C72: Ludhiana | D72: Malwa | E72: Hakam Singh Thekedar | F72: =IFS( OR(P72>=75, ((H72<>J72)+(J72<>I72)+(I72<>K72))>=3), "Highly Volatile", AND(COUNTIF(H72:K72, G72)+1>=4, O72<55, P72<65), "Stronghold", AND(COUNTIF(H72:K72, G72)+1>=3, O72<70, P72<75), "Lean", AND(R72<>G72, ((H72=R72)+(J72=R72)+(K72=R72))>=2, O72<60, P72<70), "Opposition Lean", TRUE, "Battleground" ) -> Highly Volatile | G72: AAP | H72: AAP | I72: AAP | J72: INC | K72: INC | M72: INC | N72: 24.6 | O72: {=_xlfn.XLOOKUP(B72, 'Assembly Competitiveness'!$B$4:$B$120,'Assembly Competitiveness'!$O$4:$O$120, "-")} -> 27.142 | P72: {=_xlfn.XLOOKUP(B72,'Assembly Volatality'!$B$4:$B$120,'Assembly Volatality'!$L$4:$L$120, "-")} -> 31.07 | Q72: =ROUND(0.45*O72+0.4*P72+0.15*IF(H72<>K72,100,0),1) -> 39.6 | R72: INC | S72: YES | T72: =IFS( AND(G72="AAP", OR(F72="Stronghold", F72="Lean")), "Defend", OR( AND(G72="AAP", OR(F72="Battleground", F72="Highly Volatile", F72="Opposition Lean")), AND(R72="AAP", OR(F72="Battleground", F72="Highly Volatile", F72="Opposition Lean")) ), "Battleground", OR(K72="AAP", M72="AAP", R72="AAP"), "Expand", TRUE, "Long Shot" ) -> Battleground | U72: =IFS( AND(G72="INC", OR(F72="Stronghold", F72="Lean")), "Defend", OR( AND(G72="INC", OR(F72="Battleground", F72="Highly Volatile", F72="Opposition Lean")), AND(R72="INC", OR(F72="Battleground", F72="Highly Volatile", F72="Opposition Lean")) ), "Battleground", OR(K72="INC", M72="INC", R72="INC"), "Expand", TRUE, "Long Shot" ) -> Battleground | V72: =IFS( AND(G72="SAD", OR(F72="Stronghold", F72="Lean")), "Defend", OR( AND(G72="SAD", OR(F72="Battleground", F72="Highly Volatile", F72="Opposition Lean")), AND(R72="SAD", OR(F72="Battleground", F72="Highly Volatile", F72="Opposition Lean")) ), "Battleground", OR(K72="SAD", M72="SAD", R72="SAD"), "Expand", TRUE, "Long Shot" ) -> Long Shot | W72: =IFS( AND(G72="BJP", OR(F72="Stronghold", F72="Lean")), "Defend", OR( AND(G72="BJP", OR(F72="Battleground", F72="Highly Volatile", F72="Opposition Lean")), AND(R72="BJP", OR(F72="Battleground", F72="Highly Volatile", F72="Opposition Lean")) ), "Battleground", OR(K72="BJP", M72="BJP", R72="BJP"), "Expand", TRUE, "Long Shot" ) -> Long Shot | X72: =IFS(K72="EMERGING", "YES", COUNTIFS(T72:W72, "<>Long Shot", T72:W72, "<>") >= 3, "YES", TRUE, "")
A73: 70 | B73: Jagraon | C73: Ludhiana | D73: Malwa | E73: Sarvjit Kaur Manuke | F73: =IFS( OR(P73>=75, ((H73<>J73)+(J73<>I73)+(I73<>K73))>=3), "Highly Volatile", AND(COUNTIF(H73:K73, G73)+1>=4, O73<55, P73<65), "Stronghold", AND(COUNTIF(H73:K73, G73)+1>=3, O73<70, P73<75), "Lean", AND(R73<>G73, ((H73=R73)+(J73=R73)+(K73=R73))>=2, O73<60, P73<70), "Opposition Lean", TRUE, "Battleground" ) -> Highly Volatile | G73: AAP | H73: AAP | I73: AAP | J73: INC | K73: INC | M73: SAD | N73: 31.87 | O73: {=_xlfn.XLOOKUP(B73, 'Assembly Competitiveness'!$B$4:$B$120,'Assembly Competitiveness'!$O$4:$O$120, "-")} -> 16.162 | P73: {=_xlfn.XLOOKUP(B73,'Assembly Volatality'!$B$4:$B$120,'Assembly Volatality'!$L$4:$L$120, "-")} -> 31.8 | Q73: =ROUND(0.45*O73+0.4*P73+0.15*IF(H73<>K73,100,0),1) -> 35 | R73: SAD | S73: YES | T73: =IFS( AND(G73="AAP", OR(F73="Stronghold", F73="Lean")), "Defend", OR( AND(G73="AAP", OR(F73="Battleground", F73="Highly Volatile", F73="Opposition Lean")), AND(R73="AAP", OR(F73="Battleground", F73="Highly Volatile", F73="Opposition Lean")) ), "Battleground", OR(K73="AAP", M73="AAP", R73="AAP"), "Expand", TRUE, "Long Shot" ) -> Battleground | U73: =IFS( AND(G73="INC", OR(F73="Stronghold", F73="Lean")), "Defend", OR( AND(G73="INC", OR(F73="Battleground", F73="Highly Volatile", F73="Opposition Lean")), AND(R73="INC", OR(F73="Battleground", F73="Highly Volatile", F73="Opposition Lean")) ), "Battleground", OR(K73="INC", M73="INC", R73="INC"), "Expand", TRUE, "Long Shot" ) -> Expand | V73: =IFS( AND(G73="SAD", OR(F73="Stronghold", F73="Lean")), "Defend", OR( AND(G73="SAD", OR(F73="Battleground", F73="Highly Volatile", F73="Opposition Lean")), AND(R73="SAD", OR(F73="Battleground", F73="Highly Volatile", F73="Opposition Lean")) ), "Battleground", OR(K73="SAD", M73="SAD", R73="SAD"), "Expand", TRUE, "Long Shot" ) -> Battleground | W73: =IFS( AND(G73="BJP", OR(F73="Stronghold", F73="Lean")), "Defend", OR( AND(G73="BJP", OR(F73="Battleground", F73="Highly Volatile", F73="Opposition Lean")), AND(R73="BJP", OR(F73="Battleground", F73="Highly Volatile", F73="Opposition Lean")) ), "Battleground", OR(K73="BJP", M73="BJP", R73="BJP"), "Expand", TRUE, "Long Shot" ) -> Long Shot | X73: =IFS(K73="EMERGING", "YES", COUNTIFS(T73:W73, "<>Long Shot", T73:W73, "<>") >= 3, "YES", TRUE, "") -> YES
A74: 71 | B74: Nihal Singh Wala | C74: Moga | D74: Malwa | E74: Manjit Singh Bilaspur | F74: =IFS( OR(P74>=75, ((H74<>J74)+(J74<>I74)+(I74<>K74))>=3), "Highly Volatile", AND(COUNTIF(H74:K74, G74)+1>=4, O74<55, P74<65), "Stronghold", AND(COUNTIF(H74:K74, G74)+1>=3, O74<70, P74<75), "Lean", AND(R74<>G74, ((H74=R74)+(J74=R74)+(K74=R74))>=2, O74<60, P74<70), "Opposition Lean", TRUE, "Battleground" ) -> Highly Volatile | G74: AAP | H74: AAP | I74: AAP | J74: INC | K74: EMERGING | M74: INC | N74: 27.07 | O74: {=_xlfn.XLOOKUP(B74, 'Assembly Competitiveness'!$B$4:$B$120,'Assembly Competitiveness'!$O$4:$O$120, "-")} -> 15.152 | P74: {=_xlfn.XLOOKUP(B74,'Assembly Volatality'!$B$4:$B$120,'Assembly Volatality'!$L$4:$L$120, "-")} -> 25.81 | Q74: =ROUND(0.45*O74+0.4*P74+0.15*IF(H74<>K74,100,0),1) -> 32.1 | R74: INC | S74: YES | T74: =IFS( AND(G74="AAP", OR(F74="Stronghold", F74="Lean")), "Defend", OR( AND(G74="AAP", OR(F74="Battleground", F74="Highly Volatile", F74="Opposition Lean")), AND(R74="AAP", OR(F74="Battleground", F74="Highly Volatile", F74="Opposition Lean")) ), "Battleground", OR(K74="AAP", M74="AAP", R74="AAP"), "Expand", TRUE, "Long Shot" ) -> Battleground | U74: =IFS( AND(G74="INC", OR(F74="Stronghold", F74="Lean")), "Defend", OR( AND(G74="INC", OR(F74="Battleground", F74="Highly Volatile", F74="Opposition Lean")), AND(R74="INC", OR(F74="Battleground", F74="Highly Volatile", F74="Opposition Lean")) ), "Battleground", OR(K74="INC", M74="INC", R74="INC"), "Expand", TRUE, "Long Shot" ) -> Battleground | V74: =IFS( AND(G74="SAD", OR(F74="Stronghold", F74="Lean")), "Defend", OR( AND(G74="SAD", OR(F74="Battleground", F74="Highly Volatile", F74="Opposition Lean")), AND(R74="SAD", OR(F74="Battleground", F74="Highly Volatile", F74="Opposition Lean")) ), "Battleground", OR(K74="SAD", M74="SAD", R74="SAD"), "Expand", TRUE, "Long Shot" ) -> Long Shot | W74: =IFS( AND(G74="BJP", OR(F74="Stronghold", F74="Lean")), "Defend", OR( AND(G74="BJP", OR(F74="Battleground", F74="Highly Volatile", F74="Opposition Lean")), AND(R74="BJP", OR(F74="Battleground", F74="Highly Volatile", F74="Opposition Lean")) ), "Battleground", OR(K74="BJP", M74="BJP", R74="BJP"), "Expand", TRUE, "Long Shot" ) -> Long Shot | X74: =IFS(K74="EMERGING", "YES", COUNTIFS(T74:W74, "<>Long Shot", T74:W74, "<>") >= 3, "YES", TRUE, "") -> YES
A75: 72 | B75: Bagha Purana | C75: Moga | D75: Malwa | E75: Amritpal Singh Sukhanand | F75: =IFS( OR(P75>=75, ((H75<>J75)+(J75<>I75)+(I75<>K75))>=3), "Highly Volatile", AND(COUNTIF(H75:K75, G75)+1>=4, O75<55, P75<65), "Stronghold", AND(COUNTIF(H75:K75, G75)+1>=3, O75<70, P75<75), "Lean", AND(R75<>G75, ((H75=R75)+(J75=R75)+(K75=R75))>=2, O75<60, P75<70), "Opposition Lean", TRUE, "Battleground" ) -> Battleground | G75: AAP | H75: INC | I75: AAP | J75: INC | K75: EMERGING | M75: SAD | N75: 25.56 | O75: {=_xlfn.XLOOKUP(B75, 'Assembly Competitiveness'!$B$4:$B$120,'Assembly Competitiveness'!$O$4:$O$120, "-")} -> 32.818 | P75: {=_xlfn.XLOOKUP(B75,'Assembly Volatality'!$B$4:$B$120,'Assembly Volatality'!$L$4:$L$120, "-")} -> 64.64 | Q75: =ROUND(0.45*O75+0.4*P75+0.15*IF(H75<>K75,100,0),1) -> 55.6 | R75: SAD | S75: YES | T75: =IFS( AND(G75="AAP", OR(F75="Stronghold", F75="Lean")), "Defend", OR( AND(G75="AAP", OR(F75="Battleground", F75="Highly Volatile", F75="Opposition Lean")), AND(R75="AAP", OR(F75="Battleground", F75="Highly Volatile", F75="Opposition Lean")) ), "Battleground", OR(K75="AAP", M75="AAP", R75="AAP"), "Expand", TRUE, "Long Shot" ) -> Battleground | U75: =IFS( AND(G75="INC", OR(F75="Stronghold", F75="Lean")), "Defend", OR( AND(G75="INC", OR(F75="Battleground", F75="Highly Volatile", F75="Opposition Lean")), AND(R75="INC", OR(F75="Battleground", F75="Highly Volatile", F75="Opposition Lean")) ), "Battleground", OR(K75="INC", M75="INC", R75="INC"), "Expand", TRUE, "Long Shot" ) -> Long Shot | V75: =IFS( AND(G75="SAD", OR(F75="Stronghold", F75="Lean")), "Defend", OR( AND(G75="SAD", OR(F75="Battleground", F75="Highly Volatile", F75="Opposition Lean")), AND(R75="SAD", OR(F75="Battleground", F75="Highly Volatile", F75="Opposition Lean")) ), "Battleground", OR(K75="SAD", M75="SAD", R75="SAD"), "Expand", TRUE, "Long Shot" ) -> Battleground | W75: =IFS( AND(G75="BJP", OR(F75="Stronghold", F75="Lean")), "Defend", OR( AND(G75="BJP", OR(F75="Battleground", F75="Highly Volatile", F75="Opposition Lean")), AND(R75="BJP", OR(F75="Battleground", F75="Highly Volatile", F75="Opposition Lean")) ), "Battleground", OR(K75="BJP", M75="BJP", R75="BJP"), "Expand", TRUE, "Long Shot" ) -> Long Shot | X75: =IFS(K75="EMERGING", "YES", COUNTIFS(T75:W75, "<>Long Shot", T75:W75, "<>") >= 3, "YES", TRUE, "") -> YES
A76: 73 | B76: Moga | C76: Moga | D76: Malwa | E76: Dr. Amandeep Kaur Arora | F76: =IFS( OR(P76>=75, ((H76<>J76)+(J76<>I76)+(I76<>K76))>=3), "Highly Volatile", AND(COUNTIF(H76:K76, G76)+1>=4, O76<55, P76<65), "Stronghold", AND(COUNTIF(H76:K76, G76)+1>=3, O76<70, P76<75), "Lean", AND(R76<>G76, ((H76=R76)+(J76=R76)+(K76=R76))>=2, O76<60, P76<70), "Opposition Lean", TRUE, "Battleground" ) -> Opposition Lean | G76: AAP | H76: INC | I76: AAP | J76: INC | K76: EMERGING | M76: INC | N76: 14.59 | O76: {=_xlfn.XLOOKUP(B76, 'Assembly Competitiveness'!$B$4:$B$120,'Assembly Competitiveness'!$O$4:$O$120, "-")} -> 46.3005 | P76: {=_xlfn.XLOOKUP(B76,'Assembly Volatality'!$B$4:$B$120,'Assembly Volatality'!$L$4:$L$120, "-")} -> 57.41 | Q76: =ROUND(0.45*O76+0.4*P76+0.15*IF(H76<>K76,100,0),1) -> 58.8 | R76: INC | S76: YES | T76: =IFS( AND(G76="AAP", OR(F76="Stronghold", F76="Lean")), "Defend", OR( AND(G76="AAP", OR(F76="Battleground", F76="Highly Volatile", F76="Opposition Lean")), AND(R76="AAP", OR(F76="Battleground", F76="Highly Volatile", F76="Opposition Lean")) ), "Battleground", OR(K76="AAP", M76="AAP", R76="AAP"), "Expand", TRUE, "Long Shot" ) -> Battleground | U76: =IFS( AND(G76="INC", OR(F76="Stronghold", F76="Lean")), "Defend", OR( AND(G76="INC", OR(F76="Battleground", F76="Highly Volatile", F76="Opposition Lean")), AND(R76="INC", OR(F76="Battleground", F76="Highly Volatile", F76="Opposition Lean")) ), "Battleground", OR(K76="INC", M76="INC", R76="INC"), "Expand", TRUE, "Long Shot" ) -> Battleground | V76: =IFS( AND(G76="SAD", OR(F76="Stronghold", F76="Lean")), "Defend", OR( AND(G76="SAD", OR(F76="Battleground", F76="Highly Volatile", F76="Opposition Lean")), AND(R76="SAD", OR(F76="Battleground", F76="Highly Volatile", F76="Opposition Lean")) ), "Battleground", OR(K76="SAD", M76="SAD", R76="SAD"), "Expand", TRUE, "Long Shot" ) -> Long Shot | W76: =IFS( AND(G76="BJP", OR(F76="Stronghold", F76="Lean")), "Defend", OR( AND(G76="BJP", OR(F76="Battleground", F76="Highly Volatile", F76="Opposition Lean")), AND(R76="BJP", OR(F76="Battleground", F76="Highly Volatile", F76="Opposition Lean")) ), "Battleground", OR(K76="BJP", M76="BJP", R76="BJP"), "Expand", TRUE, "Long Shot" ) -> Long Shot | X76: =IFS(K76="EMERGING", "YES", COUNTIFS(T76:W76, "<>Long Shot", T76:W76, "<>") >= 3, "YES", TRUE, "") -> YES
A77: 74 | B77: Dharamkot | C77: Moga | D77: Malwa | E77: Devinderjeet Singh Laddi Dhose | F77: =IFS( OR(P77>=75, ((H77<>J77)+(J77<>I77)+(I77<>K77))>=3), "Highly Volatile", AND(COUNTIF(H77:K77, G77)+1>=4, O77<55, P77<65), "Stronghold", AND(COUNTIF(H77:K77, G77)+1>=3, O77<70, P77<75), "Lean", AND(R77<>G77, ((H77=R77)+(J77=R77)+(K77=R77))>=2, O77<60, P77<70), "Opposition Lean", TRUE, "Battleground" ) -> Opposition Lean | G77: AAP | H77: INC | I77: AAP | J77: INC | K77: EMERGING | M77: INC | N77: 21.19 | O77: {=_xlfn.XLOOKUP(B77, 'Assembly Competitiveness'!$B$4:$B$120,'Assembly Competitiveness'!$O$4:$O$120, "-")} -> 16.72 | P77: {=_xlfn.XLOOKUP(B77,'Assembly Volatality'!$B$4:$B$120,'Assembly Volatality'!$L$4:$L$120, "-")} -> 49.75 | Q77: =ROUND(0.45*O77+0.4*P77+0.15*IF(H77<>K77,100,0),1) -> 42.4 | R77: INC | S77: YES | T77: =IFS( AND(G77="AAP", OR(F77="Stronghold", F77="Lean")), "Defend", OR( AND(G77="AAP", OR(F77="Battleground", F77="Highly Volatile", F77="Opposition Lean")), AND(R77="AAP", OR(F77="Battleground", F77="Highly Volatile", F77="Opposition Lean")) ), "Battleground", OR(K77="AAP", M77="AAP", R77="AAP"), "Expand", TRUE, "Long Shot" ) -> Battleground | U77: =IFS( AND(G77="INC", OR(F77="Stronghold", F77="Lean")), "Defend", OR( AND(G77="INC", OR(F77="Battleground", F77="Highly Volatile", F77="Opposition Lean")), AND(R77="INC", OR(F77="Battleground", F77="Highly Volatile", F77="Opposition Lean")) ), "Battleground", OR(K77="INC", M77="INC", R77="INC"), "Expand", TRUE, "Long Shot" ) -> Battleground | V77: =IFS( AND(G77="SAD", OR(F77="Stronghold", F77="Lean")), "Defend", OR( AND(G77="SAD", OR(F77="Battleground", F77="Highly Volatile", F77="Opposition Lean")), AND(R77="SAD", OR(F77="Battleground", F77="Highly Volatile", F77="Opposition Lean")) ), "Battleground", OR(K77="SAD", M77="SAD", R77="SAD"), "Expand", TRUE, "Long Shot" ) -> Long Shot | W77: =IFS( AND(G77="BJP", OR(F77="Stronghold", F77="Lean")), "Defend", OR( AND(G77="BJP", OR(F77="Battleground", F77="Highly Volatile", F77="Opposition Lean")), AND(R77="BJP", OR(F77="Battleground", F77="Highly Volatile", F77="Opposition Lean")) ), "Battleground", OR(K77="BJP", M77="BJP", R77="BJP"), "Expand", TRUE, "Long Shot" ) -> Long Shot | X77: =IFS(K77="EMERGING", "YES", COUNTIFS(T77:W77, "<>Long Shot", T77:W77, "<>") >= 3, "YES", TRUE, "") -> YES
A78: 75 | B78: Zira | C78: Ferozepur | D78: Malwa | E78: Naresh Kataria | F78: =IFS( OR(P78>=75, ((H78<>J78)+(J78<>I78)+(I78<>K78))>=3), "Highly Volatile", AND(COUNTIF(H78:K78, G78)+1>=4, O78<55, P78<65), "Stronghold", AND(COUNTIF(H78:K78, G78)+1>=3, O78<70, P78<75), "Lean", AND(R78<>G78, ((H78=R78)+(J78=R78)+(K78=R78))>=2, O78<60, P78<70), "Opposition Lean", TRUE, "Battleground" ) -> Battleground | G78: AAP | H78: INC | I78: AAP | J78: INC | K78: EMERGING | M78: SAD | N78: 15.13 | O78: {=_xlfn.XLOOKUP(B78, 'Assembly Competitiveness'!$B$4:$B$120,'Assembly Competitiveness'!$O$4:$O$120, "-")} -> 25.7255 | P78: {=_xlfn.XLOOKUP(B78,'Assembly Volatality'!$B$4:$B$120,'Assembly Volatality'!$L$4:$L$120, "-")} -> 44.6 | Q78: =ROUND(0.45*O78+0.4*P78+0.15*IF(H78<>K78,100,0),1) -> 44.4 | R78: SAD | S78: YES | T78: =IFS( AND(G78="AAP", OR(F78="Stronghold", F78="Lean")), "Defend", OR( AND(G78="AAP", OR(F78="Battleground", F78="Highly Volatile", F78="Opposition Lean")), AND(R78="AAP", OR(F78="Battleground", F78="Highly Volatile", F78="Opposition Lean")) ), "Battleground", OR(K78="AAP", M78="AAP", R78="AAP"), "Expand", TRUE, "Long Shot" ) -> Battleground | U78: =IFS( AND(G78="INC", OR(F78="Stronghold", F78="Lean")), "Defend", OR( AND(G78="INC", OR(F78="Battleground", F78="Highly Volatile", F78="Opposition Lean")), AND(R78="INC", OR(F78="Battleground", F78="Highly Volatile", F78="Opposition Lean")) ), "Battleground", OR(K78="INC", M78="INC", R78="INC"), "Expand", TRUE, "Long Shot" ) -> Long Shot | V78: =IFS( AND(G78="SAD", OR(F78="Stronghold", F78="Lean")), "Defend", OR( AND(G78="SAD", OR(F78="Battleground", F78="Highly Volatile", F78="Opposition Lean")), AND(R78="SAD", OR(F78="Battleground", F78="Highly Volatile", F78="Opposition Lean")) ), "Battleground", OR(K78="SAD", M78="SAD", R78="SAD"), "Expand", TRUE, "Long Shot" ) -> Battleground | W78: =IFS( AND(G78="BJP", OR(F78="Stronghold", F78="Lean")), "Defend", OR( AND(G78="BJP", OR(F78="Battleground", F78="Highly Volatile", F78="Opposition Lean")), AND(R78="BJP", OR(F78="Battleground", F78="Highly Volatile", F78="Opposition Lean")) ), "Battleground", OR(K78="BJP", M78="BJP", R78="BJP"), "Expand", TRUE, "Long Shot" ) -> Long Shot | X78: =IFS(K78="EMERGING", "YES", COUNTIFS(T78:W78, "<>Long Shot", T78:W78, "<>") >= 3, "YES", TRUE, "") -> YES
A79: 76 | B79: Firozpur City | C79: Ferozepur | D79: Malwa | E79: Ranbir Singh | F79: =IFS( OR(P79>=75, ((H79<>J79)+(J79<>I79)+(I79<>K79))>=3), "Highly Volatile", AND(COUNTIF(H79:K79, G79)+1>=4, O79<55, P79<65), "Stronghold", AND(COUNTIF(H79:K79, G79)+1>=3, O79<70, P79<75), "Lean", AND(R79<>G79, ((H79=R79)+(J79=R79)+(K79=R79))>=2, O79<60, P79<70), "Opposition Lean", TRUE, "Battleground" ) -> Highly Volatile | G79: AAP | H79: INC | I79: AAP | J79: SAD | K79: BJP | M79: INC | N79: 15.78 | O79: {=_xlfn.XLOOKUP(B79, 'Assembly Competitiveness'!$B$4:$B$120,'Assembly Competitiveness'!$O$4:$O$120, "-")} -> 22.687 | P79: {=_xlfn.XLOOKUP(B79,'Assembly Volatality'!$B$4:$B$120,'Assembly Volatality'!$L$4:$L$120, "-")} -> 49.85 | Q79: =ROUND(0.45*O79+0.4*P79+0.15*IF(H79<>K79,100,0),1) -> 45.1 | R79: INC | S79: YES | T79: =IFS( AND(G79="AAP", OR(F79="Stronghold", F79="Lean")), "Defend", OR( AND(G79="AAP", OR(F79="Battleground", F79="Highly Volatile", F79="Opposition Lean")), AND(R79="AAP", OR(F79="Battleground", F79="Highly Volatile", F79="Opposition Lean")) ), "Battleground", OR(K79="AAP", M79="AAP", R79="AAP"), "Expand", TRUE, "Long Shot" ) -> Battleground | U79: =IFS( AND(G79="INC", OR(F79="Stronghold", F79="Lean")), "Defend", OR( AND(G79="INC", OR(F79="Battleground", F79="Highly Volatile", F79="Opposition Lean")), AND(R79="INC", OR(F79="Battleground", F79="Highly Volatile", F79="Opposition Lean")) ), "Battleground", OR(K79="INC", M79="INC", R79="INC"), "Expand", TRUE, "Long Shot" ) -> Battleground | V79: =IFS( AND(G79="SAD", OR(F79="Stronghold", F79="Lean")), "Defend", OR( AND(G79="SAD", OR(F79="Battleground", F79="Highly Volatile", F79="Opposition Lean")), AND(R79="SAD", OR(F79="Battleground", F79="Highly Volatile", F79="Opposition Lean")) ), "Battleground", OR(K79="SAD", M79="SAD", R79="SAD"), "Expand", TRUE, "Long Shot" ) -> Long Shot | W79: =IFS( AND(G79="BJP", OR(F79="Stronghold", F79="Lean")), "Defend", OR( AND(G79="BJP", OR(F79="Battleground", F79="Highly Volatile", F79="Opposition Lean")), AND(R79="BJP", OR(F79="Battleground", F79="Highly Volatile", F79="Opposition Lean")) ), "Battleground", OR(K79="BJP", M79="BJP", R79="BJP"), "Expand", TRUE, "Long Shot" ) -> Expand | X79: =IFS(K79="EMERGING", "YES", COUNTIFS(T79:W79, "<>Long Shot", T79:W79, "<>") >= 3, "YES", TRUE, "") -> YES
A80: 77 | B80: Firozpur Rural | C80: Ferozepur | D80: Malwa | E80: Rajneesh Kumar Dahiya | F80: =IFS( OR(P80>=75, ((H80<>J80)+(J80<>I80)+(I80<>K80))>=3), "Highly Volatile", AND(COUNTIF(H80:K80, G80)+1>=4, O80<55, P80<65), "Stronghold", AND(COUNTIF(H80:K80, G80)+1>=3, O80<70, P80<75), "Lean", AND(R80<>G80, ((H80=R80)+(J80=R80)+(K80=R80))>=2, O80<60, P80<70), "Opposition Lean", TRUE, "Battleground" ) -> Highly Volatile | G80: AAP | H80: INC | I80: AAP | J80: SAD | K80: SAD | M80: SAD | N80: 18.34 | O80: {=_xlfn.XLOOKUP(B80, 'Assembly Competitiveness'!$B$4:$B$120,'Assembly Competitiveness'!$O$4:$O$120, "-")} -> 21.863 | P80: {=_xlfn.XLOOKUP(B80,'Assembly Volatality'!$B$4:$B$120,'Assembly Volatality'!$L$4:$L$120, "-")} -> 51.29 | Q80: =ROUND(0.45*O80+0.4*P80+0.15*IF(H80<>K80,100,0),1) -> 45.4 | R80: SAD | S80: YES | T80: =IFS( AND(G80="AAP", OR(F80="Stronghold", F80="Lean")), "Defend", OR( AND(G80="AAP", OR(F80="Battleground", F80="Highly Volatile", F80="Opposition Lean")), AND(R80="AAP", OR(F80="Battleground", F80="Highly Volatile", F80="Opposition Lean")) ), "Battleground", OR(K80="AAP", M80="AAP", R80="AAP"), "Expand", TRUE, "Long Shot" ) -> Battleground | U80: =IFS( AND(G80="INC", OR(F80="Stronghold", F80="Lean")), "Defend", OR( AND(G80="INC", OR(F80="Battleground", F80="Highly Volatile", F80="Opposition Lean")), AND(R80="INC", OR(F80="Battleground", F80="Highly Volatile", F80="Opposition Lean")) ), "Battleground", OR(K80="INC", M80="INC", R80="INC"), "Expand", TRUE, "Long Shot" ) -> Long Shot | V80: =IFS( AND(G80="SAD", OR(F80="Stronghold", F80="Lean")), "Defend", OR( AND(G80="SAD", OR(F80="Battleground", F80="Highly Volatile", F80="Opposition Lean")), AND(R80="SAD", OR(F80="Battleground", F80="Highly Volatile", F80="Opposition Lean")) ), "Battleground", OR(K80="SAD", M80="SAD", R80="SAD"), "Expand", TRUE, "Long Shot" ) -> Battleground | W80: =IFS( AND(G80="BJP", OR(F80="Stronghold", F80="Lean")), "Defend", OR( AND(G80="BJP", OR(F80="Battleground", F80="Highly Volatile", F80="Opposition Lean")), AND(R80="BJP", OR(F80="Battleground", F80="Highly Volatile", F80="Opposition Lean")) ), "Battleground", OR(K80="BJP", M80="BJP", R80="BJP"), "Expand", TRUE, "Long Shot" ) -> Long Shot | X80: =IFS(K80="EMERGING", "YES", COUNTIFS(T80:W80, "<>Long Shot", T80:W80, "<>") >= 3, "YES", TRUE, "")
A81: 78 | B81: Guru Har Sahai | C81: Ferozepur | D81: Malwa | E81: Fauja Singh | F81: =IFS( OR(P81>=75, ((H81<>J81)+(J81<>I81)+(I81<>K81))>=3), "Highly Volatile", AND(COUNTIF(H81:K81, G81)+1>=4, O81<55, P81<65), "Stronghold", AND(COUNTIF(H81:K81, G81)+1>=3, O81<70, P81<75), "Lean", AND(R81<>G81, ((H81=R81)+(J81=R81)+(K81=R81))>=2, O81<60, P81<70), "Opposition Lean", TRUE, "Battleground" ) -> Highly Volatile | G81: AAP | H81: INC | I81: AAP | J81: SAD | K81: SAD | M81: SAD | N81: 7.61 | O81: {=_xlfn.XLOOKUP(B81, 'Assembly Competitiveness'!$B$4:$B$120,'Assembly Competitiveness'!$O$4:$O$120, "-")} -> 54.9855 | P81: {=_xlfn.XLOOKUP(B81,'Assembly Volatality'!$B$4:$B$120,'Assembly Volatality'!$L$4:$L$120, "-")} -> 49.52 | Q81: =ROUND(0.45*O81+0.4*P81+0.15*IF(H81<>K81,100,0),1) -> 59.6 | R81: SAD | S81: YES | T81: =IFS( AND(G81="AAP", OR(F81="Stronghold", F81="Lean")), "Defend", OR( AND(G81="AAP", OR(F81="Battleground", F81="Highly Volatile", F81="Opposition Lean")), AND(R81="AAP", OR(F81="Battleground", F81="Highly Volatile", F81="Opposition Lean")) ), "Battleground", OR(K81="AAP", M81="AAP", R81="AAP"), "Expand", TRUE, "Long Shot" ) -> Battleground | U81: =IFS( AND(G81="INC", OR(F81="Stronghold", F81="Lean")), "Defend", OR( AND(G81="INC", OR(F81="Battleground", F81="Highly Volatile", F81="Opposition Lean")), AND(R81="INC", OR(F81="Battleground", F81="Highly Volatile", F81="Opposition Lean")) ), "Battleground", OR(K81="INC", M81="INC", R81="INC"), "Expand", TRUE, "Long Shot" ) -> Long Shot | V81: =IFS( AND(G81="SAD", OR(F81="Stronghold", F81="Lean")), "Defend", OR( AND(G81="SAD", OR(F81="Battleground", F81="Highly Volatile", F81="Opposition Lean")), AND(R81="SAD", OR(F81="Battleground", F81="Highly Volatile", F81="Opposition Lean")) ), "Battleground", OR(K81="SAD", M81="SAD", R81="SAD"), "Expand", TRUE, "Long Shot" ) -> Battleground | W81: =IFS( AND(G81="BJP", OR(F81="Stronghold", F81="Lean")), "Defend", OR( AND(G81="BJP", OR(F81="Battleground", F81="Highly Volatile", F81="Opposition Lean")), AND(R81="BJP", OR(F81="Battleground", F81="Highly Volatile", F81="Opposition Lean")) ), "Battleground", OR(K81="BJP", M81="BJP", R81="BJP"), "Expand", TRUE, "Long Shot" ) -> Long Shot | X81: =IFS(K81="EMERGING", "YES", COUNTIFS(T81:W81, "<>Long Shot", T81:W81, "<>") >= 3, "YES", TRUE, "")
